Workbook
Name deal_project_name: Assumptions!$F$7
Name deal_city_state: Assumptions!$F$8
Name deal_analysis_start_date: Assumptions!$F$11
Name deal_hold_period_months: Assumptions!$E$28
Name deal_gross_sf: Assumptions!$F$12
Name deal_net_sf: Assumptions!$F$13
Name acq_purchase_price: Assumptions!$F$17
Name acq_closing_cost_pct: Assumptions!$E$18
Name acq_fee_pct: Assumptions!$F$19
Name acq_legal_costs: Assumptions!$F$21
Name acq_other_financing_fees: Assumptions!$F$23
Name ops_vacancy_pct: Assumptions!$P$7
Name ops_credit_loss_pct: Assumptions!$P$8
Name infl_other_revenue: Assumptions!$P$37
Name infl_expenses: Assumptions!$P$38
Name infl_taxes: Assumptions!$P$39
Name ops_mgmt_fee_pct_egi: Assumptions!$N$19
Name ops_insurance_annual: Assumptions!$N$20
Name ops_utilities_annual: Assumptions!$N$22
Name ops_rm_annual: Assumptions!$N$23
Name ops_security_annual: Assumptions!$N$25
Name ops_property_taxes_annual: Assumptions!$N$27
Name ops_other_expense1_annual: Assumptions!$N$28
Name ops_capex_reserves_psf_yr: Assumptions!$N$33
Name debt_acq_ltv_max: Assumptions!$AA$9
Name debt_acq_fund_reno_pct: Assumptions!$AA$10
Name debt_acq_fund_ti_lc_pct: Assumptions!$AA$11
Name debt_acq_fund_capex_pct: Assumptions!$AA$12
Name debt_acq_orig_fee_pct: Assumptions!$Z$21
Name debt_acq_fixed_interest_flag: Assumptions!$Z$17
Name debt_acq_fixed_rate_or_spread: Assumptions!$AA$18
Name debt_acq_sofr_cap: Assumptions!$AA$19
Name debt_acq_sofr_floor: Assumptions!$AA$20
Name debt_acq_io_months: Assumptions!$AA$23
Name debt_acq_amort_years: Assumptions!$AA$24
Name exit_cap_rate: Assumptions!$F$29
Name exit_sale_cost_pct: Assumptions!$F$33
Name exit_date: Assumptions!$F$28
Name wf_lp_pct: Assumptions!$P$43
Name wf_gp_pct: Assumptions!$P$44
Name wf_h1_irr: Assumptions!$P$45
Name wf_h1_promote: Assumptions!$P$46
Name reno_prelim_hard_amount: 'Renovation Budget'!$B$22
Name reno_prelim_soft_amount: 'Renovation Budget'!$B$30
Name reno_hard_cont_pct: 'Renovation Budget'!$B$21
Name reno_soft_cont_pct: 'Renovation Budget'!$B$29
Name out_template_id: '_TEMPLATE_META'!$B$1
Name out_template_version: '_TEMPLATE_META'!$B$2
Name out_contract_version: '_TEMPLATE_META'!$B$3
Name out_check_status: 'Error Check'!$B$110
Name out_check_error_count: 'Error Check'!$B$111
Name out_check_sources_equal_uses: 'Error Check'!$B$112
Name out_check_waterfall_ties: 'Error Check'!$B$113
Name out_check_cf_ties: 'Error Check'!$B$114
Name out_unlevered_irr: 'Returns Summary'!$B$8
Name out_unlevered_peak_capital: 'Returns Summary'!$B$9
Name out_unlevered_net_profit: 'Returns Summary'!$B$10
Name out_unlevered_multiple: 'Returns Summary'!$B$11
Name out_levered_irr: 'Returns Summary'!$B$12
Name out_levered_peak_equity: 'Returns Summary'!$B$13

Sheet _TEMPLATE_META
A1: Template_ID | B1: IND_ACQ
A2: Template_Version | B2: 1.0.0
A3: Contract_Version | B3: IND_ACQ_V1
A4: Generated_On | B4: 2025-12-21T21:38:18Z

Sheet Assumptions
A1: Project Name
A2: City, State | AD2: 1257437
AD3: 1651217
A4: Assumptions | AD4: 11254064
AD5: 11464581
A6: General Property | H6: Operating Assumptions | S6: Acquisition Debt Assumptions
A7: Project Name | F7: Project Name | H7: General Vacancy (% Tenant Rev) | P7: 0.05 | S7: First Mortgage Financing
A8: Building City, State | F8: City, State | H8: Credit Loss (% Tenant Rev) | P8: 0 | S8: Cash Flow Sweep? | Z8: No
A9: General Partner | F9: General Partner | S9: Loan to Value - Acquisition | AA9: 0.6
A10: Limited Partner | F10: Limited Partner | H10: Revenue Assumptions | S10: % of Renovation Costs Funded | AA10: 0.6 | AD10: 0.01
A11: Analysis Start Month | E11: 0 | F11: 45658 | H11: Parking Revenue (Annual) | N11: $/NSF | P11: 0 | S11: % of TI/LC Funded | AA11: 0.6 | AD11: 6531000
A12: Gross SF | F12: 150000 | H12: Other Revenue 1 (Annual) | N12: $/NSF | P12: 0 | S12: % of CapEx Funded | AA12: 0.6
A13: Net SF | F13: 125000 | H13: Other Revenue 2 (Annual) | N13: $/NSF | P13: 0 | S13: Loan Amount - Acquisition | AA13: =ROUND(AA9*($F$24 + $AD$10*($AD$11*AA10 + $Z15))/(1-AA9*$AD$10),0)
A14: Month Stabilized | F14: Month 1 | H14: Other Revenue 3 (Annual) | N14: $/NSF | P14: 0 | S14: Loan Amount - Renovation | AA14: =ROUND($AD$11*AA10,0)
H15: Other Revenue 4 (Annual) | N15: $/NSF | P15: 0 | S15: Loan Amount - TI/LC/CapEx Holdback | Z15: 300000 | AA15: =Z15
A16: Acquisition Assumptions | H16: Other Revenue 5 (Annual) | N16: $/NSF | P16: 0 | S16: Loan Proceeds | AA16: =ROUND(AA13+AA14+AA15,0)
A17: Building Acquisition Price | F17: 12000000 | S17: Fixed Interest Rate? | Z17: Y
A18: Closing Costs | E18: 0.03 | F18: =ROUND($F$17*$E$18,0) | H18: Expense Assumptions | S18: Fixed Rate/Spread over SOFR | AA18: 0.055
A19: Partner Acquisition Fee | F19: 0 | H19: Management Fee (Annual) | N19: % EGI | P19: 0.015 | S19: SOFR Cap | AA19: 0.08
A20: Required Reserves | F20: 0 | H20: Insurance (Annual) | N20: Fixed | P20: 10080 | S20: SOFR Floor | AA20: 0
A21: Legal Costs | F21: 0 | H21: G&A (Annual) | N21: Fixed | P21: 0 | S21: Financing Fee | Z21: 0.01 | AA21: =ROUND($Z21*$AA16,0)
A22: Financing Fees - Transfer Fee | F22: 0 | H22: Utilities (Annual) | N22: Fixed | P22: 15862 | S22: Interest Calculation | Z22: 30/360
A23: Other Financing Fees | F23: 0 | H23: R&M (Annual) | N23: Fixed | P23: 16897 | S23: I/O Period (Months) | AA23: -
A24: All In Acquisition Costs | F24: =ROUND($F$17+$F$18+$F$19+$F$20+$F$21+$F$22+$F$23,0) | H24: Cleaning/Janitorial Services (Annual) | N24: Fixed | P24: 0 | S24: Amortization (Years) | AA24: 30
A25: Going In Cap Rate | F25: =$AD$2/$F$17 | H25: Security (Annual) | N25: Fixed | P25: 5000 | S25: Acquisition Loan Payoff Month | Z25: =EDATE($F$11,36) | AA25: Month 36
H26: Non-Recoverable OpEx (Annual) | N26: Fixed | P26: 0 | S26: Exit Fee | AA26: 0
A27: Exit Assumptions | H27: Property Taxes (Fixed) | N27: Fixed | P27: 353650
A28: Sale Month / Year / Date | E28: 60 | F28: =EDATE($F$11,$E$28) | H28: Other Expense 1 (Annual) | N28: $/NSF | P28: 0.4 | S28: Refi Debt Assumptions
A29: Exit Cap Rate Assumption | F29: 0.065 | H29: Other Expense 2 (Annual) | N29: $/NSF | P29: 0 | S29: Conversion Method (LTV/Acquisition) | Z29: Acquisition
A30: NOI at Exit | E30: Forward 12 | F30: 1815948 | H30: Other Expense 3 (Annual) | N30: $/NSF | P30: 0 | S30: Convert? | Z30: Y
A31: Gross Sale Proceeds | F31: =ROUND($F$30/$F$29,0) | H31: Other Expense 4 (Annual) | N31: $/NSF | P31: 0 | S31: Interest Calculation | Z31: 30/360
A32: Price per SF (Remeasured) | F32: =ROUND($F$31/$F$13,2) | H32: Other Expense 5 (Annual) | N32: $/NSF | P32: 0 | S32: Refi Debt Start Month | Z32: =EDATE($F$11,36) | AA32: Month 36
A33: Transaction Costs | F33: 0.01 | H33: Non-Operating Expenses (Annual) | N33: $/NSF | P33: 0 | S33: Refi Debt Payoff Month | Z33: =EDATE($F$11,$E$28) | AA33: ="Month "&$E$28
A34: Net Sales Proceeds | F34: =ROUND($F$31*(1-$F$33),0) | H34: CapEx Reserves (Annual) | N34: $/NSF | P34: 0.1 | S34: I/O Period (Months) | AA34: -
A35: Net Price per SF (Remeasured) | F35: =ROUND($F$34/$F$13,2) | S35: Cap Rate For LTV | AA35: 0.07
H36: Inflation Assumptions | S36: Loan to Value | AA36: 0.7
H37: Other Revenue Inflation Rate | P37: 0.03 | S37: % of TI/LC Funded | AA37: 0.7
H38: Expense Inflation Rate | P38: 0.03 | S38: % of CapEx Funded | AA38: 0.7
H39: Tax Inflation Rate | P39: 0.03 | S39: Amortization (Years) | AA39: 30
S40: NOI at Debt Acquisition | AA40: =$AD$3
H41: Waterfall Structure | S41: Loan Amount - Refi | AA41: =$AD$4
P42: Promote | S42: Loan Amount - TI/LC/CapEx Holdback | Z42: 800000 | AA42: =MIN($Z42,$AD$5-$AA41-1)
H43: Limited Partner Equity % | P43: 0.9 | S43: Max Proceeds | AA43: =$AD$5
H44: General Partner Equity % | P44: 0.1 | S44: Initial Commitment Fee | AA44: 0.01
H45: First Promote Hurdle | P45: 0.08 | S45: Exit Fee | AA45: 0
H46: Promote After 1st Hurdle | P46: 0.12 | S46: Fixed Interest Rate? | Z46: Y
H47: Second Promote Hurdle | N47: Not Applicable | S47: Fixed Rate/Spread over SOFR | AA47: 0.05
H48: Promote After 2nd Hurdle | N48: Not Applicable | S48: SOFR Cap | AA48: 0.08
H49: Third Promote Hurdle | N49: Not Applicable | S49: SOFR Floor | AA49: 0
H50: Promote After 3rd Hurdle | N50: Not Applicable
S51: Mezzanine Loan Assumptions
A52: Below-the-Line Capital Summary & Additional Capital Input | S52: Mezzanine Debt? | Z52: N
B53: Tenant Improvements | F53: Leasing Commissions | J53: CapEx Reserves | M53: Other CapEx (Not Incl. in Reno. Costs) | P53: Total Capital
A54: Year 1 | B54: 875000 | F54: 534364 | J54: 12500 | M54: 0 | P54: =SUM(B54,F54,J54,M54)
A55: Year 2 | B55: 0 | F55: 0 | J55: 12875 | M55: 0 | P55: =SUM(B55,F55,J55,M55)
A56: Year 3 | B56: 385000 | F56: 276623 | J56: 13261 | M56: 0 | P56: =SUM(B56,F56,J56,M56)
A57: Year 4 | B57: 175000 | F57: 125738 | J57: 13659 | M57: 0 | P57: =SUM(B57,F57,J57,M57)
A58: Year 5 | B58: 0 | F58: 0 | J58: 14069 | M58: 0 | P58: =SUM(B58,F58,J58,M58)
A59: Total - First 5 Years | B59: =SUM(B54:B58) | F59: =SUM(F54:F58) | J59: =SUM(J54:J58) | M59: =SUM(M54:M58) | P59: =SUM(P54:P58)
A61: Sensitivities - Levered IRR/Levered Multiple
A62: Exit Month | F62: Exit Cap Rate | S62: 10 Year Treasury
F63: 0.07 | H63: 0.0675 | J63: 0.065 | L63: 0.0625 | N63: 0.06 | S63: Use Treasury? | Z63: N
D64: Month 48 | F64: 20.4% / 2.0x | H64: 22.3% / 2.1x | J64: 24.1% / 2.3x | L64: 26.1% / 2.4x | N64: 28.1% / 2.5x
D65: Month 54 | F65: 17.2% / 1.9x | H65: 18.7% / 2.1x | J65: 20.3% / 2.2x | L65: 22.0% / 2.3x | N65: 23.7% / 2.4x
D66: Month 60 | F66: 17.2% / 2.1x | H66: 18.5% / 2.2x | J66: 19.9% / 2.3x | L66: 21.3% / 2.5x | N66: 22.8% / 2.6x
D67: Month 66 | F67: 18.7% / 2.4x | H67: 19.8% / 2.5x | J67: 21.0% / 2.6x | L67: 22.2% / 2.8x | N67: 23.5% / 2.9x
D68: Month 72 | F68: 18.3% / 2.5x | H68: 19.3% / 2.6x | J68: 20.4% / 2.8x | L68: 21.4% / 2.9x | N68: 22.6% / 3.1x
A72: Checks (should be 0)
A73: Sources – Uses (Investment Level) | F73: ='Model Outputs'!$E$13-'Model Outputs'!$E$20
A74: LP % + GP % - 100% | F74: =$P$43+$P$44-1
A75: Acq Loan Proceeds tie-out | F75: =$AA$16-($AA$13+$AA$14+$AA$15)
A76: Net Sales Proceeds tie-out | F76: =$F$34-ROUND($F$31*(1-$F$33),0)
A77: Below-the-line Total Capital tie-out | F77: =$P$59-($B$59+$F$59+$J$59+$M$59)

Sheet Rent Roll
A1: Project Name | AA1: =SUM(B36:B55)
A2: City, State
A4: Rent Roll
A6: Rent Roll - In-Place / Initial Lease Up
A8: Tenant | B8: Sq Ft | C8: % Total | D8: Current Annual Rent PSF | E8: Annual Step Calculation | F8: Annual Step Amounts | G8: Lease Start | H8: Lease End | I8: Lease Type | J8: Stop Amount (Annual) | K8: Free Rent | L8: Tenant Improvements | M8: Leasing Commissions Calculation | N8: Leasing Commissions | O8: Comments
A9: Beignet Station | B9: 25000 | C9: =IF(B9="","",B9/$B$30) | D9: 13 | E9: % Bump | F9: 0.03 | G9: 45689 | H9: 46812 | I9: NNN | K9: 0 | L9: 7 | M9: $/SF | N9: 6
A10: Orange and Blue | B10: 25000 | C10: =IF(B10="","",B10/$B$30) | D10: 13 | E10: % Bump | F10: 0.03 | G10: 45689 | H10: 49368 | I10: NNN | K10: 3 | L10: 7 | M10: % of Rental Revenue | N10: 0.06
A11: Specific Statics | B11: 30000 | C11: =IF(B11="","",B11/$B$30) | D11: 13 | E11: % Bump | F11: 0.03 | G11: 45689 | H11: 46446 | I11: NNN | K11: 3 | L11: 7 | M11: % of Rental Revenue | N11: 0.06
A12: AZ Salt & Daughter | B12: 25000 | C12: =IF(B12="","",B12/$B$30) | D12: 13 | E12: % Bump | F12: 0.03 | G12: 45689 | H12: 46446 | I12: NNN | K12: 2 | L12: 7 | M12: % of Rental Revenue | N12: 0.06
A13: Moyra's Aviation | B13: 20000 | C13: =IF(B13="","",B13/$B$30) | D13: 13 | E13: % Bump | F13: 0.03 | G13: 45689 | H13: 47542 | I13: NNN | K13: 2 | L13: 7 | M13: % of Rental Revenue | N13: 0.06
C14: =IF(B14="","",B14/$B$30)
C15: =IF(B15="","",B15/$B$30)
C16: =IF(B16="","",B16/$B$30)
C17: =IF(B17="","",B17/$B$30)
C18: =IF(B18="","",B18/$B$30)
C19: =IF(B19="","",B19/$B$30)
C20: =IF(B20="","",B20/$B$30)
C21: =IF(B21="","",B21/$B$30)
C22: =IF(B22="","",B22/$B$30)
C23: =IF(B23="","",B23/$B$30)
C24: =IF(B24="","",B24/$B$30)
C25: =IF(B25="","",B25/$B$30)
... C28: =IF(B28="","",B28/$B$30)
A29: Vacant Space | B29: 0 | C29: N/A | D29: N/A | F29: N/A | G29: N/A | H29: N/A | K29: N/A | L29: N/A | N29: N/A
A30: Project Name Total: | B30: =SUM(B9:B29) | C30: =SUM(C9:C29)
A31: Project Name Average: | B31: =COUNTIF(A9:A28,"<>") | D31: =IFERROR(AVERAGEIF(D9:D28,">0"),"") | G31: =IFERROR(AVERAGE(G9:G28),"") | H31: =IFERROR(EDATE(AVERAGE(H9:H28),-1),"") | K31: =IFERROR(AVERAGEIF(K9:K28,">=0"),"") | L31: =IFERROR(AVERAGEIF(L9:L28,">0"),"")
A33: Rent Roll - Market Rollover
A35: Tenant | B35: Sq Ft | C35: % Total | D35: Market Annual Rent PSF | E35: Annual Step Calculation | F35: Annual Step Amounts | G35: Lease Start | H35: Lease End | I35: Lease Type | J35: Stop Amount (Annual) | K35: Free Rent | L35: Tenant Improvements | M35: Leasing Commissions Calculation | N35: Leasing Commissions | O35: Comments
A36: Beignet Station | B36: 25000 | C36: =IF(B36="","",B36/$AA$1) | D36: 16 | E36: % Bump | F36: 0.03 | G36: 46905 | H36: 48760 | I36: NNN | K36: 2 | L36: 7 | M36: % of Rental Revenue | N36: 0.06
A37: Rapunzel | B37: 25000 | C37: =IF(B37="","",B37/$AA$1) | D37: 19 | E37: % Bump | F37: 0.03 | G37: 49461 | H37: 51317 | I37: NNN | K37: 2 | L37: 7 | M37: % of Rental Revenue | N37: 0.06
A38: Specific Statics | B38: 30000 | C38: =IF(B38="","",B38/$AA$1) | D38: 16 | E38: % Bump | F38: 0.03 | G38: 46539 | H38: 48395 | I38: NNN | K38: 2 | L38: 7 | M38: % of Rental Revenue | N38: 0.06
A39: HSC Homes | B39: 25000 | C39: =IF(B39="","",B39/$AA$1) | D39: 16 | E39: % Bump | F39: 0.03 | G39: 46539 | H39: 48395 | I39: NNN | K39: 2 | L39: 7 | M39: % of Rental Revenue | N39: 0.06
A40: PG Technologies | B40: 20000 | C40: =IF(B40="","",B40/$AA$1) | D40: 16 | E40: % Bump | F40: 0.03 | G40: 47635 | H40: 49490 | I40: NNN | K40: 2 | L40: 7 | M40: % of Rental Revenue | N40: 0.06
C41: =IF(B41="","",B41/$AA$1)
C42: =IF(B42="","",B42/$AA$1)
C43: =IF(B43="","",B43/$AA$1)
C44: =IF(B44="","",B44/$AA$1)
C45: =IF(B45="","",B45/$AA$1)
C46: =IF(B46="","",B46/$AA$1)
C47: =IF(B47="","",B47/$AA$1)
C48: =IF(B48="","",B48/$AA$1)
C49: =IF(B49="","",B49/$AA$1)
C50: =IF(B50="","",B50/$AA$1)
C51: =IF(B51="","",B51/$AA$1)
C52: =IF(B52="","",B52/$AA$1)
... C55: =IF(B55="","",B55/$AA$1)
A56: Project Name Average: | D56: =IFERROR(AVERAGEIF(D36:D55,">0"),"") | G56: =IFERROR(EDATE(AVERAGE(G36:G55),-1),"") | H56: =IFERROR(EDATE(AVERAGE(H36:H55),-1),"")
Z60: 0

Sheet Renovation Budget
A1: Project Name
A2: City, State
A4: Renovation Budget
A6: Renovation Budget - Project Name - City, State
A7: Hard Costs
A8: Category | B8: Cost Basis | C8: Total Cost | D8: $/ nsf | E8: $/ gsf | F8: Start Date | G8: Duration | H8: End Date | I8: Duration (mo)
A9: Shell Industrial | B9: Fixed Amount | C9: 0 | D9: =IFERROR(C9/Assumptions!$F$13,0) | E9: =IFERROR(C9/Assumptions!$F$12,0) | F9: =Assumptions!$F$11 | G9: 4 | H9: =EOMONTH(EDATE(F9,G9-1),0) | I9: =G9
A10: Sitework | B10: Fixed Amount | C10: 0 | D10: =IFERROR(C10/Assumptions!$F$13,0) | E10: =IFERROR(C10/Assumptions!$F$12,0) | F10: =Assumptions!$F$11 | G10: 12 | H10: =EOMONTH(EDATE(F10,G10-1),0) | I10: =G10
A11: Landscape (Ground Level) | B11: Fixed Amount | C11: 0 | D11: =IFERROR(C11/Assumptions!$F$13,0) | E11: =IFERROR(C11/Assumptions!$F$12,0) | F11: =Assumptions!$F$11 | G11: 12 | H11: =EOMONTH(EDATE(F11,G11-1),0) | I11: =G11
A12: Landscape (Amenity + Penthouse) | B12: Fixed Amount | C12: 0 | D12: =IFERROR(C12/Assumptions!$F$13,0) | E12: =IFERROR(C12/Assumptions!$F$12,0) | F12: =Assumptions!$F$11 | G12: 12 | H12: =EOMONTH(EDATE(F12,G12-1),0) | I12: =G12
A13: Improvements | B13: Fixed Amount | C13: 0 | D13: =IFERROR(C13/Assumptions!$F$13,0) | E13: =IFERROR(C13/Assumptions!$F$12,0) | F13: =Assumptions!$F$11 | G13: 12 | H13: =EOMONTH(EDATE(F13,G13-1),0) | I13: =G13
A14: Garage - Above Grade | B14: Fixed Amount | C14: 0 | D14: =IFERROR(C14/Assumptions!$F$13,0) | E14: =IFERROR(C14/Assumptions!$F$12,0) | F14: =Assumptions!$F$11 | G14: 12 | H14: =EOMONTH(EDATE(F14,G14-1),0) | I14: =G14
A15: Thermal and Moisture Protection | B15: Fixed Amount | C15: 0 | D15: =IFERROR(C15/Assumptions!$F$13,0) | E15: =IFERROR(C15/Assumptions!$F$12,0) | F15: =Assumptions!$F$11 | G15: 12 | H15: =EOMONTH(EDATE(F15,G15-1),0) | I15: =G15
A16: Doors and Windows | B16: Fixed Amount | C16: 0 | D16: =IFERROR(C16/Assumptions!$F$13,0) | E16: =IFERROR(C16/Assumptions!$F$12,0) | F16: =Assumptions!$F$11 | G16: 12 | H16: =EOMONTH(EDATE(F16,G16-1),0) | I16: =G16
A17: Finishes | B17: Fixed Amount | C17: 0 | D17: =IFERROR(C17/Assumptions!$F$13,0) | E17: =IFERROR(C17/Assumptions!$F$12,0) | F17: =Assumptions!$F$11 | G17: 12 | H17: =EOMONTH(EDATE(F17,G17-1),0) | I17: =G17
A18: Special Ties | B18: Fixed Amount | C18: 0 | D18: =IFERROR(C18/Assumptions!$F$13,0) | E18: =IFERROR(C18/Assumptions!$F$12,0) | F18: =Assumptions!$F$11 | G18: 12 | H18: =EOMONTH(EDATE(F18,G18-1),0) | I18: =G18
A19: Equipment | B19: Fixed Amount | C19: 0 | D19: =IFERROR(C19/Assumptions!$F$13,0) | E19: =IFERROR(C19/Assumptions!$F$12,0) | F19: =Assumptions!$F$11 | G19: 12 | H19: =EOMONTH(EDATE(F19,G19-1),0) | I19: =G19
A20: Furnishings | B20: Fixed Amount | C20: 0 | D20: =IFERROR(C20/Assumptions!$F$13,0) | E20: =IFERROR(C20/Assumptions!$F$12,0) | F20: =Assumptions!$F$11 | G20: 12 | H20: =EOMONTH(EDATE(F20,G20-1),0) | I20: =G20
A21: Hard Cost Contingency | B21: % of Hard Costs | C21: =ROUND(D21*(SUM($C$9:$C$20)+$C$22),0) | D21: 0 | E21: =IFERROR(C21/Assumptions!$F$12,0) | F21: =Assumptions!$F$11 | G21: 12 | H21: =EOMONTH(EDATE(F21,G21-1),0) | I21: =G21
A22: Preliminary Renovation Costs | B22: $/NSF | C22: =ROUND(D22*Assumptions!$F$13,0) | D22: 30 | E22: =IFERROR(C22/Assumptions!$F$12,0) | F22: =Assumptions!$F$11 | G22: 12 | H22: =EOMONTH(EDATE(F22,G22-1),0) | I22: =G22
A23: Subtotal- Hard Costs | C23: =SUM($C$9:$C$22) | D23: =IFERROR(C23/Assumptions!$F$13,0) | E23: =IFERROR(C23/Assumptions!$F$12,0)
A25: Soft Costs
A26: Category | B26: Cost Basis | C26: Total Cost | D26: $/ nsf | E26: $/ gsf | F26: Start Date | G26: Duration | H26: End Date | I26: Duration (mo)
A27: Acquisition Management Fee | B27: Fixed Amount | C27: 100000 | D27: =IFERROR(C27/Assumptions!$F$13,0) | E27: =IFERROR(C27/Assumptions!$F$12,0) | F27: =Assumptions!$F$11 | G27: 12 | H27: =EOMONTH(EDATE(F27,G27-1),0) | I27: =G27
A28: Bury Power Lines (Austin Energy) | B28: Fixed Amount | C28: 100000 | D28: =IFERROR(C28/Assumptions!$F$13,0) | E28: =IFERROR(C28/Assumptions!$F$12,0) | F28: =Assumptions!$F$11 | G28: 12 | H28: =EOMONTH(EDATE(F28,G28-1),0) | I28: =G28
A29: Soft Cost Contingency | B29: % of Soft Costs | C29: =ROUND(D29*(SUM($C$27:$C$28)+$C$30),0) | D29: 0.03 | E29: =IFERROR(C29/Assumptions!$F$12,0) | F29: =Assumptions!$F$11 | G29: 12 | H29: =EOMONTH(EDATE(F29,G29-1),0) | I29: =G29
A30: Preliminary Soft Costs | B30: $/NSF | C30: =ROUND(D30*Assumptions!$F$13,0) | D30: 20 | E30: =IFERROR(C30/Assumptions!$F$12,0) | F30: =Assumptions!$F$11 | G30: 12 | H30: =EOMONTH(EDATE(F30,G30-1),0) | I30: =G30
A31: Operating Deficit | B31: In Use | C31: 0 | D31: =IFERROR(C31/Assumptions!$F$13,0) | E31: =IFERROR(C31/Assumptions!$F$12,0) | F31: =Assumptions!$F$11 | G31: 1 | H31: =EOMONTH(EDATE(F31,G31-1),0) | I31: =G31
A32: Subtotal- Soft Costs | C32: =SUM($C$27:$C$31) | D32: =IFERROR(C32/Assumptions!$F$13,0) | E32: =IFERROR(C32/Assumptions!$F$12,0)
A34: Subtotal Renovation Costs | C34: =C23+C32 | D34: =IFERROR(C34/Assumptions!$F$13,0)
A36: LTV Debt Analysis | F36: Loan & Equity Amount Summary
A37: Acquisition Cost | B37: =Assumptions!$F$24 | C37: LTV - Acquisition | D37: =Assumptions!$AA$9 | F37: Loan Amount | G37: =Assumptions!$AA$16
A38: Financing Fee | B38: =Assumptions!$AA$21 | C38: LTV - Renovations | D38: =Assumptions!$AA$10 | F38: Equity Amount | G38: =B44-G37
A39: Total Renovation Budget | B39: =B37+B38+C34 | C39: LTV - TI/LC | D39: =Assumptions!$AA$11 | F39: Mezzanine Amount | G39: =B43
A40: Tenant Improvements during Acquisition Loan | B40: 1260000 | C40: LTV - CapEx | D40: =Assumptions!$AA$12 | F40: Total Cost | G40: =B44
A41: Leasing Commissions during Acquisition Loan | B41: 810987 | F41: Debt for Acquisition | G41: =Assumptions!$AA$13
A42: CapEx during Acquisition Loan | B42: 0 | F42: Debt for Renovations | G42: =Assumptions!$AA$14
A43: Mezzanine Amount | B43: 0 | F43: Debt for TI/LCs/Capex | G43: =Assumptions!$AA$15
A44: Total Cost | B44: =SUM(B39:B43) | F44: Total Acquisition Loan | G44: =Assumptions!$AA$16
F45: Mezzanine | G45: =B43
F46: Equity | G46: =G38

Sheet Monthly CF
A1: Project Name | B1: =Assumptions!$F$7
A2: City, State | B2: =Assumptions!$F$8
A4: Monthly CF
A6: Circular Break | C6: No
B7: Investment Held? | D7: =IF(D$11<=Assumptions!$E$28,1,0) | E7: =IF(E$11<=Assumptions!$E$28,1,0) | F7: =IF(F$11<=Assumptions!$E$28,1,0) | G7: =IF(G$11<=Assumptions!$E$28,1,0) | H7: =IF(H$11<=Assumptions!$E$28,1,0) | I7: =IF(I$11<=Assumptions!$E$28,1,0) | J7: =IF(J$11<=Assumptions!$E$28,1,0) | K7: =IF(K$11<=Assumptions!$E$28,1,0) | ... DT7: =IF(DT$11<=Assumptions!$E$28,1,0)
B8: Year | D8: =YEAR(D$12) | E8: =YEAR(E$12) | F8: =YEAR(F$12) | G8: =YEAR(G$12) | H8: =YEAR(H$12) | I8: =YEAR(I$12) | J8: =YEAR(J$12) | K8: =YEAR(K$12) | ... DT8: =YEAR(DT$12)
B9: Year # | D9: =IF(D$11=0,0,INT((D$11-1)/12)+1) | E9: =IF(E$11=0,0,INT((E$11-1)/12)+1) | F9: =IF(F$11=0,0,INT((F$11-1)/12)+1) | G9: =IF(G$11=0,0,INT((G$11-1)/12)+1) | H9: =IF(H$11=0,0,INT((H$11-1)/12)+1) | I9: =IF(I$11=0,0,INT((I$11-1)/12)+1) | J9: =IF(J$11=0,0,INT((J$11-1)/12)+1) | K9: =IF(K$11=0,0,INT((K$11-1)/12)+1) | ... DT9: =IF(DT$11=0,0,INT((DT$11-1)/12)+1)
B10: Quarter # | D10: =IF(D$11=0,0,INT((D$11-1)/3)+1) | E10: =IF(E$11=0,0,INT((E$11-1)/3)+1) | F10: =IF(F$11=0,0,INT((F$11-1)/3)+1) | G10: =IF(G$11=0,0,INT((G$11-1)/3)+1) | H10: =IF(H$11=0,0,INT((H$11-1)/3)+1) | I10: =IF(I$11=0,0,INT((I$11-1)/3)+1) | J10: =IF(J$11=0,0,INT((J$11-1)/3)+1) | K10: =IF(K$11=0,0,INT((K$11-1)/3)+1) | ... DT10: =IF(DT$11=0,0,INT((DT$11-1)/3)+1)
B11: Month | D11: 0 | E11: 1 | F11: 2 | G11: 3 | H11: 4 | I11: 5 | J11: 6 | K11: 7 | L11: 8 | M11: 9 | N11: 10 | O11: 11 | P11: 12 | Q11: 13 | R11: 14 | S11: 15 | T11: 16 | U11: 17 | V11: 18 | W11: 19 | X11: 20 | Y11: 21 | Z11: 22 | AA11: 23 | AB11: 24 | AC11: 25 | AD11: 26 | AE11: 27 | AF11: 28 | AG11: 29 | AH11: 30 | AI11: 31 | AJ11: 32 | AK11: 33 | AL11: 34 | AM11: 35 | AN11: 36 | AO11: 37 | AP11: 38 | AQ11: 39 | AR11: 40 | AS11: 41 | AT11: 42 | AU11: 43 | AV11: 44 | AW11: 45 | AX11: 46 | AY11: 47 | AZ11: 48 | BA11: 49 | BB11: 50 | BC11: 51 | BD11: 52 | BE11: 53 | BF11: 54 | BG11: 55 | BH11: 56 | BI11: 57 | BJ11: 58 | BK11: 59 | BL11: 60 | BM11: 61 | BN11: 62 | BO11: 63 | BP11: 64 | BQ11: 65 | BR11: 66 | BS11: 67 | BT11: 68 | BU11: 69 | BV11: 70 | BW11: 71 | BX11: 72 | BY11: 73 | BZ11: 74 | CA11: 75 | CB11: 76 | CC11: 77 | CD11: 78 | CE11: 79 | CF11: 80 | CG11: 81 | CH11: 82 | CI11: 83 | CJ11: 84 | CK11: 85 | CL11: 86 | CM11: 87 | CN11: 88 | CO11: 89 | CP11: 90 | CQ11: 91 | CR11: 92 | CS11: 93 | CT11: 94 | CU11: 95 | CV11: 96 | CW11: 97 | CX11: 98 | CY11: 99 | CZ11: 100 | DA11: 101 | DB11: 102 | DC11: 103 | DD11: 104 | DE11: 105 | DF11: 106 | DG11: 107 | DH11: 108 | DI11: 109 | DJ11: 110 | DK11: 111 | DL11: 112 | DM11: 113 | DN11: 114 | DO11: 115 | DP11: 116 | DQ11: 117 | DR11: 118 | DS11: 119 | DT11: 120
A12: Date | C12: TOTAL | D12: =EDATE(Assumptions!$F$11,0) | E12: =EDATE(Assumptions!$F$11,1) | F12: =EDATE(Assumptions!$F$11,2) | G12: =EDATE(Assumptions!$F$11,3) | H12: =EDATE(Assumptions!$F$11,4) | I12: =EDATE(Assumptions!$F$11,5) | J12: =EDATE(Assumptions!$F$11,6) | K12: =EDATE(Assumptions!$F$11,7) | L12: =EDATE(Assumptions!$F$11,8) | M12: =EDATE(Assumptions!$F$11,9) | N12: =EDATE(Assumptions!$F$11,10) | O12: =EDATE(Assumptions!$F$11,11) | P12: =EDATE(Assumptions!$F$11,12) | Q12: =EDATE(Assumptions!$F$11,13) | R12: =EDATE(Assumptions!$F$11,14) | S12: =EDATE(Assumptions!$F$11,15) | T12: =EDATE(Assumptions!$F$11,16) | U12: =EDATE(Assumptions!$F$11,17) | V12: =EDATE(Assumptions!$F$11,18) | W12: =EDATE(Assumptions!$F$11,19) | X12: =EDATE(Assumptions!$F$11,20) | Y12: =EDATE(Assumptions!$F$11,21) | Z12: =EDATE(Assumptions!$F$11,22) | AA12: =EDATE(Assumptions!$F$11,23) | AB12: =EDATE(Assumptions!$F$11,24) | AC12: =EDATE(Assumptions!$F$11,25) | AD12: =EDATE(Assumptions!$F$11,26) | AE12: =EDATE(Assumptions!$F$11,27) | AF12: =EDATE(Assumptions!$F$11,28) | AG12: =EDATE(Assumptions!$F$11,29) | AH12: =EDATE(Assumptions!$F$11,30) | AI12: =EDATE(Assumptions!$F$11,31) | AJ12: =EDATE(Assumptions!$F$11,32) | AK12: =EDATE(Assumptions!$F$11,33) | AL12: =EDATE(Assumptions!$F$11,34) | AM12: =EDATE(Assumptions!$F$11,35) | AN12: =EDATE(Assumptions!$F$11,36) | AO12: =EDATE(Assumptions!$F$11,37) | AP12: =EDATE(Assumptions!$F$11,38) | AQ12: =EDATE(Assumptions!$F$11,39) | AR12: =EDATE(Assumptions!$F$11,40) | AS12: =EDATE(Assumptions!$F$11,41) | AT12: =EDATE(Assumptions!$F$11,42) | AU12: =EDATE(Assumptions!$F$11,43) | AV12: =EDATE(Assumptions!$F$11,44) | AW12: =EDATE(Assumptions!$F$11,45) | AX12: =EDATE(Assumptions!$F$11,46) | AY12: =EDATE(Assumptions!$F$11,47) | AZ12: =EDATE(Assumptions!$F$11,48) | BA12: =EDATE(Assumptions!$F$11,49) | BB12: =EDATE(Assumptions!$F$11,50) | BC12: =EDATE(Assumptions!$F$11,51) | BD12: =EDATE(Assumptions!$F$11,52) | BE12: =EDATE(Assumptions!$F$11,53) | BF12: =EDATE(Assumptions!$F$11,54) | BG12: =EDATE(Assumptions!$F$11,55) | BH12: =EDATE(Assumptions!$F$11,56) | BI12: =EDATE(Assumptions!$F$11,57) | BJ12: =EDATE(Assumptions!$F$11,58) | BK12: =EDATE(Assumptions!$F$11,59) | BL12: =EDATE(Assumptions!$F$11,60) | BM12: =EDATE(Assumptions!$F$11,61) | BN12: =EDATE(Assumptions!$F$11,62) | BO12: =EDATE(Assumptions!$F$11,63) | BP12: =EDATE(Assumptions!$F$11,64) | BQ12: =EDATE(Assumptions!$F$11,65) | BR12: =EDATE(Assumptions!$F$11,66) | BS12: =EDATE(Assumptions!$F$11,67) | BT12: =EDATE(Assumptions!$F$11,68) | BU12: =EDATE(Assumptions!$F$11,69) | BV12: =EDATE(Assumptions!$F$11,70) | BW12: =EDATE(Assumptions!$F$11,71) | BX12: =EDATE(Assumptions!$F$11,72) | BY12: =EDATE(Assumptions!$F$11,73) | BZ12: =EDATE(Assumptions!$F$11,74) | CA12: =EDATE(Assumptions!$F$11,75) | CB12: =EDATE(Assumptions!$F$11,76) | CC12: =EDATE(Assumptions!$F$11,77) | CD12: =EDATE(Assumptions!$F$11,78) | CE12: =EDATE(Assumptions!$F$11,79) | CF12: =EDATE(Assumptions!$F$11,80) | CG12: =EDATE(Assumptions!$F$11,81) | CH12: =EDATE(Assumptions!$F$11,82) | CI12: =EDATE(Assumptions!$F$11,83) | CJ12: =EDATE(Assumptions!$F$11,84) | CK12: =EDATE(Assumptions!$F$11,85) | CL12: =EDATE(Assumptions!$F$11,86) | CM12: =EDATE(Assumptions!$F$11,87) | CN12: =EDATE(Assumptions!$F$11,88) | CO12: =EDATE(Assumptions!$F$11,89) | CP12: =EDATE(Assumptions!$F$11,90) | CQ12: =EDATE(Assumptions!$F$11,91) | CR12: =EDATE(Assumptions!$F$11,92) | CS12: =EDATE(Assumptions!$F$11,93) | CT12: =EDATE(Assumptions!$F$11,94) | CU12: =EDATE(Assumptions!$F$11,95) | CV12: =EDATE(Assumptions!$F$11,96) | CW12: =EDATE(Assumptions!$F$11,97) | CX12: =EDATE(Assumptions!$F$11,98) | CY12: =EDATE(Assumptions!$F$11,99) | CZ12: =EDATE(Assumptions!$F$11,100) | DA12: =EDATE(Assumptions!$F$11,101) | DB12: =EDATE(Assumptions!$F$11,102) | DC12: =EDATE(Assumptions!$F$11,103) | DD12: =EDATE(Assumptions!$F$11,104) | DE12: =EDATE(Assumptions!$F$11,105) | DF12: =EDATE(Assumptions!$F$11,106) | DG12: =EDATE(Assumptions!$F$11,107) | DH12: =EDATE(Assumptions!$F$11,108) | DI12: =EDATE(Assumptions!$F$11,109) | DJ12: =EDATE(Assumptions!$F$11,110) | DK12: =EDATE(Assumptions!$F$11,111) | DL12: =EDATE(Assumptions!$F$11,112) | DM12: =EDATE(Assumptions!$F$11,113) | DN12: =EDATE(Assumptions!$F$11,114) | DO12: =EDATE(Assumptions!$F$11,115) | DP12: =EDATE(Assumptions!$F$11,116) | DQ12: =EDATE(Assumptions!$F$11,117) | DR12: =EDATE(Assumptions!$F$11,118) | DS12: =EDATE(Assumptions!$F$11,119) | DT12: =EDATE(Assumptions!$F$11,120)
A14: General Property Information: | C14: =SUM(D14:DT14)
A15: Total Occupied SF | C15: =SUM(D15:DT15) | D15: =SUM(D155,D157,D159,D161,D163)+SUM(D165,D167,D169,D171,D173) | E15: =SUM(E155,E157,E159,E161,E163)+SUM(E165,E167,E169,E171,E173) | F15: =SUM(F155,F157,F159,F161,F163)+SUM(F165,F167,F169,F171,F173) | G15: =SUM(G155,G157,G159,G161,G163)+SUM(G165,G167,G169,G171,G173) | H15: =SUM(H155,H157,H159,H161,H163)+SUM(H165,H167,H169,H171,H173) | I15: =SUM(I155,I157,I159,I161,I163)+SUM(I165,I167,I169,I171,I173) | J15: =SUM(J155,J157,J159,J161,J163)+SUM(J165,J167,J169,J171,J173) | K15: =SUM(K155,K157,K159,K161,K163)+SUM(K165,K167,K169,K171,K173) | ... DT15: =SUM(DT155,DT157,DT159,DT161,DT163)+SUM(DT165,DT167,DT169,DT171,DT173)
A16: Average Occupancy - Leasable SF | C16: =SUM(D16:DT16) | D16: =IF(Assumptions!$F$13=0,0,D$15/Assumptions!$F$13) | E16: =IF(Assumptions!$F$13=0,0,E$15/Assumptions!$F$13) | F16: =IF(Assumptions!$F$13=0,0,F$15/Assumptions!$F$13) | G16: =IF(Assumptions!$F$13=0,0,G$15/Assumptions!$F$13) | H16: =IF(Assumptions!$F$13=0,0,H$15/Assumptions!$F$13) | I16: =IF(Assumptions!$F$13=0,0,I$15/Assumptions!$F$13) | J16: =IF(Assumptions!$F$13=0,0,J$15/Assumptions!$F$13) | K16: =IF(Assumptions!$F$13=0,0,K$15/Assumptions!$F$13) | ... DT16: =IF(Assumptions!$F$13=0,0,DT$15/Assumptions!$F$13)
A17: Leases Expiring - SF | C17: =SUM(D17:DT17) | D17: =IF(D$11=FC141,'Rent Roll'!$B$9,0)+IF(D$11=FC142,'Rent Roll'!$B$10,0)+IF(D$11=FC143,'Rent Roll'!$B$11,0)+IF(D$11=FC144,'Rent Roll'!$B$12,0)+IF(D$11=FC145,'Rent Roll'!$B$13,0)+IF(D$11=FC146,'Rent Roll'!$B$36,0)+IF(D$11=FC147,'Rent Roll'!$B$37,0)+IF(D$11=FC148,'Rent Roll'!$B$38,0)+IF(D$11=FC149,'Rent Roll'!$B$39,0)+IF(D$11=FC150,'Rent Roll'!$B$40,0) | E17: =IF(E$11=FC141,'Rent Roll'!$B$9,0)+IF(E$11=FC142,'Rent Roll'!$B$10,0)+IF(E$11=FC143,'Rent Roll'!$B$11,0)+IF(E$11=FC144,'Rent Roll'!$B$12,0)+IF(E$11=FC145,'Rent Roll'!$B$13,0)+IF(E$11=FC146,'Rent Roll'!$B$36,0)+IF(E$11=FC147,'Rent Roll'!$B$37,0)+IF(E$11=FC148,'Rent Roll'!$B$38,0)+IF(E$11=FC149,'Rent Roll'!$B$39,0)+IF(E$11=FC150,'Rent Roll'!$B$40,0) | F17: =IF(F$11=FC141,'Rent Roll'!$B$9,0)+IF(F$11=FC142,'Rent Roll'!$B$10,0)+IF(F$11=FC143,'Rent Roll'!$B$11,0)+IF(F$11=FC144,'Rent Roll'!$B$12,0)+IF(F$11=FC145,'Rent Roll'!$B$13,0)+IF(F$11=FC146,'Rent Roll'!$B$36,0)+IF(F$11=FC147,'Rent Roll'!$B$37,0)+IF(F$11=FC148,'Rent Roll'!$B$38,0)+IF(F$11=FC149,'Rent Roll'!$B$39,0)+IF(F$11=FC150,'Rent Roll'!$B$40,0) | G17: =IF(G$11=FC141,'Rent Roll'!$B$9,0)+IF(G$11=FC142,'Rent Roll'!$B$10,0)+IF(G$11=FC143,'Rent Roll'!$B$11,0)+IF(G$11=FC144,'Rent Roll'!$B$12,0)+IF(G$11=FC145,'Rent Roll'!$B$13,0)+IF(G$11=FC146,'Rent Roll'!$B$36,0)+IF(G$11=FC147,'Rent Roll'!$B$37,0)+IF(G$11=FC148,'Rent Roll'!$B$38,0)+IF(G$11=FC149,'Rent Roll'!$B$39,0)+IF(G$11=FC150,'Rent Roll'!$B$40,0) | H17: =IF(H$11=FC141,'Rent Roll'!$B$9,0)+IF(H$11=FC142,'Rent Roll'!$B$10,0)+IF(H$11=FC143,'Rent Roll'!$B$11,0)+IF(H$11=FC144,'Rent Roll'!$B$12,0)+IF(H$11=FC145,'Rent Roll'!$B$13,0)+IF(H$11=FC146,'Rent Roll'!$B$36,0)+IF(H$11=FC147,'Rent Roll'!$B$37,0)+IF(H$11=FC148,'Rent Roll'!$B$38,0)+IF(H$11=FC149,'Rent Roll'!$B$39,0)+IF(H$11=FC150,'Rent Roll'!$B$40,0) | I17: =IF(I$11=FC141,'Rent Roll'!$B$9,0)+IF(I$11=FC142,'Rent Roll'!$B$10,0)+IF(I$11=FC143,'Rent Roll'!$B$11,0)+IF(I$11=FC144,'Rent Roll'!$B$12,0)+IF(I$11=FC145,'Rent Roll'!$B$13,0)+IF(I$11=FC146,'Rent Roll'!$B$36,0)+IF(I$11=FC147,'Rent Roll'!$B$37,0)+IF(I$11=FC148,'Rent Roll'!$B$38,0)+IF(I$11=FC149,'Rent Roll'!$B$39,0)+IF(I$11=FC150,'Rent Roll'!$B$40,0) | J17: =IF(J$11=FC141,'Rent Roll'!$B$9,0)+IF(J$11=FC142,'Rent Roll'!$B$10,0)+IF(J$11=FC143,'Rent Roll'!$B$11,0)+IF(J$11=FC144,'Rent Roll'!$B$12,0)+IF(J$11=FC145,'Rent Roll'!$B$13,0)+IF(J$11=FC146,'Rent Roll'!$B$36,0)+IF(J$11=FC147,'Rent Roll'!$B$37,0)+IF(J$11=FC148,'Rent Roll'!$B$38,0)+IF(J$11=FC149,'Rent Roll'!$B$39,0)+IF(J$11=FC150,'Rent Roll'!$B$40,0) | K17: =IF(K$11=FC141,'Rent Roll'!$B$9,0)+IF(K$11=FC142,'Rent Roll'!$B$10,0)+IF(K$11=FC143,'Rent Roll'!$B$11,0)+IF(K$11=FC144,'Rent Roll'!$B$12,0)+IF(K$11=FC145,'Rent Roll'!$B$13,0)+IF(K$11=FC146,'Rent Roll'!$B$36,0)+IF(K$11=FC147,'Rent Roll'!$B$37,0)+IF(K$11=FC148,'Rent Roll'!$B$38,0)+IF(K$11=FC149,'Rent Roll'!$B$39,0)+IF(K$11=FC150,'Rent Roll'!$B$40,0) | L17: =IF(L$11=FC141,'Rent Roll'!$B$9,0)+IF(L$11=FC142,'Rent Roll'!$B$10,0)+IF(L$11=FC143,'Rent Roll'!$B$11,0)+IF(L$11=FC144,'Rent Roll'!$B$12,0)+IF(L$11=FC145,'Rent Roll'!$B$13,0)+IF(L$11=FC146,'Rent Roll'!$B$36,0)+IF(L$11=FC147,'Rent Roll'!$B$37,0)+IF(L$11=FC148,'Rent Roll'!$B$38,0)+IF(L$11=FC149,'Rent Roll'!$B$39,0)+IF(L$11=FC150,'Rent Roll'!$B$40,0) | M17: =IF(M$11=FC141,'Rent Roll'!$B$9,0)+IF(M$11=FC142,'Rent Roll'!$B$10,0)+IF(M$11=FC143,'Rent Roll'!$B$11,0)+IF(M$11=FC144,'Rent Roll'!$B$12,0)+IF(M$11=FC145,'Rent Roll'!$B$13,0)+IF(M$11=FC146,'Rent Roll'!$B$36,0)+IF(M$11=FC147,'Rent Roll'!$B$37,0)+IF(M$11=FC148,'Rent Roll'!$B$38,0)+IF(M$11=FC149,'Rent Roll'!$B$39,0)+IF(M$11=FC150,'Rent Roll'!$B$40,0) | N17: =IF(N$11=FC141,'Rent Roll'!$B$9,0)+IF(N$11=FC142,'Rent Roll'!$B$10,0)+IF(N$11=FC143,'Rent Roll'!$B$11,0)+IF(N$11=FC144,'Rent Roll'!$B$12,0)+IF(N$11=FC145,'Rent Roll'!$B$13,0)+IF(N$11=FC146,'Rent Roll'!$B$36,0)+IF(N$11=FC147,'Rent Roll'!$B$37,0)+IF(N$11=FC148,'Rent Roll'!$B$38,0)+IF(N$11=FC149,'Rent Roll'!$B$39,0)+IF(N$11=FC150,'Rent Roll'!$B$40,0) | O17: =IF(O$11=FC141,'Rent Roll'!$B$9,0)+IF(O$11=FC142,'Rent Roll'!$B$10,0)+IF(O$11=FC143,'Rent Roll'!$B$11,0)+IF(O$11=FC144,'Rent Roll'!$B$12,0)+IF(O$11=FC145,'Rent Roll'!$B$13,0)+IF(O$11=FC146,'Rent Roll'!$B$36,0)+IF(O$11=FC147,'Rent Roll'!$B$37,0)+IF(O$11=FC148,'Rent Roll'!$B$38,0)+IF(O$11=FC149,'Rent Roll'!$B$39,0)+IF(O$11=FC150,'Rent Roll'!$B$40,0) | P17: =IF(P$11=FC141,'Rent Roll'!$B$9,0)+IF(P$11=FC142,'Rent Roll'!$B$10,0)+IF(P$11=FC143,'Rent Roll'!$B$11,0)+IF(P$11=FC144,'Rent Roll'!$B$12,0)+IF(P$11=FC145,'Rent Roll'!$B$13,0)+IF(P$11=FC146,'Rent Roll'!$B$36,0)+IF(P$11=FC147,'Rent Roll'!$B$37,0)+IF(P$11=FC148,'Rent Roll'!$B$38,0)+IF(P$11=FC149,'Rent Roll'!$B$39,0)+IF(P$11=FC150,'Rent Roll'!$B$40,0) | Q17: =IF(Q$11=FC141,'Rent Roll'!$B$9,0)+IF(Q$11=FC142,'Rent Roll'!$B$10,0)+IF(Q$11=FC143,'Rent Roll'!$B$11,0)+IF(Q$11=FC144,'Rent Roll'!$B$12,0)+IF(Q$11=FC145,'Rent Roll'!$B$13,0)+IF(Q$11=FC146,'Rent Roll'!$B$36,0)+IF(Q$11=FC147,'Rent Roll'!$B$37,0)+IF(Q$11=FC148,'Rent Roll'!$B$38,0)+IF(Q$11=FC149,'Rent Roll'!$B$39,0)+IF(Q$11=FC150,'Rent Roll'!$B$40,0) | R17: =IF(R$11=FC141,'Rent Roll'!$B$9,0)+IF(R$11=FC142,'Rent Roll'!$B$10,0)+IF(R$11=FC143,'Rent Roll'!$B$11,0)+IF(R$11=FC144,'Rent Roll'!$B$12,0)+IF(R$11=FC145,'Rent Roll'!$B$13,0)+IF(R$11=FC146,'Rent Roll'!$B$36,0)+IF(R$11=FC147,'Rent Roll'!$B$37,0)+IF(R$11=FC148,'Rent Roll'!$B$38,0)+IF(R$11=FC149,'Rent Roll'!$B$39,0)+IF(R$11=FC150,'Rent Roll'!$B$40,0) | S17: =IF(S$11=FC141,'Rent Roll'!$B$9,0)+IF(S$11=FC142,'Rent Roll'!$B$10,0)+IF(S$11=FC143,'Rent Roll'!$B$11,0)+IF(S$11=FC144,'Rent Roll'!$B$12,0)+IF(S$11=FC145,'Rent Roll'!$B$13,0)+IF(S$11=FC146,'Rent Roll'!$B$36,0)+IF(S$11=FC147,'Rent Roll'!$B$37,0)+IF(S$11=FC148,'Rent Roll'!$B$38,0)+IF(S$11=FC149,'Rent Roll'!$B$39,0)+IF(S$11=FC150,'Rent Roll'!$B$40,0) | T17: =IF(T$11=FC141,'Rent Roll'!$B$9,0)+IF(T$11=FC142,'Rent Roll'!$B$10,0)+IF(T$11=FC143,'Rent Roll'!$B$11,0)+IF(T$11=FC144,'Rent Roll'!$B$12,0)+IF(T$11=FC145,'Rent Roll'!$B$13,0)+IF(T$11=FC146,'Rent Roll'!$B$36,0)+IF(T$11=FC147,'Rent Roll'!$B$37,0)+IF(T$11=FC148,'Rent Roll'!$B$38,0)+IF(T$11=FC149,'Rent Roll'!$B$39,0)+IF(T$11=FC150,'Rent Roll'!$B$40,0) | U17: =IF(U$11=FC141,'Rent Roll'!$B$9,0)+IF(U$11=FC142,'Rent Roll'!$B$10,0)+IF(U$11=FC143,'Rent Roll'!$B$11,0)+IF(U$11=FC144,'Rent Roll'!$B$12,0)+IF(U$11=FC145,'Rent Roll'!$B$13,0)+IF(U$11=FC146,'Rent Roll'!$B$36,0)+IF(U$11=FC147,'Rent Roll'!$B$37,0)+IF(U$11=FC148,'Rent Roll'!$B$38,0)+IF(U$11=FC149,'Rent Roll'!$B$39,0)+IF(U$11=FC150,'Rent Roll'!$B$40,0) | V17: =IF(V$11=FC141,'Rent Roll'!$B$9,0)+IF(V$11=FC142,'Rent Roll'!$B$10,0)+IF(V$11=FC143,'Rent Roll'!$B$11,0)+IF(V$11=FC144,'Rent Roll'!$B$12,0)+IF(V$11=FC145,'Rent Roll'!$B$13,0)+IF(V$11=FC146,'Rent Roll'!$B$36,0)+IF(V$11=FC147,'Rent Roll'!$B$37,0)+IF(V$11=FC148,'Rent Roll'!$B$38,0)+IF(V$11=FC149,'Rent Roll'!$B$39,0)+IF(V$11=FC150,'Rent Roll'!$B$40,0) | W17: =IF(W$11=FC141,'Rent Roll'!$B$9,0)+IF(W$11=FC142,'Rent Roll'!$B$10,0)+IF(W$11=FC143,'Rent Roll'!$B$11,0)+IF(W$11=FC144,'Rent Roll'!$B$12,0)+IF(W$11=FC145,'Rent Roll'!$B$13,0)+IF(W$11=FC146,'Rent Roll'!$B$36,0)+IF(W$11=FC147,'Rent Roll'!$B$37,0)+IF(W$11=FC148,'Rent Roll'!$B$38,0)+IF(W$11=FC149,'Rent Roll'!$B$39,0)+IF(W$11=FC150,'Rent Roll'!$B$40,0) | X17: =IF(X$11=FC141,'Rent Roll'!$B$9,0)+IF(X$11=FC142,'Rent Roll'!$B$10,0)+IF(X$11=FC143,'Rent Roll'!$B$11,0)+IF(X$11=FC144,'Rent Roll'!$B$12,0)+IF(X$11=FC145,'Rent Roll'!$B$13,0)+IF(X$11=FC146,'Rent Roll'!$B$36,0)+IF(X$11=FC147,'Rent Roll'!$B$37,0)+IF(X$11=FC148,'Rent Roll'!$B$38,0)+IF(X$11=FC149,'Rent Roll'!$B$39,0)+IF(X$11=FC150,'Rent Roll'!$B$40,0) | Y17: =IF(Y$11=FC141,'Rent Roll'!$B$9,0)+IF(Y$11=FC142,'Rent Roll'!$B$10,0)+IF(Y$11=FC143,'Rent Roll'!$B$11,0)+IF(Y$11=FC144,'Rent Roll'!$B$12,0)+IF(Y$11=FC145,'Rent Roll'!$B$13,0)+IF(Y$11=FC146,'Rent Roll'!$B$36,0)+IF(Y$11=FC147,'Rent Roll'!$B$37,0)+IF(Y$11=FC148,'Rent Roll'!$B$38,0)+IF(Y$11=FC149,'Rent Roll'!$B$39,0)+IF(Y$11=FC150,'Rent Roll'!$B$40,0) | Z17: =IF(Z$11=FC141,'Rent Roll'!$B$9,0)+IF(Z$11=FC142,'Rent Roll'!$B$10,0)+IF(Z$11=FC143,'Rent Roll'!$B$11,0)+IF(Z$11=FC144,'Rent Roll'!$B$12,0)+IF(Z$11=FC145,'Rent Roll'!$B$13,0)+IF(Z$11=FC146,'Rent Roll'!$B$36,0)+IF(Z$11=FC147,'Rent Roll'!$B$37,0)+IF(Z$11=FC148,'Rent Roll'!$B$38,0)+IF(Z$11=FC149,'Rent Roll'!$B$39,0)+IF(Z$11=FC150,'Rent Roll'!$B$40,0) | AA17: =IF(AA$11=FC141,'Rent Roll'!$B$9,0)+IF(AA$11=FC142,'Rent Roll'!$B$10,0)+IF(AA$11=FC143,'Rent Roll'!$B$11,0)+IF(AA$11=FC144,'Rent Roll'!$B$12,0)+IF(AA$11=FC145,'Rent Roll'!$B$13,0)+IF(AA$11=FC146,'Rent Roll'!$B$36,0)+IF(AA$11=FC147,'Rent Roll'!$B$37,0)+IF(AA$11=FC148,'Rent Roll'!$B$38,0)+IF(AA$11=FC149,'Rent Roll'!$B$39,0)+IF(AA$11=FC150,'Rent Roll'!$B$40,0) | AB17: =IF(AB$11=FC141,'Rent Roll'!$B$9,0)+IF(AB$11=FC142,'Rent Roll'!$B$10,0)+IF(AB$11=FC143,'Rent Roll'!$B$11,0)+IF(AB$11=FC144,'Rent Roll'!$B$12,0)+IF(AB$11=FC145,'Rent Roll'!$B$13,0)+IF(AB$11=FC146,'Rent Roll'!$B$36,0)+IF(AB$11=FC147,'Rent Roll'!$B$37,0)+IF(AB$11=FC148,'Rent Roll'!$B$38,0)+IF(AB$11=FC149,'Rent Roll'!$B$39,0)+IF(AB$11=FC150,'Rent Roll'!$B$40,0) | AC17: =IF(AC$11=FC141,'Rent Roll'!$B$9,0)+IF(AC$11=FC142,'Rent Roll'!$B$10,0)+IF(AC$11=FC143,'Rent Roll'!$B$11,0)+IF(AC$11=FC144,'Rent Roll'!$B$12,0)+IF(AC$11=FC145,'Rent Roll'!$B$13,0)+IF(AC$11=FC146,'Rent Roll'!$B$36,0)+IF(AC$11=FC147,'Rent Roll'!$B$37,0)+IF(AC$11=FC148,'Rent Roll'!$B$38,0)+IF(AC$11=FC149,'Rent Roll'!$B$39,0)+IF(AC$11=FC150,'Rent Roll'!$B$40,0) | AD17: =IF(AD$11=FC141,'Rent Roll'!$B$9,0)+IF(AD$11=FC142,'Rent Roll'!$B$10,0)+IF(AD$11=FC143,'Rent Roll'!$B$11,0)+IF(AD$11=FC144,'Rent Roll'!$B$12,0)+IF(AD$11=FC145,'Rent Roll'!$B$13,0)+IF(AD$11=FC146,'Rent Roll'!$B$36,0)+IF(AD$11=FC147,'Rent Roll'!$B$37,0)+IF(AD$11=FC148,'Rent Roll'!$B$38,0)+IF(AD$11=FC149,'Rent Roll'!$B$39,0)+IF(AD$11=FC150,'Rent Roll'!$B$40,0) | AE17: =IF(AE$11=FC141,'Rent Roll'!$B$9,0)+IF(AE$11=FC142,'Rent Roll'!$B$10,0)+IF(AE$11=FC143,'Rent Roll'!$B$11,0)+IF(AE$11=FC144,'Rent Roll'!$B$12,0)+IF(AE$11=FC145,'Rent Roll'!$B$13,0)+IF(AE$11=FC146,'Rent Roll'!$B$36,0)+IF(AE$11=FC147,'Rent Roll'!$B$37,0)+IF(AE$11=FC148,'Rent Roll'!$B$38,0)+IF(AE$11=FC149,'Rent Roll'!$B$39,0)+IF(AE$11=FC150,'Rent Roll'!$B$40,0) | AF17: =IF(AF$11=FC141,'Rent Roll'!$B$9,0)+IF(AF$11=FC142,'Rent Roll'!$B$10,0)+IF(AF$11=FC143,'Rent Roll'!$B$11,0)+IF(AF$11=FC144,'Rent Roll'!$B$12,0)+IF(AF$11=FC145,'Rent Roll'!$B$13,0)+IF(AF$11=FC146,'Rent Roll'!$B$36,0)+IF(AF$11=FC147,'Rent Roll'!$B$37,0)+IF(AF$11=FC148,'Rent Roll'!$B$38,0)+IF(AF$11=FC149,'Rent Roll'!$B$39,0)+IF(AF$11=FC150,'Rent Roll'!$B$40,0) | AG17: =IF(AG$11=FC141,'Rent Roll'!$B$9,0)+IF(AG$11=FC142,'Rent Roll'!$B$10,0)+IF(AG$11=FC143,'Rent Roll'!$B$11,0)+IF(AG$11=FC144,'Rent Roll'!$B$12,0)+IF(AG$11=FC145,'Rent Roll'!$B$13,0)+IF(AG$11=FC146,'Rent Roll'!$B$36,0)+IF(AG$11=FC147,'Rent Roll'!$B$37,0)+IF(AG$11=FC148,'Rent Roll'!$B$38,0)+IF(AG$11=FC149,'Rent Roll'!$B$39,0)+IF(AG$11=FC150,'Rent Roll'!$B$40,0) | AH17: =IF(AH$11=FC141,'Rent Roll'!$B$9,0)+IF(AH$11=FC142,'Rent Roll'!$B$10,0)+IF(AH$11=FC143,'Rent Roll'!$B$11,0)+IF(AH$11=FC144,'Rent Roll'!$B$12,0)+IF(AH$11=FC145,'Rent Roll'!$B$13,0)+IF(AH$11=FC146,'Rent Roll'!$B$36,0)+IF(AH$11=FC147,'Rent Roll'!$B$37,0)+IF(AH$11=FC148,'Rent Roll'!$B$38,0)+IF(AH$11=FC149,'Rent Roll'!$B$39,0)+IF(AH$11=FC150,'Rent Roll'!$B$40,0) | AI17: =IF(AI$11=FC141,'Rent Roll'!$B$9,0)+IF(AI$11=FC142,'Rent Roll'!$B$10,0)+IF(AI$11=FC143,'Rent Roll'!$B$11,0)+IF(AI$11=FC144,'Rent Roll'!$B$12,0)+IF(AI$11=FC145,'Rent Roll'!$B$13,0)+IF(AI$11=FC146,'Rent Roll'!$B$36,0)+IF(AI$11=FC147,'Rent Roll'!$B$37,0)+IF(AI$11=FC148,'Rent Roll'!$B$38,0)+IF(AI$11=FC149,'Rent Roll'!$B$39,0)+IF(AI$11=FC150,'Rent Roll'!$B$40,0) | AJ17: =IF(AJ$11=FC141,'Rent Roll'!$B$9,0)+IF(AJ$11=FC142,'Rent Roll'!$B$10,0)+IF(AJ$11=FC143,'Rent Roll'!$B$11,0)+IF(AJ$11=FC144,'Rent Roll'!$B$12,0)+IF(AJ$11=FC145,'Rent Roll'!$B$13,0)+IF(AJ$11=FC146,'Rent Roll'!$B$36,0)+IF(AJ$11=FC147,'Rent Roll'!$B$37,0)+IF(AJ$11=FC148,'Rent Roll'!$B$38,0)+IF(AJ$11=FC149,'Rent Roll'!$B$39,0)+IF(AJ$11=FC150,'Rent Roll'!$B$40,0) | AK17: =IF(AK$11=FC141,'Rent Roll'!$B$9,0)+IF(AK$11=FC142,'Rent Roll'!$B$10,0)+IF(AK$11=FC143,'Rent Roll'!$B$11,0)+IF(AK$11=FC144,'Rent Roll'!$B$12,0)+IF(AK$11=FC145,'Rent Roll'!$B$13,0)+IF(AK$11=FC146,'Rent Roll'!$B$36,0)+IF(AK$11=FC147,'Rent Roll'!$B$37,0)+IF(AK$11=FC148,'Rent Roll'!$B$38,0)+IF(AK$11=FC149,'Rent Roll'!$B$39,0)+IF(AK$11=FC150,'Rent Roll'!$B$40,0) | AL17: =IF(AL$11=FC141,'Rent Roll'!$B$9,0)+IF(AL$11=FC142,'Rent Roll'!$B$10,0)+IF(AL$11=FC143,'Rent Roll'!$B$11,0)+IF(AL$11=FC144,'Rent Roll'!$B$12,0)+IF(AL$11=FC145,'Rent Roll'!$B$13,0)+IF(AL$11=FC146,'Rent Roll'!$B$36,0)+IF(AL$11=FC147,'Rent Roll'!$B$37,0)+IF(AL$11=FC148,'Rent Roll'!$B$38,0)+IF(AL$11=FC149,'Rent Roll'!$B$39,0)+IF(AL$11=FC150,'Rent Roll'!$B$40,0) | AM17: =IF(AM$11=FC141,'Rent Roll'!$B$9,0)+IF(AM$11=FC142,'Rent Roll'!$B$10,0)+IF(AM$11=FC143,'Rent Roll'!$B$11,0)+IF(AM$11=FC144,'Rent Roll'!$B$12,0)+IF(AM$11=FC145,'Rent Roll'!$B$13,0)+IF(AM$11=FC146,'Rent Roll'!$B$36,0)+IF(AM$11=FC147,'Rent Roll'!$B$37,0)+IF(AM$11=FC148,'Rent Roll'!$B$38,0)+IF(AM$11=FC149,'Rent Roll'!$B$39,0)+IF(AM$11=FC150,'Rent Roll'!$B$40,0) | AN17: =IF(AN$11=FC141,'Rent Roll'!$B$9,0)+IF(AN$11=FC142,'Rent Roll'!$B$10,0)+IF(AN$11=FC143,'Rent Roll'!$B$11,0)+IF(AN$11=FC144,'Rent Roll'!$B$12,0)+IF(AN$11=FC145,'Rent Roll'!$B$13,0)+IF(AN$11=FC146,'Rent Roll'!$B$36,0)+IF(AN$11=FC147,'Rent Roll'!$B$37,0)+IF(AN$11=FC148,'Rent Roll'!$B$38,0)+IF(AN$11=FC149,'Rent Roll'!$B$39,0)+IF(AN$11=FC150,'Rent Roll'!$B$40,0) | AO17: =IF(AO$11=FC141,'Rent Roll'!$B$9,0)+IF(AO$11=FC142,'Rent Roll'!$B$10,0)+IF(AO$11=FC143,'Rent Roll'!$B$11,0)+IF(AO$11=FC144,'Rent Roll'!$B$12,0)+IF(AO$11=FC145,'Rent Roll'!$B$13,0)+IF(AO$11=FC146,'Rent Roll'!$B$36,0)+IF(AO$11=FC147,'Rent Roll'!$B$37,0)+IF(AO$11=FC148,'Rent Roll'!$B$38,0)+IF(AO$11=FC149,'Rent Roll'!$B$39,0)+IF(AO$11=FC150,'Rent Roll'!$B$40,0) | AP17: =IF(AP$11=FC141,'Rent Roll'!$B$9,0)+IF(AP$11=FC142,'Rent Roll'!$B$10,0)+IF(AP$11=FC143,'Rent Roll'!$B$11,0)+IF(AP$11=FC144,'Rent Roll'!$B$12,0)+IF(AP$11=FC145,'Rent Roll'!$B$13,0)+IF(AP$11=FC146,'Rent Roll'!$B$36,0)+IF(AP$11=FC147,'Rent Roll'!$B$37,0)+IF(AP$11=FC148,'Rent Roll'!$B$38,0)+IF(AP$11=FC149,'Rent Roll'!$B$39,0)+IF(AP$11=FC150,'Rent Roll'!$B$40,0) | AQ17: =IF(AQ$11=FC141,'Rent Roll'!$B$9,0)+IF(AQ$11=FC142,'Rent Roll'!$B$10,0)+IF(AQ$11=FC143,'Rent Roll'!$B$11,0)+IF(AQ$11=FC144,'Rent Roll'!$B$12,0)+IF(AQ$11=FC145,'Rent Roll'!$B$13,0)+IF(AQ$11=FC146,'Rent Roll'!$B$36,0)+IF(AQ$11=FC147,'Rent Roll'!$B$37,0)+IF(AQ$11=FC148,'Rent Roll'!$B$38,0)+IF(AQ$11=FC149,'Rent Roll'!$B$39,0)+IF(AQ$11=FC150,'Rent Roll'!$B$40,0) | AR17: =IF(AR$11=FC141,'Rent Roll'!$B$9,0)+IF(AR$11=FC142,'Rent Roll'!$B$10,0)+IF(AR$11=FC143,'Rent Roll'!$B$11,0)+IF(AR$11=FC144,'Rent Roll'!$B$12,0)+IF(AR$11=FC145,'Rent Roll'!$B$13,0)+IF(AR$11=FC146,'Rent Roll'!$B$36,0)+IF(AR$11=FC147,'Rent Roll'!$B$37,0)+IF(AR$11=FC148,'Rent Roll'!$B$38,0)+IF(AR$11=FC149,'Rent Roll'!$B$39,0)+IF(AR$11=FC150,'Rent Roll'!$B$40,0) | AS17: =IF(AS$11=FC141,'Rent Roll'!$B$9,0)+IF(AS$11=FC142,'Rent Roll'!$B$10,0)+IF(AS$11=FC143,'Rent Roll'!$B$11,0)+IF(AS$11=FC144,'Rent Roll'!$B$12,0)+IF(AS$11=FC145,'Rent Roll'!$B$13,0)+IF(AS$11=FC146,'Rent Roll'!$B$36,0)+IF(AS$11=FC147,'Rent Roll'!$B$37,0)+IF(AS$11=FC148,'Rent Roll'!$B$38,0)+IF(AS$11=FC149,'Rent Roll'!$B$39,0)+IF(AS$11=FC150,'Rent Roll'!$B$40,0) | AT17: =IF(AT$11=FC141,'Rent Roll'!$B$9,0)+IF(AT$11=FC142,'Rent Roll'!$B$10,0)+IF(AT$11=FC143,'Rent Roll'!$B$11,0)+IF(AT$11=FC144,'Rent Roll'!$B$12,0)+IF(AT$11=FC145,'Rent Roll'!$B$13,0)+IF(AT$11=FC146,'Rent Roll'!$B$36,0)+IF(AT$11=FC147,'Rent Roll'!$B$37,0)+IF(AT$11=FC148,'Rent Roll'!$B$38,0)+IF(AT$11=FC149,'Rent Roll'!$B$39,0)+IF(AT$11=FC150,'Rent Roll'!$B$40,0) | AU17: =IF(AU$11=FC141,'Rent Roll'!$B$9,0)+IF(AU$11=FC142,'Rent Roll'!$B$10,0)+IF(AU$11=FC143,'Rent Roll'!$B$11,0)+IF(AU$11=FC144,'Rent Roll'!$B$12,0)+IF(AU$11=FC145,'Rent Roll'!$B$13,0)+IF(AU$11=FC146,'Rent Roll'!$B$36,0)+IF(AU$11=FC147,'Rent Roll'!$B$37,0)+IF(AU$11=FC148,'Rent Roll'!$B$38,0)+IF(AU$11=FC149,'Rent Roll'!$B$39,0)+IF(AU$11=FC150,'Rent Roll'!$B$40,0) | AV17: =IF(AV$11=FC141,'Rent Roll'!$B$9,0)+IF(AV$11=FC142,'Rent Roll'!$B$10,0)+IF(AV$11=FC143,'Rent Roll'!$B$11,0)+IF(AV$11=FC144,'Rent Roll'!$B$12,0)+IF(AV$11=FC145,'Rent Roll'!$B$13,0)+IF(AV$11=FC146,'Rent Roll'!$B$36,0)+IF(AV$11=FC147,'Rent Roll'!$B$37,0)+IF(AV$11=FC148,'Rent Roll'!$B$38,0)+IF(AV$11=FC149,'Rent Roll'!$B$39,0)+IF(AV$11=FC150,'Rent Roll'!$B$40,0) | AW17: =IF(AW$11=FC141,'Rent Roll'!$B$9,0)+IF(AW$11=FC142,'Rent Roll'!$B$10,0)+IF(AW$11=FC143,'Rent Roll'!$B$11,0)+IF(AW$11=FC144,'Rent Roll'!$B$12,0)+IF(AW$11=FC145,'Rent Roll'!$B$13,0)+IF(AW$11=FC146,'Rent Roll'!$B$36,0)+IF(AW$11=FC147,'Rent Roll'!$B$37,0)+IF(AW$11=FC148,'Rent Roll'!$B$38,0)+IF(AW$11=FC149,'Rent Roll'!$B$39,0)+IF(AW$11=FC150,'Rent Roll'!$B$40,0) | AX17: =IF(AX$11=FC141,'Rent Roll'!$B$9,0)+IF(AX$11=FC142,'Rent Roll'!$B$10,0)+IF(AX$11=FC143,'Rent Roll'!$B$11,0)+IF(AX$11=FC144,'Rent Roll'!$B$12,0)+IF(AX$11=FC145,'Rent Roll'!$B$13,0)+IF(AX$11=FC146,'Rent Roll'!$B$36,0)+IF(AX$11=FC147,'Rent Roll'!$B$37,0)+IF(AX$11=FC148,'Rent Roll'!$B$38,0)+IF(AX$11=FC149,'Rent Roll'!$B$39,0)+IF(AX$11=FC150,'Rent Roll'!$B$40,0) | AY17: =IF(AY$11=FC141,'Rent Roll'!$B$9,0)+IF(AY$11=FC142,'Rent Roll'!$B$10,0)+IF(AY$11=FC143,'Rent Roll'!$B$11,0)+IF(AY$11=FC144,'Rent Roll'!$B$12,0)+IF(AY$11=FC145,'Rent Roll'!$B$13,0)+IF(AY$11=FC146,'Rent Roll'!$B$36,0)+IF(AY$11=FC147,'Rent Roll'!$B$37,0)+IF(AY$11=FC148,'Rent Roll'!$B$38,0)+IF(AY$11=FC149,'Rent Roll'!$B$39,0)+IF(AY$11=FC150,'Rent Roll'!$B$40,0) | AZ17: =IF(AZ$11=FC141,'Rent Roll'!$B$9,0)+IF(AZ$11=FC142,'Rent Roll'!$B$10,0)+IF(AZ$11=FC143,'Rent Roll'!$B$11,0)+IF(AZ$11=FC144,'Rent Roll'!$B$12,0)+IF(AZ$11=FC145,'Rent Roll'!$B$13,0)+IF(AZ$11=FC146,'Rent Roll'!$B$36,0)+IF(AZ$11=FC147,'Rent Roll'!$B$37,0)+IF(AZ$11=FC148,'Rent Roll'!$B$38,0)+IF(AZ$11=FC149,'Rent Roll'!$B$39,0)+IF(AZ$11=FC150,'Rent Roll'!$B$40,0) | BA17: =IF(BA$11=FC141,'Rent Roll'!$B$9,0)+IF(BA$11=FC142,'Rent Roll'!$B$10,0)+IF(BA$11=FC143,'Rent Roll'!$B$11,0)+IF(BA$11=FC144,'Rent Roll'!$B$12,0)+IF(BA$11=FC145,'Rent Roll'!$B$13,0)+IF(BA$11=FC146,'Rent Roll'!$B$36,0)+IF(BA$11=FC147,'Rent Roll'!$B$37,0)+IF(BA$11=FC148,'Rent Roll'!$B$38,0)+IF(BA$11=FC149,'Rent Roll'!$B$39,0)+IF(BA$11=FC150,'Rent Roll'!$B$40,0) | BB17: =IF(BB$11=FC141,'Rent Roll'!$B$9,0)+IF(BB$11=FC142,'Rent Roll'!$B$10,0)+IF(BB$11=FC143,'Rent Roll'!$B$11,0)+IF(BB$11=FC144,'Rent Roll'!$B$12,0)+IF(BB$11=FC145,'Rent Roll'!$B$13,0)+IF(BB$11=FC146,'Rent Roll'!$B$36,0)+IF(BB$11=FC147,'Rent Roll'!$B$37,0)+IF(BB$11=FC148,'Rent Roll'!$B$38,0)+IF(BB$11=FC149,'Rent Roll'!$B$39,0)+IF(BB$11=FC150,'Rent Roll'!$B$40,0) | BC17: =IF(BC$11=FC141,'Rent Roll'!$B$9,0)+IF(BC$11=FC142,'Rent Roll'!$B$10,0)+IF(BC$11=FC143,'Rent Roll'!$B$11,0)+IF(BC$11=FC144,'Rent Roll'!$B$12,0)+IF(BC$11=FC145,'Rent Roll'!$B$13,0)+IF(BC$11=FC146,'Rent Roll'!$B$36,0)+IF(BC$11=FC147,'Rent Roll'!$B$37,0)+IF(BC$11=FC148,'Rent Roll'!$B$38,0)+IF(BC$11=FC149,'Rent Roll'!$B$39,0)+IF(BC$11=FC150,'Rent Roll'!$B$40,0) | BD17: =IF(BD$11=FC141,'Rent Roll'!$B$9,0)+IF(BD$11=FC142,'Rent Roll'!$B$10,0)+IF(BD$11=FC143,'Rent Roll'!$B$11,0)+IF(BD$11=FC144,'Rent Roll'!$B$12,0)+IF(BD$11=FC145,'Rent Roll'!$B$13,0)+IF(BD$11=FC146,'Rent Roll'!$B$36,0)+IF(BD$11=FC147,'Rent Roll'!$B$37,0)+IF(BD$11=FC148,'Rent Roll'!$B$38,0)+IF(BD$11=FC149,'Rent Roll'!$B$39,0)+IF(BD$11=FC150,'Rent Roll'!$B$40,0) | BE17: =IF(BE$11=FC141,'Rent Roll'!$B$9,0)+IF(BE$11=FC142,'Rent Roll'!$B$10,0)+IF(BE$11=FC143,'Rent Roll'!$B$11,0)+IF(BE$11=FC144,'Rent Roll'!$B$12,0)+IF(BE$11=FC145,'Rent Roll'!$B$13,0)+IF(BE$11=FC146,'Rent Roll'!$B$36,0)+IF(BE$11=FC147,'Rent Roll'!$B$37,0)+IF(BE$11=FC148,'Rent Roll'!$B$38,0)+IF(BE$11=FC149,'Rent Roll'!$B$39,0)+IF(BE$11=FC150,'Rent Roll'!$B$40,0) | BF17: =IF(BF$11=FC141,'Rent Roll'!$B$9,0)+IF(BF$11=FC142,'Rent Roll'!$B$10,0)+IF(BF$11=FC143,'Rent Roll'!$B$11,0)+IF(BF$11=FC144,'Rent Roll'!$B$12,0)+IF(BF$11=FC145,'Rent Roll'!$B$13,0)+IF(BF$11=FC146,'Rent Roll'!$B$36,0)+IF(BF$11=FC147,'Rent Roll'!$B$37,0)+IF(BF$11=FC148,'Rent Roll'!$B$38,0)+IF(BF$11=FC149,'Rent Roll'!$B$39,0)+IF(BF$11=FC150,'Rent Roll'!$B$40,0) | BG17: =IF(BG$11=FC141,'Rent Roll'!$B$9,0)+IF(BG$11=FC142,'Rent Roll'!$B$10,0)+IF(BG$11=FC143,'Rent Roll'!$B$11,0)+IF(BG$11=FC144,'Rent Roll'!$B$12,0)+IF(BG$11=FC145,'Rent Roll'!$B$13,0)+IF(BG$11=FC146,'Rent Roll'!$B$36,0)+IF(BG$11=FC147,'Rent Roll'!$B$37,0)+IF(BG$11=FC148,'Rent Roll'!$B$38,0)+IF(BG$11=FC149,'Rent Roll'!$B$39,0)+IF(BG$11=FC150,'Rent Roll'!$B$40,0) | BH17: =IF(BH$11=FC141,'Rent Roll'!$B$9,0)+IF(BH$11=FC142,'Rent Roll'!$B$10,0)+IF(BH$11=FC143,'Rent Roll'!$B$11,0)+IF(BH$11=FC144,'Rent Roll'!$B$12,0)+IF(BH$11=FC145,'Rent Roll'!$B$13,0)+IF(BH$11=FC146,'Rent Roll'!$B$36,0)+IF(BH$11=FC147,'Rent Roll'!$B$37,0)+IF(BH$11=FC148,'Rent Roll'!$B$38,0)+IF(BH$11=FC149,'Rent Roll'!$B$39,0)+IF(BH$11=FC150,'Rent Roll'!$B$40,0) | BI17: =IF(BI$11=FC141,'Rent Roll'!$B$9,0)+IF(BI$11=FC142,'Rent Roll'!$B$10,0)+IF(BI$11=FC143,'Rent Roll'!$B$11,0)+IF(BI$11=FC144,'Rent Roll'!$B$12,0)+IF(BI$11=FC145,'Rent Roll'!$B$13,0)+IF(BI$11=FC146,'Rent Roll'!$B$36,0)+IF(BI$11=FC147,'Rent Roll'!$B$37,0)+IF(BI$11=FC148,'Rent Roll'!$B$38,0)+IF(BI$11=FC149,'Rent Roll'!$B$39,0)+IF(BI$11=FC150,'Rent Roll'!$B$40,0) | BJ17: =IF(BJ$11=FC141,'Rent Roll'!$B$9,0)+IF(BJ$11=FC142,'Rent Roll'!$B$10,0)+IF(BJ$11=FC143,'Rent Roll'!$B$11,0)+IF(BJ$11=FC144,'Rent Roll'!$B$12,0)+IF(BJ$11=FC145,'Rent Roll'!$B$13,0)+IF(BJ$11=FC146,'Rent Roll'!$B$36,0)+IF(BJ$11=FC147,'Rent Roll'!$B$37,0)+IF(BJ$11=FC148,'Rent Roll'!$B$38,0)+IF(BJ$11=FC149,'Rent Roll'!$B$39,0)+IF(BJ$11=FC150,'Rent Roll'!$B$40,0) | BK17: =IF(BK$11=FC141,'Rent Roll'!$B$9,0)+IF(BK$11=FC142,'Rent Roll'!$B$10,0)+IF(BK$11=FC143,'Rent Roll'!$B$11,0)+IF(BK$11=FC144,'Rent Roll'!$B$12,0)+IF(BK$11=FC145,'Rent Roll'!$B$13,0)+IF(BK$11=FC146,'Rent Roll'!$B$36,0)+IF(BK$11=FC147,'Rent Roll'!$B$37,0)+IF(BK$11=FC148,'Rent Roll'!$B$38,0)+IF(BK$11=FC149,'Rent Roll'!$B$39,0)+IF(BK$11=FC150,'Rent Roll'!$B$40,0) | BL17: =IF(BL$11=FC141,'Rent Roll'!$B$9,0)+IF(BL$11=FC142,'Rent Roll'!$B$10,0)+IF(BL$11=FC143,'Rent Roll'!$B$11,0)+IF(BL$11=FC144,'Rent Roll'!$B$12,0)+IF(BL$11=FC145,'Rent Roll'!$B$13,0)+IF(BL$11=FC146,'Rent Roll'!$B$36,0)+IF(BL$11=FC147,'Rent Roll'!$B$37,0)+IF(BL$11=FC148,'Rent Roll'!$B$38,0)+IF(BL$11=FC149,'Rent Roll'!$B$39,0)+IF(BL$11=FC150,'Rent Roll'!$B$40,0) | BM17: =IF(BM$11=FD141,'Rent Roll'!$B$9,0)+IF(BM$11=FD142,'Rent Roll'!$B$10,0)+IF(BM$11=FD143,'Rent Roll'!$B$11,0)+IF(BM$11=FD144,'Rent Roll'!$B$12,0)+IF(BM$11=FD145,'Rent Roll'!$B$13,0)+IF(BM$11=FD146,'Rent Roll'!$B$36,0)+IF(BM$11=FD147,'Rent Roll'!$B$37,0)+IF(BM$11=FD148,'Rent Roll'!$B$38,0)+IF(BM$11=FD149,'Rent Roll'!$B$39,0)+IF(BM$11=FD150,'Rent Roll'!$B$40,0) | BN17: =IF(BN$11=FE141,'Rent Roll'!$B$9,0)+IF(BN$11=FE142,'Rent Roll'!$B$10,0)+IF(BN$11=FE143,'Rent Roll'!$B$11,0)+IF(BN$11=FE144,'Rent Roll'!$B$12,0)+IF(BN$11=FE145,'Rent Roll'!$B$13,0)+IF(BN$11=FE146,'Rent Roll'!$B$36,0)+IF(BN$11=FE147,'Rent Roll'!$B$37,0)+IF(BN$11=FE148,'Rent Roll'!$B$38,0)+IF(BN$11=FE149,'Rent Roll'!$B$39,0)+IF(BN$11=FE150,'Rent Roll'!$B$40,0) | BO17: =IF(BO$11=FF141,'Rent Roll'!$B$9,0)+IF(BO$11=FF142,'Rent Roll'!$B$10,0)+IF(BO$11=FF143,'Rent Roll'!$B$11,0)+IF(BO$11=FF144,'Rent Roll'!$B$12,0)+IF(BO$11=FF145,'Rent Roll'!$B$13,0)+IF(BO$11=FF146,'Rent Roll'!$B$36,0)+IF(BO$11=FF147,'Rent Roll'!$B$37,0)+IF(BO$11=FF148,'Rent Roll'!$B$38,0)+IF(BO$11=FF149,'Rent Roll'!$B$39,0)+IF(BO$11=FF150,'Rent Roll'!$B$40,0) | BP17: =IF(BP$11=FG141,'Rent Roll'!$B$9,0)+IF(BP$11=FG142,'Rent Roll'!$B$10,0)+IF(BP$11=FG143,'Rent Roll'!$B$11,0)+IF(BP$11=FG144,'Rent Roll'!$B$12,0)+IF(BP$11=FG145,'Rent Roll'!$B$13,0)+IF(BP$11=FG146,'Rent Roll'!$B$36,0)+IF(BP$11=FG147,'Rent Roll'!$B$37,0)+IF(BP$11=FG148,'Rent Roll'!$B$38,0)+IF(BP$11=FG149,'Rent Roll'!$B$39,0)+IF(BP$11=FG150,'Rent Roll'!$B$40,0) | BQ17: =IF(BQ$11=FH141,'Rent Roll'!$B$9,0)+IF(BQ$11=FH142,'Rent Roll'!$B$10,0)+IF(BQ$11=FH143,'Rent Roll'!$B$11,0)+IF(BQ$11=FH144,'Rent Roll'!$B$12,0)+IF(BQ$11=FH145,'Rent Roll'!$B$13,0)+IF(BQ$11=FH146,'Rent Roll'!$B$36,0)+IF(BQ$11=FH147,'Rent Roll'!$B$37,0)+IF(BQ$11=FH148,'Rent Roll'!$B$38,0)+IF(BQ$11=FH149,'Rent Roll'!$B$39,0)+IF(BQ$11=FH150,'Rent Roll'!$B$40,0) | BR17: =IF(BR$11=FI141,'Rent Roll'!$B$9,0)+IF(BR$11=FI142,'Rent Roll'!$B$10,0)+IF(BR$11=FI143,'Rent Roll'!$B$11,0)+IF(BR$11=FI144,'Rent Roll'!$B$12,0)+IF(BR$11=FI145,'Rent Roll'!$B$13,0)+IF(BR$11=FI146,'Rent Roll'!$B$36,0)+IF(BR$11=FI147,'Rent Roll'!$B$37,0)+IF(BR$11=FI148,'Rent Roll'!$B$38,0)+IF(BR$11=FI149,'Rent Roll'!$B$39,0)+IF(BR$11=FI150,'Rent Roll'!$B$40,0) | BS17: =IF(BS$11=FJ141,'Rent Roll'!$B$9,0)+IF(BS$11=FJ142,'Rent Roll'!$B$10,0)+IF(BS$11=FJ143,'Rent Roll'!$B$11,0)+IF(BS$11=FJ144,'Rent Roll'!$B$12,0)+IF(BS$11=FJ145,'Rent Roll'!$B$13,0)+IF(BS$11=FJ146,'Rent Roll'!$B$36,0)+IF(BS$11=FJ147,'Rent Roll'!$B$37,0)+IF(BS$11=FJ148,'Rent Roll'!$B$38,0)+IF(BS$11=FJ149,'Rent Roll'!$B$39,0)+IF(BS$11=FJ150,'Rent Roll'!$B$40,0) | ... DT17: =IF(DT$11=HK141,'Rent Roll'!$B$9,0)+IF(DT$11=HK142,'Rent Roll'!$B$10,0)+IF(DT$11=HK143,'Rent Roll'!$B$11,0)+IF(DT$11=HK144,'Rent Roll'!$B$12,0)+IF(DT$11=HK145,'Rent Roll'!$B$13,0)+IF(DT$11=HK146,'Rent Roll'!$B$36,0)+IF(DT$11=HK147,'Rent Roll'!$B$37,0)+IF(DT$11=HK148,'Rent Roll'!$B$38,0)+IF(DT$11=HK149,'Rent Roll'!$B$39,0)+IF(DT$11=HK150,'Rent Roll'!$B$40,0)
A18: Leases Expiring - % (Remeasured) | C18: =SUM(D18:DT18) | D18: =IF(Assumptions!$F$13=0,0,D$17/Assumptions!$F$13) | E18: =IF(Assumptions!$F$13=0,0,E$17/Assumptions!$F$13) | F18: =IF(Assumptions!$F$13=0,0,F$17/Assumptions!$F$13) | G18: =IF(Assumptions!$F$13=0,0,G$17/Assumptions!$F$13) | H18: =IF(Assumptions!$F$13=0,0,H$17/Assumptions!$F$13) | I18: =IF(Assumptions!$F$13=0,0,I$17/Assumptions!$F$13) | J18: =IF(Assumptions!$F$13=0,0,J$17/Assumptions!$F$13) | K18: =IF(Assumptions!$F$13=0,0,K$17/Assumptions!$F$13) | ... DT18: =IF(Assumptions!$F$13=0,0,DT$17/Assumptions!$F$13)
A20: Inflation | C20: =SUM(D20:DT20)
A22: Rent Revenue | C22: =SUM(D22:DT22)
A23: Potential Base Rent | C23: =SUM(D23:DT23) | D23: =SUM(D154,D156,D158,D160,D162) | E23: =SUM(E154,E156,E158,E160,E162) | F23: =SUM(F154,F156,F158,F160,F162) | G23: =SUM(G154,G156,G158,G160,G162) | H23: =SUM(H154,H156,H158,H160,H162) | I23: =SUM(I154,I156,I158,I160,I162) | J23: =SUM(J154,J156,J158,J160,J162) | K23: =SUM(K154,K156,K158,K160,K162) | ... DT23: =SUM(DT154,DT156,DT158,DT160,DT162)
A24: Scheduled Market Base Rent | C24: =SUM(D24:DT24) | D24: =SUM(D164,D166,D168,D170,D172) | E24: =SUM(E164,E166,E168,E170,E172) | F24: =SUM(F164,F166,F168,F170,F172) | G24: =SUM(G164,G166,G168,G170,G172) | H24: =SUM(H164,H166,H168,H170,H172) | I24: =SUM(I164,I166,I168,I170,I172) | J24: =SUM(J164,J166,J168,J170,J172) | K24: =SUM(K164,K166,K168,K170,K172) | ... DT24: =SUM(DT164,DT166,DT168,DT170,DT172)
A25: Total Tenant Revenue | C25: =SUM(D25:DT25) | D25: =D$23+D$24 | E25: =E$23+E$24 | F25: =F$23+F$24 | G25: =G$23+G$24 | H25: =H$23+H$24 | I25: =I$23+I$24 | J25: =J$23+J$24 | K25: =K$23+K$24 | ... DT25: =DT$23+DT$24
A27: Total Base Expense Recoveries | C27: =SUM(D27:DT27) | D27: =IF(D$11=0,0,-D$52*(SUM(D155,D157,D159,D161,D163))/Assumptions!$F$13) | E27: =IF(E$11=0,0,-E$52*(SUM(E155,E157,E159,E161,E163))/Assumptions!$F$13) | F27: =IF(F$11=0,0,-F$52*(SUM(F155,F157,F159,F161,F163))/Assumptions!$F$13) | G27: =IF(G$11=0,0,-G$52*(SUM(G155,G157,G159,G161,G163))/Assumptions!$F$13) | H27: =IF(H$11=0,0,-H$52*(SUM(H155,H157,H159,H161,H163))/Assumptions!$F$13) | I27: =IF(I$11=0,0,-I$52*(SUM(I155,I157,I159,I161,I163))/Assumptions!$F$13) | J27: =IF(J$11=0,0,-J$52*(SUM(J155,J157,J159,J161,J163))/Assumptions!$F$13) | K27: =IF(K$11=0,0,-K$52*(SUM(K155,K157,K159,K161,K163))/Assumptions!$F$13) | ... DT27: =IF(DT$11=0,0,-DT$52*(SUM(DT155,DT157,DT159,DT161,DT163))/Assumptions!$F$13)
A28: Total Market Expense Recoveries | C28: =SUM(D28:DT28) | D28: =IF(D$11=0,0,-D$52*(SUM(D165,D167,D169,D171,D173))/Assumptions!$F$13) | E28: =IF(E$11=0,0,-E$52*(SUM(E165,E167,E169,E171,E173))/Assumptions!$F$13) | F28: =IF(F$11=0,0,-F$52*(SUM(F165,F167,F169,F171,F173))/Assumptions!$F$13) | G28: =IF(G$11=0,0,-G$52*(SUM(G165,G167,G169,G171,G173))/Assumptions!$F$13) | H28: =IF(H$11=0,0,-H$52*(SUM(H165,H167,H169,H171,H173))/Assumptions!$F$13) | I28: =IF(I$11=0,0,-I$52*(SUM(I165,I167,I169,I171,I173))/Assumptions!$F$13) | J28: =IF(J$11=0,0,-J$52*(SUM(J165,J167,J169,J171,J173))/Assumptions!$F$13) | K28: =IF(K$11=0,0,-K$52*(SUM(K165,K167,K169,K171,K173))/Assumptions!$F$13) | ... DT28: =IF(DT$11=0,0,-DT$52*(SUM(DT165,DT167,DT169,DT171,DT173))/Assumptions!$F$13)
A29: Total Expense Recoveries | C29: =SUM(D29:DT29) | D29: =D$27+D$28 | E29: =E$27+E$28 | F29: =F$27+F$28 | G29: =G$27+G$28 | H29: =H$27+H$28 | I29: =I$27+I$28 | J29: =J$27+J$28 | K29: =K$27+K$28 | ... DT29: =DT$27+DT$28
A30: Total Other Revenue | C30: =SUM(D30:DT30) | D30: =IF(D$11=0,0,ROUND(Assumptions!$F$13*(Assumptions!$P$11+Assumptions!$P$12+Assumptions!$P$13+Assumptions!$P$14+Assumptions!$P$15+Assumptions!$P$16)*(1+Assumptions!$P$37)^(D$9-1)/12,0)) | E30: =IF(E$11=0,0,ROUND(Assumptions!$F$13*(Assumptions!$P$11+Assumptions!$P$12+Assumptions!$P$13+Assumptions!$P$14+Assumptions!$P$15+Assumptions!$P$16)*(1+Assumptions!$P$37)^(E$9-1)/12,0)) | F30: =IF(F$11=0,0,ROUND(Assumptions!$F$13*(Assumptions!$P$11+Assumptions!$P$12+Assumptions!$P$13+Assumptions!$P$14+Assumptions!$P$15+Assumptions!$P$16)*(1+Assumptions!$P$37)^(F$9-1)/12,0)) | G30: =IF(G$11=0,0,ROUND(Assumptions!$F$13*(Assumptions!$P$11+Assumptions!$P$12+Assumptions!$P$13+Assumptions!$P$14+Assumptions!$P$15+Assumptions!$P$16)*(1+Assumptions!$P$37)^(G$9-1)/12,0)) | H30: =IF(H$11=0,0,ROUND(Assumptions!$F$13*(Assumptions!$P$11+Assumptions!$P$12+Assumptions!$P$13+Assumptions!$P$14+Assumptions!$P$15+Assumptions!$P$16)*(1+Assumptions!$P$37)^(H$9-1)/12,0)) | I30: =IF(I$11=0,0,ROUND(Assumptions!$F$13*(Assumptions!$P$11+Assumptions!$P$12+Assumptions!$P$13+Assumptions!$P$14+Assumptions!$P$15+Assumptions!$P$16)*(1+Assumptions!$P$37)^(I$9-1)/12,0)) | J30: =IF(J$11=0,0,ROUND(Assumptions!$F$13*(Assumptions!$P$11+Assumptions!$P$12+Assumptions!$P$13+Assumptions!$P$14+Assumptions!$P$15+Assumptions!$P$16)*(1+Assumptions!$P$37)^(J$9-1)/12,0)) | K30: =IF(K$11=0,0,ROUND(Assumptions!$F$13*(Assumptions!$P$11+Assumptions!$P$12+Assumptions!$P$13+Assumptions!$P$14+Assumptions!$P$15+Assumptions!$P$16)*(1+Assumptions!$P$37)^(K$9-1)/12,0)) | ... DT30: =IF(DT$11=0,0,ROUND(Assumptions!$F$13*(Assumptions!$P$11+Assumptions!$P$12+Assumptions!$P$13+Assumptions!$P$14+Assumptions!$P$15+Assumptions!$P$16)*(1+Assumptions!$P$37)^(DT$9-1)/12,0))
A31: Gross Rental Revenue | C31: =SUM(D31:DT31) | D31: =D$25+D$29+D$30 | E31: =E$25+E$29+E$30 | F31: =F$25+F$29+F$30 | G31: =G$25+G$29+G$30 | H31: =H$25+H$29+H$30 | I31: =I$25+I$29+I$30 | J31: =J$25+J$29+J$30 | K31: =K$25+K$29+K$30 | ... DT31: =DT$25+DT$29+DT$30
A33: General Vacancy | C33: =SUM(D33:DT33) | D33: =-D$31*Assumptions!$P$7 | E33: =-E$31*Assumptions!$P$7 | F33: =-F$31*Assumptions!$P$7 | G33: =-G$31*Assumptions!$P$7 | H33: =-H$31*Assumptions!$P$7 | I33: =-I$31*Assumptions!$P$7 | J33: =-J$31*Assumptions!$P$7 | K33: =-K$31*Assumptions!$P$7 | ... DT33: =-DT$31*Assumptions!$P$7
A34: Credit & Collections Loss | C34: =SUM(D34:DT34) | D34: =-D$31*Assumptions!$P$8 | E34: =-E$31*Assumptions!$P$8 | F34: =-F$31*Assumptions!$P$8 | G34: =-G$31*Assumptions!$P$8 | H34: =-H$31*Assumptions!$P$8 | I34: =-I$31*Assumptions!$P$8 | J34: =-J$31*Assumptions!$P$8 | K34: =-K$31*Assumptions!$P$8 | ... DT34: =-DT$31*Assumptions!$P$8
A35: Effective Gross Income | C35: =SUM(D35:DT35) | D35: =D$31+D$33+D$34 | E35: =E$31+E$33+E$34 | F35: =F$31+F$33+F$34 | G35: =G$31+G$33+G$34 | H35: =H$31+H$33+H$34 | I35: =I$31+I$33+I$34 | J35: =J$31+J$33+J$34 | K35: =K$31+K$33+K$34 | ... DT35: =DT$31+DT$33+DT$34
A37: Operating Expenses | C37: =SUM(D37:DT37)
A38: Management Fee (Annual) | C38: =SUM(D38:DT38) | D38: =IF(D$11=0,0,-(Assumptions!$P$19)*(1-(Assumptions!$P$7))*((D$25+D$30)+(IF(Assumptions!$F$13=0,0,D$15/Assumptions!$F$13))*(-(SUM(D$39,D$40,D$41,D$42,D$43,D$44,D$45,D$46,D$47,D$48,D$49,D$50))))/(1-(Assumptions!$P$19)*(1-(Assumptions!$P$7))*(IF(Assumptions!$F$13=0,0,D$15/Assumptions!$F$13)))) | E38: =IF(E$11=0,0,-(Assumptions!$P$19)*(1-(Assumptions!$P$7))*((E$25+E$30)+(IF(Assumptions!$F$13=0,0,E$15/Assumptions!$F$13))*(-(SUM(E$39,E$40,E$41,E$42,E$43,E$44,E$45,E$46,E$47,E$48,E$49,E$50))))/(1-(Assumptions!$P$19)*(1-(Assumptions!$P$7))*(IF(Assumptions!$F$13=0,0,E$15/Assumptions!$F$13)))) | F38: =IF(F$11=0,0,-(Assumptions!$P$19)*(1-(Assumptions!$P$7))*((F$25+F$30)+(IF(Assumptions!$F$13=0,0,F$15/Assumptions!$F$13))*(-(SUM(F$39,F$40,F$41,F$42,F$43,F$44,F$45,F$46,F$47,F$48,F$49,F$50))))/(1-(Assumptions!$P$19)*(1-(Assumptions!$P$7))*(IF(Assumptions!$F$13=0,0,F$15/Assumptions!$F$13)))) | G38: =IF(G$11=0,0,-(Assumptions!$P$19)*(1-(Assumptions!$P$7))*((G$25+G$30)+(IF(Assumptions!$F$13=0,0,G$15/Assumptions!$F$13))*(-(SUM(G$39,G$40,G$41,G$42,G$43,G$44,G$45,G$46,G$47,G$48,G$49,G$50))))/(1-(Assumptions!$P$19)*(1-(Assumptions!$P$7))*(IF(Assumptions!$F$13=0,0,G$15/Assumptions!$F$13)))) | H38: =IF(H$11=0,0,-(Assumptions!$P$19)*(1-(Assumptions!$P$7))*((H$25+H$30)+(IF(Assumptions!$F$13=0,0,H$15/Assumptions!$F$13))*(-(SUM(H$39,H$40,H$41,H$42,H$43,H$44,H$45,H$46,H$47,H$48,H$49,H$50))))/(1-(Assumptions!$P$19)*(1-(Assumptions!$P$7))*(IF(Assumptions!$F$13=0,0,H$15/Assumptions!$F$13)))) | I38: =IF(I$11=0,0,-(Assumptions!$P$19)*(1-(Assumptions!$P$7))*((I$25+I$30)+(IF(Assumptions!$F$13=0,0,I$15/Assumptions!$F$13))*(-(SUM(I$39,I$40,I$41,I$42,I$43,I$44,I$45,I$46,I$47,I$48,I$49,I$50))))/(1-(Assumptions!$P$19)*(1-(Assumptions!$P$7))*(IF(Assumptions!$F$13=0,0,I$15/Assumptions!$F$13)))) | J38: =IF(J$11=0,0,-(Assumptions!$P$19)*(1-(Assumptions!$P$7))*((J$25+J$30)+(IF(Assumptions!$F$13=0,0,J$15/Assumptions!$F$13))*(-(SUM(J$39,J$40,J$41,J$42,J$43,J$44,J$45,J$46,J$47,J$48,J$49,J$50))))/(1-(Assumptions!$P$19)*(1-(Assumptions!$P$7))*(IF(Assumptions!$F$13=0,0,J$15/Assumptions!$F$13)))) | K38: =IF(K$11=0,0,-(Assumptions!$P$19)*(1-(Assumptions!$P$7))*((K$25+K$30)+(IF(Assumptions!$F$13=0,0,K$15/Assumptions!$F$13))*(-(SUM(K$39,K$40,K$41,K$42,K$43,K$44,K$45,K$46,K$47,K$48,K$49,K$50))))/(1-(Assumptions!$P$19)*(1-(Assumptions!$P$7))*(IF(Assumptions!$F$13=0,0,K$15/Assumptions!$F$13)))) | ... DT38: =IF(DT$11=0,0,-(Assumptions!$P$19)*(1-(Assumptions!$P$7))*((DT$25+DT$30)+(IF(Assumptions!$F$13=0,0,DT$15/Assumptions!$F$13))*(-(SUM(DT$39,DT$40,DT$41,DT$42,DT$43,DT$44,DT$45,DT$46,DT$47,DT$48,DT$49,DT$50))))/(1-(Assumptions!$P$19)*(1-(Assumptions!$P$7))*(IF(Assumptions!$F$13=0,0,DT$15/Assumptions!$F$13))))
A39: Insurance (Annual) | C39: =SUM(D39:DT39) | D39: =IF(D$11=0,0,-ROUND(Assumptions!$P$20*(1+Assumptions!$P$38)^(D$9-1)/12,0)) | E39: =IF(E$11=0,0,-ROUND(Assumptions!$P$20*(1+Assumptions!$P$38)^(E$9-1)/12,0)) | F39: =IF(F$11=0,0,-ROUND(Assumptions!$P$20*(1+Assumptions!$P$38)^(F$9-1)/12,0)) | G39: =IF(G$11=0,0,-ROUND(Assumptions!$P$20*(1+Assumptions!$P$38)^(G$9-1)/12,0)) | H39: =IF(H$11=0,0,-ROUND(Assumptions!$P$20*(1+Assumptions!$P$38)^(H$9-1)/12,0)) | I39: =IF(I$11=0,0,-ROUND(Assumptions!$P$20*(1+Assumptions!$P$38)^(I$9-1)/12,0)) | J39: =IF(J$11=0,0,-ROUND(Assumptions!$P$20*(1+Assumptions!$P$38)^(J$9-1)/12,0)) | K39: =IF(K$11=0,0,-ROUND(Assumptions!$P$20*(1+Assumptions!$P$38)^(K$9-1)/12,0)) | ... DT39: =IF(DT$11=0,0,-ROUND(Assumptions!$P$20*(1+Assumptions!$P$38)^(DT$9-1)/12,0))
A40: G&A (Annual) | C40: =SUM(D40:DT40) | D40: =IF(D$11=0,0,-ROUND(Assumptions!$P$21*(1+Assumptions!$P$38)^(D$9-1)/12,0)) | E40: =IF(E$11=0,0,-ROUND(Assumptions!$P$21*(1+Assumptions!$P$38)^(E$9-1)/12,0)) | F40: =IF(F$11=0,0,-ROUND(Assumptions!$P$21*(1+Assumptions!$P$38)^(F$9-1)/12,0)) | G40: =IF(G$11=0,0,-ROUND(Assumptions!$P$21*(1+Assumptions!$P$38)^(G$9-1)/12,0)) | H40: =IF(H$11=0,0,-ROUND(Assumptions!$P$21*(1+Assumptions!$P$38)^(H$9-1)/12,0)) | I40: =IF(I$11=0,0,-ROUND(Assumptions!$P$21*(1+Assumptions!$P$38)^(I$9-1)/12,0)) | J40: =IF(J$11=0,0,-ROUND(Assumptions!$P$21*(1+Assumptions!$P$38)^(J$9-1)/12,0)) | K40: =IF(K$11=0,0,-ROUND(Assumptions!$P$21*(1+Assumptions!$P$38)^(K$9-1)/12,0)) | ... DT40: =IF(DT$11=0,0,-ROUND(Assumptions!$P$21*(1+Assumptions!$P$38)^(DT$9-1)/12,0))
A41: Utilities (Annual) | C41: =SUM(D41:DT41) | D41: =IF(D$11=0,0,-ROUND(Assumptions!$P$22*(1+Assumptions!$P$38)^(D$9-1)/12,0)) | E41: =IF(E$11=0,0,-ROUND(Assumptions!$P$22*(1+Assumptions!$P$38)^(E$9-1)/12,0)) | F41: =IF(F$11=0,0,-ROUND(Assumptions!$P$22*(1+Assumptions!$P$38)^(F$9-1)/12,0)) | G41: =IF(G$11=0,0,-ROUND(Assumptions!$P$22*(1+Assumptions!$P$38)^(G$9-1)/12,0)) | H41: =IF(H$11=0,0,-ROUND(Assumptions!$P$22*(1+Assumptions!$P$38)^(H$9-1)/12,0)) | I41: =IF(I$11=0,0,-ROUND(Assumptions!$P$22*(1+Assumptions!$P$38)^(I$9-1)/12,0)) | J41: =IF(J$11=0,0,-ROUND(Assumptions!$P$22*(1+Assumptions!$P$38)^(J$9-1)/12,0)) | K41: =IF(K$11=0,0,-ROUND(Assumptions!$P$22*(1+Assumptions!$P$38)^(K$9-1)/12,0)) | ... DT41: =IF(DT$11=0,0,-ROUND(Assumptions!$P$22*(1+Assumptions!$P$38)^(DT$9-1)/12,0))
A42: R&M (Annual) | C42: =SUM(D42:DT42) | D42: =IF(D$11=0,0,-ROUND(Assumptions!$P$23*(1+Assumptions!$P$38)^(D$9-1)/12,0)) | E42: =IF(E$11=0,0,-ROUND(Assumptions!$P$23*(1+Assumptions!$P$38)^(E$9-1)/12,0)) | F42: =IF(F$11=0,0,-ROUND(Assumptions!$P$23*(1+Assumptions!$P$38)^(F$9-1)/12,0)) | G42: =IF(G$11=0,0,-ROUND(Assumptions!$P$23*(1+Assumptions!$P$38)^(G$9-1)/12,0)) | H42: =IF(H$11=0,0,-ROUND(Assumptions!$P$23*(1+Assumptions!$P$38)^(H$9-1)/12,0)) | I42: =IF(I$11=0,0,-ROUND(Assumptions!$P$23*(1+Assumptions!$P$38)^(I$9-1)/12,0)) | J42: =IF(J$11=0,0,-ROUND(Assumptions!$P$23*(1+Assumptions!$P$38)^(J$9-1)/12,0)) | K42: =IF(K$11=0,0,-ROUND(Assumptions!$P$23*(1+Assumptions!$P$38)^(K$9-1)/12,0)) | ... DT42: =IF(DT$11=0,0,-ROUND(Assumptions!$P$23*(1+Assumptions!$P$38)^(DT$9-1)/12,0))
A43: Cleaning/Janitorial Services (Annual) | C43: =SUM(D43:DT43) | D43: =IF(D$11=0,0,-ROUND(Assumptions!$P$24*(1+Assumptions!$P$38)^(D$9-1)/12,0)) | E43: =IF(E$11=0,0,-ROUND(Assumptions!$P$24*(1+Assumptions!$P$38)^(E$9-1)/12,0)) | F43: =IF(F$11=0,0,-ROUND(Assumptions!$P$24*(1+Assumptions!$P$38)^(F$9-1)/12,0)) | G43: =IF(G$11=0,0,-ROUND(Assumptions!$P$24*(1+Assumptions!$P$38)^(G$9-1)/12,0)) | H43: =IF(H$11=0,0,-ROUND(Assumptions!$P$24*(1+Assumptions!$P$38)^(H$9-1)/12,0)) | I43: =IF(I$11=0,0,-ROUND(Assumptions!$P$24*(1+Assumptions!$P$38)^(I$9-1)/12,0)) | J43: =IF(J$11=0,0,-ROUND(Assumptions!$P$24*(1+Assumptions!$P$38)^(J$9-1)/12,0)) | K43: =IF(K$11=0,0,-ROUND(Assumptions!$P$24*(1+Assumptions!$P$38)^(K$9-1)/12,0)) | ... DT43: =IF(DT$11=0,0,-ROUND(Assumptions!$P$24*(1+Assumptions!$P$38)^(DT$9-1)/12,0))
A44: Security (Annual) | C44: =SUM(D44:DT44) | D44: =IF(D$11=0,0,-ROUND(Assumptions!$P$25*(1+Assumptions!$P$38)^(D$9-1)/12,0)) | E44: =IF(E$11=0,0,-ROUND(Assumptions!$P$25*(1+Assumptions!$P$38)^(E$9-1)/12,0)) | F44: =IF(F$11=0,0,-ROUND(Assumptions!$P$25*(1+Assumptions!$P$38)^(F$9-1)/12,0)) | G44: =IF(G$11=0,0,-ROUND(Assumptions!$P$25*(1+Assumptions!$P$38)^(G$9-1)/12,0)) | H44: =IF(H$11=0,0,-ROUND(Assumptions!$P$25*(1+Assumptions!$P$38)^(H$9-1)/12,0)) | I44: =IF(I$11=0,0,-ROUND(Assumptions!$P$25*(1+Assumptions!$P$38)^(I$9-1)/12,0)) | J44: =IF(J$11=0,0,-ROUND(Assumptions!$P$25*(1+Assumptions!$P$38)^(J$9-1)/12,0)) | K44: =IF(K$11=0,0,-ROUND(Assumptions!$P$25*(1+Assumptions!$P$38)^(K$9-1)/12,0)) | ... DT44: =IF(DT$11=0,0,-ROUND(Assumptions!$P$25*(1+Assumptions!$P$38)^(DT$9-1)/12,0))
A45: Property Taxes (Fixed) | C45: =SUM(D45:DT45) | D45: =IF(D$11=0,0,-ROUND(Assumptions!$P$27*(1+Assumptions!$P$39)^(D$9-1)/12,0)) | E45: =IF(E$11=0,0,-ROUND(Assumptions!$P$27*(1+Assumptions!$P$39)^(E$9-1)/12,0)) | F45: =IF(F$11=0,0,-ROUND(Assumptions!$P$27*(1+Assumptions!$P$39)^(F$9-1)/12,0)) | G45: =IF(G$11=0,0,-ROUND(Assumptions!$P$27*(1+Assumptions!$P$39)^(G$9-1)/12,0)) | H45: =IF(H$11=0,0,-ROUND(Assumptions!$P$27*(1+Assumptions!$P$39)^(H$9-1)/12,0)) | I45: =IF(I$11=0,0,-ROUND(Assumptions!$P$27*(1+Assumptions!$P$39)^(I$9-1)/12,0)) | J45: =IF(J$11=0,0,-ROUND(Assumptions!$P$27*(1+Assumptions!$P$39)^(J$9-1)/12,0)) | K45: =IF(K$11=0,0,-ROUND(Assumptions!$P$27*(1+Assumptions!$P$39)^(K$9-1)/12,0)) | ... DT45: =IF(DT$11=0,0,-ROUND(Assumptions!$P$27*(1+Assumptions!$P$39)^(DT$9-1)/12,0))
A46: Other Expense 1 (Annual) | C46: =SUM(D46:DT46) | D46: =IF(D$11=0,0,-ROUND(Assumptions!$F$13*Assumptions!$P$28*(1+Assumptions!$P$38)^(D$9-1)/12,0)) | E46: =IF(E$11=0,0,-ROUND(Assumptions!$F$13*Assumptions!$P$28*(1+Assumptions!$P$38)^(E$9-1)/12,0)) | F46: =IF(F$11=0,0,-ROUND(Assumptions!$F$13*Assumptions!$P$28*(1+Assumptions!$P$38)^(F$9-1)/12,0)) | G46: =IF(G$11=0,0,-ROUND(Assumptions!$F$13*Assumptions!$P$28*(1+Assumptions!$P$38)^(G$9-1)/12,0)) | H46: =IF(H$11=0,0,-ROUND(Assumptions!$F$13*Assumptions!$P$28*(1+Assumptions!$P$38)^(H$9-1)/12,0)) | I46: =IF(I$11=0,0,-ROUND(Assumptions!$F$13*Assumptions!$P$28*(1+Assumptions!$P$38)^(I$9-1)/12,0)) | J46: =IF(J$11=0,0,-ROUND(Assumptions!$F$13*Assumptions!$P$28*(1+Assumptions!$P$38)^(J$9-1)/12,0)) | K46: =IF(K$11=0,0,-ROUND(Assumptions!$F$13*Assumptions!$P$28*(1+Assumptions!$P$38)^(K$9-1)/12,0)) | ... DT46: =IF(DT$11=0,0,-ROUND(Assumptions!$F$13*Assumptions!$P$28*(1+Assumptions!$P$38)^(DT$9-1)/12,0))
A47: Other Expense 2 (Annual) | C47: =SUM(D47:DT47) | D47: =IF(D$11=0,0,-ROUND(Assumptions!$F$13*Assumptions!$P$29*(1+Assumptions!$P$38)^(D$9-1)/12,0)) | E47: =IF(E$11=0,0,-ROUND(Assumptions!$F$13*Assumptions!$P$29*(1+Assumptions!$P$38)^(E$9-1)/12,0)) | F47: =IF(F$11=0,0,-ROUND(Assumptions!$F$13*Assumptions!$P$29*(1+Assumptions!$P$38)^(F$9-1)/12,0)) | G47: =IF(G$11=0,0,-ROUND(Assumptions!$F$13*Assumptions!$P$29*(1+Assumptions!$P$38)^(G$9-1)/12,0)) | H47: =IF(H$11=0,0,-ROUND(Assumptions!$F$13*Assumptions!$P$29*(1+Assumptions!$P$38)^(H$9-1)/12,0)) | I47: =IF(I$11=0,0,-ROUND(Assumptions!$F$13*Assumptions!$P$29*(1+Assumptions!$P$38)^(I$9-1)/12,0)) | J47: =IF(J$11=0,0,-ROUND(Assumptions!$F$13*Assumptions!$P$29*(1+Assumptions!$P$38)^(J$9-1)/12,0)) | K47: =IF(K$11=0,0,-ROUND(Assumptions!$F$13*Assumptions!$P$29*(1+Assumptions!$P$38)^(K$9-1)/12,0)) | ... DT47: =IF(DT$11=0,0,-ROUND(Assumptions!$F$13*Assumptions!$P$29*(1+Assumptions!$P$38)^(DT$9-1)/12,0))
A48: Other Expense 3 (Annual) | C48: =SUM(D48:DT48) | D48: =IF(D$11=0,0,-ROUND(Assumptions!$F$13*Assumptions!$P$30*(1+Assumptions!$P$38)^(D$9-1)/12,0)) | E48: =IF(E$11=0,0,-ROUND(Assumptions!$F$13*Assumptions!$P$30*(1+Assumptions!$P$38)^(E$9-1)/12,0)) | F48: =IF(F$11=0,0,-ROUND(Assumptions!$F$13*Assumptions!$P$30*(1+Assumptions!$P$38)^(F$9-1)/12,0)) | G48: =IF(G$11=0,0,-ROUND(Assumptions!$F$13*Assumptions!$P$30*(1+Assumptions!$P$38)^(G$9-1)/12,0)) | H48: =IF(H$11=0,0,-ROUND(Assumptions!$F$13*Assumptions!$P$30*(1+Assumptions!$P$38)^(H$9-1)/12,0)) | I48: =IF(I$11=0,0,-ROUND(Assumptions!$F$13*Assumptions!$P$30*(1+Assumptions!$P$38)^(I$9-1)/12,0)) | J48: =IF(J$11=0,0,-ROUND(Assumptions!$F$13*Assumptions!$P$30*(1+Assumptions!$P$38)^(J$9-1)/12,0)) | K48: =IF(K$11=0,0,-ROUND(Assumptions!$F$13*Assumptions!$P$30*(1+Assumptions!$P$38)^(K$9-1)/12,0)) | ... DT48: =IF(DT$11=0,0,-ROUND(Assumptions!$F$13*Assumptions!$P$30*(1+Assumptions!$P$38)^(DT$9-1)/12,0))
A49: Other Expense 4 (Annual) | C49: =SUM(D49:DT49) | D49: =IF(D$11=0,0,-ROUND(Assumptions!$F$13*Assumptions!$P$31*(1+Assumptions!$P$38)^(D$9-1)/12,0)) | E49: =IF(E$11=0,0,-ROUND(Assumptions!$F$13*Assumptions!$P$31*(1+Assumptions!$P$38)^(E$9-1)/12,0)) | F49: =IF(F$11=0,0,-ROUND(Assumptions!$F$13*Assumptions!$P$31*(1+Assumptions!$P$38)^(F$9-1)/12,0)) | G49: =IF(G$11=0,0,-ROUND(Assumptions!$F$13*Assumptions!$P$31*(1+Assumptions!$P$38)^(G$9-1)/12,0)) | H49: =IF(H$11=0,0,-ROUND(Assumptions!$F$13*Assumptions!$P$31*(1+Assumptions!$P$38)^(H$9-1)/12,0)) | I49: =IF(I$11=0,0,-ROUND(Assumptions!$F$13*Assumptions!$P$31*(1+Assumptions!$P$38)^(I$9-1)/12,0)) | J49: =IF(J$11=0,0,-ROUND(Assumptions!$F$13*Assumptions!$P$31*(1+Assumptions!$P$38)^(J$9-1)/12,0)) | K49: =IF(K$11=0,0,-ROUND(Assumptions!$F$13*Assumptions!$P$31*(1+Assumptions!$P$38)^(K$9-1)/12,0)) | ... DT49: =IF(DT$11=0,0,-ROUND(Assumptions!$F$13*Assumptions!$P$31*(1+Assumptions!$P$38)^(DT$9-1)/12,0))
A50: Other Expense 5 (Annual) | C50: =SUM(D50:DT50) | D50: =IF(D$11=0,0,-ROUND(Assumptions!$F$13*Assumptions!$P$32*(1+Assumptions!$P$38)^(D$9-1)/12,0)) | E50: =IF(E$11=0,0,-ROUND(Assumptions!$F$13*Assumptions!$P$32*(1+Assumptions!$P$38)^(E$9-1)/12,0)) | F50: =IF(F$11=0,0,-ROUND(Assumptions!$F$13*Assumptions!$P$32*(1+Assumptions!$P$38)^(F$9-1)/12,0)) | G50: =IF(G$11=0,0,-ROUND(Assumptions!$F$13*Assumptions!$P$32*(1+Assumptions!$P$38)^(G$9-1)/12,0)) | H50: =IF(H$11=0,0,-ROUND(Assumptions!$F$13*Assumptions!$P$32*(1+Assumptions!$P$38)^(H$9-1)/12,0)) | I50: =IF(I$11=0,0,-ROUND(Assumptions!$F$13*Assumptions!$P$32*(1+Assumptions!$P$38)^(I$9-1)/12,0)) | J50: =IF(J$11=0,0,-ROUND(Assumptions!$F$13*Assumptions!$P$32*(1+Assumptions!$P$38)^(J$9-1)/12,0)) | K50: =IF(K$11=0,0,-ROUND(Assumptions!$F$13*Assumptions!$P$32*(1+Assumptions!$P$38)^(K$9-1)/12,0)) | ... DT50: =IF(DT$11=0,0,-ROUND(Assumptions!$F$13*Assumptions!$P$32*(1+Assumptions!$P$38)^(DT$9-1)/12,0))
A52: Total Recoverable Operating Expenses | C52: =SUM(D52:DT52) | D52: =SUM(D$38,D$39,D$40,D$41,D$42,D$43,D$44,D$45,D$46,D$47,D$48,D$49,D$50) | E52: =SUM(E$38,E$39,E$40,E$41,E$42,E$43,E$44,E$45,E$46,E$47,E$48,E$49,E$50) | F52: =SUM(F$38,F$39,F$40,F$41,F$42,F$43,F$44,F$45,F$46,F$47,F$48,F$49,F$50) | G52: =SUM(G$38,G$39,G$40,G$41,G$42,G$43,G$44,G$45,G$46,G$47,G$48,G$49,G$50) | H52: =SUM(H$38,H$39,H$40,H$41,H$42,H$43,H$44,H$45,H$46,H$47,H$48,H$49,H$50) | I52: =SUM(I$38,I$39,I$40,I$41,I$42,I$43,I$44,I$45,I$46,I$47,I$48,I$49,I$50) | J52: =SUM(J$38,J$39,J$40,J$41,J$42,J$43,J$44,J$45,J$46,J$47,J$48,J$49,J$50) | K52: =SUM(K$38,K$39,K$40,K$41,K$42,K$43,K$44,K$45,K$46,K$47,K$48,K$49,K$50) | ... DT52: =SUM(DT$38,DT$39,DT$40,DT$41,DT$42,DT$43,DT$44,DT$45,DT$46,DT$47,DT$48,DT$49,DT$50)
A53: Non-Recoverable OpEx (Annual) | C53: =SUM(D53:DT53) | D53: =IF(D$11=0,0,-ROUND(Assumptions!$P$26*(1+Assumptions!$P$38)^(D$9-1)/12,0)) | E53: =IF(E$11=0,0,-ROUND(Assumptions!$P$26*(1+Assumptions!$P$38)^(E$9-1)/12,0)) | F53: =IF(F$11=0,0,-ROUND(Assumptions!$P$26*(1+Assumptions!$P$38)^(F$9-1)/12,0)) | G53: =IF(G$11=0,0,-ROUND(Assumptions!$P$26*(1+Assumptions!$P$38)^(G$9-1)/12,0)) | H53: =IF(H$11=0,0,-ROUND(Assumptions!$P$26*(1+Assumptions!$P$38)^(H$9-1)/12,0)) | I53: =IF(I$11=0,0,-ROUND(Assumptions!$P$26*(1+Assumptions!$P$38)^(I$9-1)/12,0)) | J53: =IF(J$11=0,0,-ROUND(Assumptions!$P$26*(1+Assumptions!$P$38)^(J$9-1)/12,0)) | K53: =IF(K$11=0,0,-ROUND(Assumptions!$P$26*(1+Assumptions!$P$38)^(K$9-1)/12,0)) | ... DT53: =IF(DT$11=0,0,-ROUND(Assumptions!$P$26*(1+Assumptions!$P$38)^(DT$9-1)/12,0))
A54: Total Operating Expenses | C54: =SUM(D54:DT54) | D54: =D$52+D$53 | E54: =E$52+E$53 | F54: =F$52+F$53 | G54: =G$52+G$53 | H54: =H$52+H$53 | I54: =I$52+I$53 | J54: =J$52+J$53 | K54: =K$52+K$53 | ... DT54: =DT$52+DT$53
A56: Net Operating Income | C56: =SUM(D56:DT56) | D56: =D$35+D$54+D$61 | E56: =E$35+E$54+E$61 | F56: =F$35+F$54+F$61 | G56: =G$35+G$54+G$61 | H56: =H$35+H$54+H$61 | I56: =I$35+I$54+I$61 | J56: =J$35+J$54+J$61 | K56: =K$35+K$54+K$61 | ... DT56: =DT$35+DT$54+DT$61
A57: DSCR | D57: =IF(IF(D$11=0,0,IF(D$11<=36,-D$183,-D$191))=0,"N/A",D$56/IF(D$11=0,0,IF(D$11<=36,-D$183,-D$191))) | E57: =IF(IF(E$11=0,0,IF(E$11<=36,-E$183,-E$191))=0,"N/A",E$56/IF(E$11=0,0,IF(E$11<=36,-E$183,-E$191))) | F57: =IF(IF(F$11=0,0,IF(F$11<=36,-F$183,-F$191))=0,"N/A",F$56/IF(F$11=0,0,IF(F$11<=36,-F$183,-F$191))) | G57: =IF(IF(G$11=0,0,IF(G$11<=36,-G$183,-G$191))=0,"N/A",G$56/IF(G$11=0,0,IF(G$11<=36,-G$183,-G$191))) | H57: =IF(IF(H$11=0,0,IF(H$11<=36,-H$183,-H$191))=0,"N/A",H$56/IF(H$11=0,0,IF(H$11<=36,-H$183,-H$191))) | I57: =IF(IF(I$11=0,0,IF(I$11<=36,-I$183,-I$191))=0,"N/A",I$56/IF(I$11=0,0,IF(I$11<=36,-I$183,-I$191))) | J57: =IF(IF(J$11=0,0,IF(J$11<=36,-J$183,-J$191))=0,"N/A",J$56/IF(J$11=0,0,IF(J$11<=36,-J$183,-J$191))) | K57: =IF(IF(K$11=0,0,IF(K$11<=36,-K$183,-K$191))=0,"N/A",K$56/IF(K$11=0,0,IF(K$11<=36,-K$183,-K$191))) | ... DT57: =IF(IF(DT$11=0,0,IF(DT$11<=36,-DT$183,-DT$191))=0,"N/A",DT$56/IF(DT$11=0,0,IF(DT$11<=36,-DT$183,-DT$191)))
A59: Non-Operating Expenses | C59: =SUM(D59:DT59)
A60: Non-Operating Expenses | C60: =SUM(D60:DT60) | D60: =IF(D$11=0,0,-ROUND(Assumptions!$F$13*Assumptions!$P$33*(1+Assumptions!$P$38)^(D$9-1)/12,0)) | E60: =IF(E$11=0,0,-ROUND(Assumptions!$F$13*Assumptions!$P$33*(1+Assumptions!$P$38)^(E$9-1)/12,0)) | F60: =IF(F$11=0,0,-ROUND(Assumptions!$F$13*Assumptions!$P$33*(1+Assumptions!$P$38)^(F$9-1)/12,0)) | G60: =IF(G$11=0,0,-ROUND(Assumptions!$F$13*Assumptions!$P$33*(1+Assumptions!$P$38)^(G$9-1)/12,0)) | H60: =IF(H$11=0,0,-ROUND(Assumptions!$F$13*Assumptions!$P$33*(1+Assumptions!$P$38)^(H$9-1)/12,0)) | I60: =IF(I$11=0,0,-ROUND(Assumptions!$F$13*Assumptions!$P$33*(1+Assumptions!$P$38)^(I$9-1)/12,0)) | J60: =IF(J$11=0,0,-ROUND(Assumptions!$F$13*Assumptions!$P$33*(1+Assumptions!$P$38)^(J$9-1)/12,0)) | K60: =IF(K$11=0,0,-ROUND(Assumptions!$F$13*Assumptions!$P$33*(1+Assumptions!$P$38)^(K$9-1)/12,0)) | ... DT60: =IF(DT$11=0,0,-ROUND(Assumptions!$F$13*Assumptions!$P$33*(1+Assumptions!$P$38)^(DT$9-1)/12,0))
A61: Total Non-Operating Expenses | C61: =SUM(D61:DT61) | D61: =D$60 | E61: =E$60 | F61: =F$60 | G61: =G$60 | H61: =H$60 | I61: =I$60 | J61: =J$60 | K61: =K$60 | ... DT61: =DT$60
A63: Capital Expenditures | C63: =SUM(D63:DT63)
A64: Base Tenant Improvements | C64: =SUM(D64:DT64) | D64: =IF(D$11=FB141,-'Rent Roll'!$B$9*'Rent Roll'!$L$9,0)+IF(D$11=FB142,-'Rent Roll'!$B$10*'Rent Roll'!$L$10,0)+IF(D$11=FB143,-'Rent Roll'!$B$11*'Rent Roll'!$L$11,0)+IF(D$11=FB144,-'Rent Roll'!$B$12*'Rent Roll'!$L$12,0)+IF(D$11=FB145,-'Rent Roll'!$B$13*'Rent Roll'!$L$13,0) | E64: =IF(E$11=FB141,-'Rent Roll'!$B$9*'Rent Roll'!$L$9,0)+IF(E$11=FB142,-'Rent Roll'!$B$10*'Rent Roll'!$L$10,0)+IF(E$11=FB143,-'Rent Roll'!$B$11*'Rent Roll'!$L$11,0)+IF(E$11=FB144,-'Rent Roll'!$B$12*'Rent Roll'!$L$12,0)+IF(E$11=FB145,-'Rent Roll'!$B$13*'Rent Roll'!$L$13,0) | F64: =IF(F$11=FB141,-'Rent Roll'!$B$9*'Rent Roll'!$L$9,0)+IF(F$11=FB142,-'Rent Roll'!$B$10*'Rent Roll'!$L$10,0)+IF(F$11=FB143,-'Rent Roll'!$B$11*'Rent Roll'!$L$11,0)+IF(F$11=FB144,-'Rent Roll'!$B$12*'Rent Roll'!$L$12,0)+IF(F$11=FB145,-'Rent Roll'!$B$13*'Rent Roll'!$L$13,0) | G64: =IF(G$11=FB141,-'Rent Roll'!$B$9*'Rent Roll'!$L$9,0)+IF(G$11=FB142,-'Rent Roll'!$B$10*'Rent Roll'!$L$10,0)+IF(G$11=FB143,-'Rent Roll'!$B$11*'Rent Roll'!$L$11,0)+IF(G$11=FB144,-'Rent Roll'!$B$12*'Rent Roll'!$L$12,0)+IF(G$11=FB145,-'Rent Roll'!$B$13*'Rent Roll'!$L$13,0) | H64: =IF(H$11=FB141,-'Rent Roll'!$B$9*'Rent Roll'!$L$9,0)+IF(H$11=FB142,-'Rent Roll'!$B$10*'Rent Roll'!$L$10,0)+IF(H$11=FB143,-'Rent Roll'!$B$11*'Rent Roll'!$L$11,0)+IF(H$11=FB144,-'Rent Roll'!$B$12*'Rent Roll'!$L$12,0)+IF(H$11=FB145,-'Rent Roll'!$B$13*'Rent Roll'!$L$13,0) | I64: =IF(I$11=FB141,-'Rent Roll'!$B$9*'Rent Roll'!$L$9,0)+IF(I$11=FB142,-'Rent Roll'!$B$10*'Rent Roll'!$L$10,0)+IF(I$11=FB143,-'Rent Roll'!$B$11*'Rent Roll'!$L$11,0)+IF(I$11=FB144,-'Rent Roll'!$B$12*'Rent Roll'!$L$12,0)+IF(I$11=FB145,-'Rent Roll'!$B$13*'Rent Roll'!$L$13,0) | J64: =IF(J$11=FB141,-'Rent Roll'!$B$9*'Rent Roll'!$L$9,0)+IF(J$11=FB142,-'Rent Roll'!$B$10*'Rent Roll'!$L$10,0)+IF(J$11=FB143,-'Rent Roll'!$B$11*'Rent Roll'!$L$11,0)+IF(J$11=FB144,-'Rent Roll'!$B$12*'Rent Roll'!$L$12,0)+IF(J$11=FB145,-'Rent Roll'!$B$13*'Rent Roll'!$L$13,0) | K64: =IF(K$11=FB141,-'Rent Roll'!$B$9*'Rent Roll'!$L$9,0)+IF(K$11=FB142,-'Rent Roll'!$B$10*'Rent Roll'!$L$10,0)+IF(K$11=FB143,-'Rent Roll'!$B$11*'Rent Roll'!$L$11,0)+IF(K$11=FB144,-'Rent Roll'!$B$12*'Rent Roll'!$L$12,0)+IF(K$11=FB145,-'Rent Roll'!$B$13*'Rent Roll'!$L$13,0) | L64: =IF(L$11=FB141,-'Rent Roll'!$B$9*'Rent Roll'!$L$9,0)+IF(L$11=FB142,-'Rent Roll'!$B$10*'Rent Roll'!$L$10,0)+IF(L$11=FB143,-'Rent Roll'!$B$11*'Rent Roll'!$L$11,0)+IF(L$11=FB144,-'Rent Roll'!$B$12*'Rent Roll'!$L$12,0)+IF(L$11=FB145,-'Rent Roll'!$B$13*'Rent Roll'!$L$13,0) | M64: =IF(M$11=FB141,-'Rent Roll'!$B$9*'Rent Roll'!$L$9,0)+IF(M$11=FB142,-'Rent Roll'!$B$10*'Rent Roll'!$L$10,0)+IF(M$11=FB143,-'Rent Roll'!$B$11*'Rent Roll'!$L$11,0)+IF(M$11=FB144,-'Rent Roll'!$B$12*'Rent Roll'!$L$12,0)+IF(M$11=FB145,-'Rent Roll'!$B$13*'Rent Roll'!$L$13,0) | N64: =IF(N$11=FB141,-'Rent Roll'!$B$9*'Rent Roll'!$L$9,0)+IF(N$11=FB142,-'Rent Roll'!$B$10*'Rent Roll'!$L$10,0)+IF(N$11=FB143,-'Rent Roll'!$B$11*'Rent Roll'!$L$11,0)+IF(N$11=FB144,-'Rent Roll'!$B$12*'Rent Roll'!$L$12,0)+IF(N$11=FB145,-'Rent Roll'!$B$13*'Rent Roll'!$L$13,0) | O64: =IF(O$11=FB141,-'Rent Roll'!$B$9*'Rent Roll'!$L$9,0)+IF(O$11=FB142,-'Rent Roll'!$B$10*'Rent Roll'!$L$10,0)+IF(O$11=FB143,-'Rent Roll'!$B$11*'Rent Roll'!$L$11,0)+IF(O$11=FB144,-'Rent Roll'!$B$12*'Rent Roll'!$L$12,0)+IF(O$11=FB145,-'Rent Roll'!$B$13*'Rent Roll'!$L$13,0) | P64: =IF(P$11=FB141,-'Rent Roll'!$B$9*'Rent Roll'!$L$9,0)+IF(P$11=FB142,-'Rent Roll'!$B$10*'Rent Roll'!$L$10,0)+IF(P$11=FB143,-'Rent Roll'!$B$11*'Rent Roll'!$L$11,0)+IF(P$11=FB144,-'Rent Roll'!$B$12*'Rent Roll'!$L$12,0)+IF(P$11=FB145,-'Rent Roll'!$B$13*'Rent Roll'!$L$13,0) | Q64: =IF(Q$11=FB141,-'Rent Roll'!$B$9*'Rent Roll'!$L$9,0)+IF(Q$11=FB142,-'Rent Roll'!$B$10*'Rent Roll'!$L$10,0)+IF(Q$11=FB143,-'Rent Roll'!$B$11*'Rent Roll'!$L$11,0)+IF(Q$11=FB144,-'Rent Roll'!$B$12*'Rent Roll'!$L$12,0)+IF(Q$11=FB145,-'Rent Roll'!$B$13*'Rent Roll'!$L$13,0) | R64: =IF(R$11=FB141,-'Rent Roll'!$B$9*'Rent Roll'!$L$9,0)+IF(R$11=FB142,-'Rent Roll'!$B$10*'Rent Roll'!$L$10,0)+IF(R$11=FB143,-'Rent Roll'!$B$11*'Rent Roll'!$L$11,0)+IF(R$11=FB144,-'Rent Roll'!$B$12*'Rent Roll'!$L$12,0)+IF(R$11=FB145,-'Rent Roll'!$B$13*'Rent Roll'!$L$13,0) | S64: =IF(S$11=FB141,-'Rent Roll'!$B$9*'Rent Roll'!$L$9,0)+IF(S$11=FB142,-'Rent Roll'!$B$10*'Rent Roll'!$L$10,0)+IF(S$11=FB143,-'Rent Roll'!$B$11*'Rent Roll'!$L$11,0)+IF(S$11=FB144,-'Rent Roll'!$B$12*'Rent Roll'!$L$12,0)+IF(S$11=FB145,-'Rent Roll'!$B$13*'Rent Roll'!$L$13,0) | T64: =IF(T$11=FB141,-'Rent Roll'!$B$9*'Rent Roll'!$L$9,0)+IF(T$11=FB142,-'Rent Roll'!$B$10*'Rent Roll'!$L$10,0)+IF(T$11=FB143,-'Rent Roll'!$B$11*'Rent Roll'!$L$11,0)+IF(T$11=FB144,-'Rent Roll'!$B$12*'Rent Roll'!$L$12,0)+IF(T$11=FB145,-'Rent Roll'!$B$13*'Rent Roll'!$L$13,0) | U64: =IF(U$11=FB141,-'Rent Roll'!$B$9*'Rent Roll'!$L$9,0)+IF(U$11=FB142,-'Rent Roll'!$B$10*'Rent Roll'!$L$10,0)+IF(U$11=FB143,-'Rent Roll'!$B$11*'Rent Roll'!$L$11,0)+IF(U$11=FB144,-'Rent Roll'!$B$12*'Rent Roll'!$L$12,0)+IF(U$11=FB145,-'Rent Roll'!$B$13*'Rent Roll'!$L$13,0) | V64: =IF(V$11=FB141,-'Rent Roll'!$B$9*'Rent Roll'!$L$9,0)+IF(V$11=FB142,-'Rent Roll'!$B$10*'Rent Roll'!$L$10,0)+IF(V$11=FB143,-'Rent Roll'!$B$11*'Rent Roll'!$L$11,0)+IF(V$11=FB144,-'Rent Roll'!$B$12*'Rent Roll'!$L$12,0)+IF(V$11=FB145,-'Rent Roll'!$B$13*'Rent Roll'!$L$13,0) | W64: =IF(W$11=FB141,-'Rent Roll'!$B$9*'Rent Roll'!$L$9,0)+IF(W$11=FB142,-'Rent Roll'!$B$10*'Rent Roll'!$L$10,0)+IF(W$11=FB143,-'Rent Roll'!$B$11*'Rent Roll'!$L$11,0)+IF(W$11=FB144,-'Rent Roll'!$B$12*'Rent Roll'!$L$12,0)+IF(W$11=FB145,-'Rent Roll'!$B$13*'Rent Roll'!$L$13,0) | X64: =IF(X$11=FB141,-'Rent Roll'!$B$9*'Rent Roll'!$L$9,0)+IF(X$11=FB142,-'Rent Roll'!$B$10*'Rent Roll'!$L$10,0)+IF(X$11=FB143,-'Rent Roll'!$B$11*'Rent Roll'!$L$11,0)+IF(X$11=FB144,-'Rent Roll'!$B$12*'Rent Roll'!$L$12,0)+IF(X$11=FB145,-'Rent Roll'!$B$13*'Rent Roll'!$L$13,0) | Y64: =IF(Y$11=FB141,-'Rent Roll'!$B$9*'Rent Roll'!$L$9,0)+IF(Y$11=FB142,-'Rent Roll'!$B$10*'Rent Roll'!$L$10,0)+IF(Y$11=FB143,-'Rent Roll'!$B$11*'Rent Roll'!$L$11,0)+IF(Y$11=FB144,-'Rent Roll'!$B$12*'Rent Roll'!$L$12,0)+IF(Y$11=FB145,-'Rent Roll'!$B$13*'Rent Roll'!$L$13,0) | Z64: =IF(Z$11=FB141,-'Rent Roll'!$B$9*'Rent Roll'!$L$9,0)+IF(Z$11=FB142,-'Rent Roll'!$B$10*'Rent Roll'!$L$10,0)+IF(Z$11=FB143,-'Rent Roll'!$B$11*'Rent Roll'!$L$11,0)+IF(Z$11=FB144,-'Rent Roll'!$B$12*'Rent Roll'!$L$12,0)+IF(Z$11=FB145,-'Rent Roll'!$B$13*'Rent Roll'!$L$13,0) | AA64: =IF(AA$11=FB141,-'Rent Roll'!$B$9*'Rent Roll'!$L$9,0)+IF(AA$11=FB142,-'Rent Roll'!$B$10*'Rent Roll'!$L$10,0)+IF(AA$11=FB143,-'Rent Roll'!$B$11*'Rent Roll'!$L$11,0)+IF(AA$11=FB144,-'Rent Roll'!$B$12*'Rent Roll'!$L$12,0)+IF(AA$11=FB145,-'Rent Roll'!$B$13*'Rent Roll'!$L$13,0) | AB64: =IF(AB$11=FB141,-'Rent Roll'!$B$9*'Rent Roll'!$L$9,0)+IF(AB$11=FB142,-'Rent Roll'!$B$10*'Rent Roll'!$L$10,0)+IF(AB$11=FB143,-'Rent Roll'!$B$11*'Rent Roll'!$L$11,0)+IF(AB$11=FB144,-'Rent Roll'!$B$12*'Rent Roll'!$L$12,0)+IF(AB$11=FB145,-'Rent Roll'!$B$13*'Rent Roll'!$L$13,0) | AC64: =IF(AC$11=FB141,-'Rent Roll'!$B$9*'Rent Roll'!$L$9,0)+IF(AC$11=FB142,-'Rent Roll'!$B$10*'Rent Roll'!$L$10,0)+IF(AC$11=FB143,-'Rent Roll'!$B$11*'Rent Roll'!$L$11,0)+IF(AC$11=FB144,-'Rent Roll'!$B$12*'Rent Roll'!$L$12,0)+IF(AC$11=FB145,-'Rent Roll'!$B$13*'Rent Roll'!$L$13,0) | AD64: =IF(AD$11=FB141,-'Rent Roll'!$B$9*'Rent Roll'!$L$9,0)+IF(AD$11=FB142,-'Rent Roll'!$B$10*'Rent Roll'!$L$10,0)+IF(AD$11=FB143,-'Rent Roll'!$B$11*'Rent Roll'!$L$11,0)+IF(AD$11=FB144,-'Rent Roll'!$B$12*'Rent Roll'!$L$12,0)+IF(AD$11=FB145,-'Rent Roll'!$B$13*'Rent Roll'!$L$13,0) | AE64: =IF(AE$11=FB141,-'Rent Roll'!$B$9*'Rent Roll'!$L$9,0)+IF(AE$11=FB142,-'Rent Roll'!$B$10*'Rent Roll'!$L$10,0)+IF(AE$11=FB143,-'Rent Roll'!$B$11*'Rent Roll'!$L$11,0)+IF(AE$11=FB144,-'Rent Roll'!$B$12*'Rent Roll'!$L$12,0)+IF(AE$11=FB145,-'Rent Roll'!$B$13*'Rent Roll'!$L$13,0) | AF64: =IF(AF$11=FB141,-'Rent Roll'!$B$9*'Rent Roll'!$L$9,0)+IF(AF$11=FB142,-'Rent Roll'!$B$10*'Rent Roll'!$L$10,0)+IF(AF$11=FB143,-'Rent Roll'!$B$11*'Rent Roll'!$L$11,0)+IF(AF$11=FB144,-'Rent Roll'!$B$12*'Rent Roll'!$L$12,0)+IF(AF$11=FB145,-'Rent Roll'!$B$13*'Rent Roll'!$L$13,0) | AG64: =IF(AG$11=FB141,-'Rent Roll'!$B$9*'Rent Roll'!$L$9,0)+IF(AG$11=FB142,-'Rent Roll'!$B$10*'Rent Roll'!$L$10,0)+IF(AG$11=FB143,-'Rent Roll'!$B$11*'Rent Roll'!$L$11,0)+IF(AG$11=FB144,-'Rent Roll'!$B$12*'Rent Roll'!$L$12,0)+IF(AG$11=FB145,-'Rent Roll'!$B$13*'Rent Roll'!$L$13,0) | AH64: =IF(AH$11=FB141,-'Rent Roll'!$B$9*'Rent Roll'!$L$9,0)+IF(AH$11=FB142,-'Rent Roll'!$B$10*'Rent Roll'!$L$10,0)+IF(AH$11=FB143,-'Rent Roll'!$B$11*'Rent Roll'!$L$11,0)+IF(AH$11=FB144,-'Rent Roll'!$B$12*'Rent Roll'!$L$12,0)+IF(AH$11=FB145,-'Rent Roll'!$B$13*'Rent Roll'!$L$13,0) | AI64: =IF(AI$11=FB141,-'Rent Roll'!$B$9*'Rent Roll'!$L$9,0)+IF(AI$11=FB142,-'Rent Roll'!$B$10*'Rent Roll'!$L$10,0)+IF(AI$11=FB143,-'Rent Roll'!$B$11*'Rent Roll'!$L$11,0)+IF(AI$11=FB144,-'Rent Roll'!$B$12*'Rent Roll'!$L$12,0)+IF(AI$11=FB145,-'Rent Roll'!$B$13*'Rent Roll'!$L$13,0) | AJ64: =IF(AJ$11=FB141,-'Rent Roll'!$B$9*'Rent Roll'!$L$9,0)+IF(AJ$11=FB142,-'Rent Roll'!$B$10*'Rent Roll'!$L$10,0)+IF(AJ$11=FB143,-'Rent Roll'!$B$11*'Rent Roll'!$L$11,0)+IF(AJ$11=FB144,-'Rent Roll'!$B$12*'Rent Roll'!$L$12,0)+IF(AJ$11=FB145,-'Rent Roll'!$B$13*'Rent Roll'!$L$13,0) | AK64: =IF(AK$11=FB141,-'Rent Roll'!$B$9*'Rent Roll'!$L$9,0)+IF(AK$11=FB142,-'Rent Roll'!$B$10*'Rent Roll'!$L$10,0)+IF(AK$11=FB143,-'Rent Roll'!$B$11*'Rent Roll'!$L$11,0)+IF(AK$11=FB144,-'Rent Roll'!$B$12*'Rent Roll'!$L$12,0)+IF(AK$11=FB145,-'Rent Roll'!$B$13*'Rent Roll'!$L$13,0) | AL64: =IF(AL$11=FB141,-'Rent Roll'!$B$9*'Rent Roll'!$L$9,0)+IF(AL$11=FB142,-'Rent Roll'!$B$10*'Rent Roll'!$L$10,0)+IF(AL$11=FB143,-'Rent Roll'!$B$11*'Rent Roll'!$L$11,0)+IF(AL$11=FB144,-'Rent Roll'!$B$12*'Rent Roll'!$L$12,0)+IF(AL$11=FB145,-'Rent Roll'!$B$13*'Rent Roll'!$L$13,0) | AM64: =IF(AM$11=FB141,-'Rent Roll'!$B$9*'Rent Roll'!$L$9,0)+IF(AM$11=FB142,-'Rent Roll'!$B$10*'Rent Roll'!$L$10,0)+IF(AM$11=FB143,-'Rent Roll'!$B$11*'Rent Roll'!$L$11,0)+IF(AM$11=FB144,-'Rent Roll'!$B$12*'Rent Roll'!$L$12,0)+IF(AM$11=FB145,-'Rent Roll'!$B$13*'Rent Roll'!$L$13,0) | AN64: =IF(AN$11=FB141,-'Rent Roll'!$B$9*'Rent Roll'!$L$9,0)+IF(AN$11=FB142,-'Rent Roll'!$B$10*'Rent Roll'!$L$10,0)+IF(AN$11=FB143,-'Rent Roll'!$B$11*'Rent Roll'!$L$11,0)+IF(AN$11=FB144,-'Rent Roll'!$B$12*'Rent Roll'!$L$12,0)+IF(AN$11=FB145,-'Rent Roll'!$B$13*'Rent Roll'!$L$13,0) | AO64: =IF(AO$11=FB141,-'Rent Roll'!$B$9*'Rent Roll'!$L$9,0)+IF(AO$11=FB142,-'Rent Roll'!$B$10*'Rent Roll'!$L$10,0)+IF(AO$11=FB143,-'Rent Roll'!$B$11*'Rent Roll'!$L$11,0)+IF(AO$11=FB144,-'Rent Roll'!$B$12*'Rent Roll'!$L$12,0)+IF(AO$11=FB145,-'Rent Roll'!$B$13*'Rent Roll'!$L$13,0) | AP64: =IF(AP$11=FB141,-'Rent Roll'!$B$9*'Rent Roll'!$L$9,0)+IF(AP$11=FB142,-'Rent Roll'!$B$10*'Rent Roll'!$L$10,0)+IF(AP$11=FB143,-'Rent Roll'!$B$11*'Rent Roll'!$L$11,0)+IF(AP$11=FB144,-'Rent Roll'!$B$12*'Rent Roll'!$L$12,0)+IF(AP$11=FB145,-'Rent Roll'!$B$13*'Rent Roll'!$L$13,0) | AQ64: =IF(AQ$11=FB141,-'Rent Roll'!$B$9*'Rent Roll'!$L$9,0)+IF(AQ$11=FB142,-'Rent Roll'!$B$10*'Rent Roll'!$L$10,0)+IF(AQ$11=FB143,-'Rent Roll'!$B$11*'Rent Roll'!$L$11,0)+IF(AQ$11=FB144,-'Rent Roll'!$B$12*'Rent Roll'!$L$12,0)+IF(AQ$11=FB145,-'Rent Roll'!$B$13*'Rent Roll'!$L$13,0) | AR64: =IF(AR$11=FB141,-'Rent Roll'!$B$9*'Rent Roll'!$L$9,0)+IF(AR$11=FB142,-'Rent Roll'!$B$10*'Rent Roll'!$L$10,0)+IF(AR$11=FB143,-'Rent Roll'!$B$11*'Rent Roll'!$L$11,0)+IF(AR$11=FB144,-'Rent Roll'!$B$12*'Rent Roll'!$L$12,0)+IF(AR$11=FB145,-'Rent Roll'!$B$13*'Rent Roll'!$L$13,0) | AS64: =IF(AS$11=FB141,-'Rent Roll'!$B$9*'Rent Roll'!$L$9,0)+IF(AS$11=FB142,-'Rent Roll'!$B$10*'Rent Roll'!$L$10,0)+IF(AS$11=FB143,-'Rent Roll'!$B$11*'Rent Roll'!$L$11,0)+IF(AS$11=FB144,-'Rent Roll'!$B$12*'Rent Roll'!$L$12,0)+IF(AS$11=FB145,-'Rent Roll'!$B$13*'Rent Roll'!$L$13,0) | AT64: =IF(AT$11=FB141,-'Rent Roll'!$B$9*'Rent Roll'!$L$9,0)+IF(AT$11=FB142,-'Rent Roll'!$B$10*'Rent Roll'!$L$10,0)+IF(AT$11=FB143,-'Rent Roll'!$B$11*'Rent Roll'!$L$11,0)+IF(AT$11=FB144,-'Rent Roll'!$B$12*'Rent Roll'!$L$12,0)+IF(AT$11=FB145,-'Rent Roll'!$B$13*'Rent Roll'!$L$13,0) | AU64: =IF(AU$11=FB141,-'Rent Roll'!$B$9*'Rent Roll'!$L$9,0)+IF(AU$11=FB142,-'Rent Roll'!$B$10*'Rent Roll'!$L$10,0)+IF(AU$11=FB143,-'Rent Roll'!$B$11*'Rent Roll'!$L$11,0)+IF(AU$11=FB144,-'Rent Roll'!$B$12*'Rent Roll'!$L$12,0)+IF(AU$11=FB145,-'Rent Roll'!$B$13*'Rent Roll'!$L$13,0) | AV64: =IF(AV$11=FB141,-'Rent Roll'!$B$9*'Rent Roll'!$L$9,0)+IF(AV$11=FB142,-'Rent Roll'!$B$10*'Rent Roll'!$L$10,0)+IF(AV$11=FB143,-'Rent Roll'!$B$11*'Rent Roll'!$L$11,0)+IF(AV$11=FB144,-'Rent Roll'!$B$12*'Rent Roll'!$L$12,0)+IF(AV$11=FB145,-'Rent Roll'!$B$13*'Rent Roll'!$L$13,0) | AW64: =IF(AW$11=FB141,-'Rent Roll'!$B$9*'Rent Roll'!$L$9,0)+IF(AW$11=FB142,-'Rent Roll'!$B$10*'Rent Roll'!$L$10,0)+IF(AW$11=FB143,-'Rent Roll'!$B$11*'Rent Roll'!$L$11,0)+IF(AW$11=FB144,-'Rent Roll'!$B$12*'Rent Roll'!$L$12,0)+IF(AW$11=FB145,-'Rent Roll'!$B$13*'Rent Roll'!$L$13,0) | AX64: =IF(AX$11=FB141,-'Rent Roll'!$B$9*'Rent Roll'!$L$9,0)+IF(AX$11=FB142,-'Rent Roll'!$B$10*'Rent Roll'!$L$10,0)+IF(AX$11=FB143,-'Rent Roll'!$B$11*'Rent Roll'!$L$11,0)+IF(AX$11=FB144,-'Rent Roll'!$B$12*'Rent Roll'!$L$12,0)+IF(AX$11=FB145,-'Rent Roll'!$B$13*'Rent Roll'!$L$13,0) | AY64: =IF(AY$11=FB141,-'Rent Roll'!$B$9*'Rent Roll'!$L$9,0)+IF(AY$11=FB142,-'Rent Roll'!$B$10*'Rent Roll'!$L$10,0)+IF(AY$11=FB143,-'Rent Roll'!$B$11*'Rent Roll'!$L$11,0)+IF(AY$11=FB144,-'Rent Roll'!$B$12*'Rent Roll'!$L$12,0)+IF(AY$11=FB145,-'Rent Roll'!$B$13*'Rent Roll'!$L$13,0) | AZ64: =IF(AZ$11=FB141,-'Rent Roll'!$B$9*'Rent Roll'!$L$9,0)+IF(AZ$11=FB142,-'Rent Roll'!$B$10*'Rent Roll'!$L$10,0)+IF(AZ$11=FB143,-'Rent Roll'!$B$11*'Rent Roll'!$L$11,0)+IF(AZ$11=FB144,-'Rent Roll'!$B$12*'Rent Roll'!$L$12,0)+IF(AZ$11=FB145,-'Rent Roll'!$B$13*'Rent Roll'!$L$13,0) | BA64: =IF(BA$11=FB141,-'Rent Roll'!$B$9*'Rent Roll'!$L$9,0)+IF(BA$11=FB142,-'Rent Roll'!$B$10*'Rent Roll'!$L$10,0)+IF(BA$11=FB143,-'Rent Roll'!$B$11*'Rent Roll'!$L$11,0)+IF(BA$11=FB144,-'Rent Roll'!$B$12*'Rent Roll'!$L$12,0)+IF(BA$11=FB145,-'Rent Roll'!$B$13*'Rent Roll'!$L$13,0) | BB64: =IF(BB$11=FB141,-'Rent Roll'!$B$9*'Rent Roll'!$L$9,0)+IF(BB$11=FB142,-'Rent Roll'!$B$10*'Rent Roll'!$L$10,0)+IF(BB$11=FB143,-'Rent Roll'!$B$11*'Rent Roll'!$L$11,0)+IF(BB$11=FB144,-'Rent Roll'!$B$12*'Rent Roll'!$L$12,0)+IF(BB$11=FB145,-'Rent Roll'!$B$13*'Rent Roll'!$L$13,0) | BC64: =IF(BC$11=FB141,-'Rent Roll'!$B$9*'Rent Roll'!$L$9,0)+IF(BC$11=FB142,-'Rent Roll'!$B$10*'Rent Roll'!$L$10,0)+IF(BC$11=FB143,-'Rent Roll'!$B$11*'Rent Roll'!$L$11,0)+IF(BC$11=FB144,-'Rent Roll'!$B$12*'Rent Roll'!$L$12,0)+IF(BC$11=FB145,-'Rent Roll'!$B$13*'Rent Roll'!$L$13,0) | BD64: =IF(BD$11=FB141,-'Rent Roll'!$B$9*'Rent Roll'!$L$9,0)+IF(BD$11=FB142,-'Rent Roll'!$B$10*'Rent Roll'!$L$10,0)+IF(BD$11=FB143,-'Rent Roll'!$B$11*'Rent Roll'!$L$11,0)+IF(BD$11=FB144,-'Rent Roll'!$B$12*'Rent Roll'!$L$12,0)+IF(BD$11=FB145,-'Rent Roll'!$B$13*'Rent Roll'!$L$13,0) | BE64: =IF(BE$11=FB141,-'Rent Roll'!$B$9*'Rent Roll'!$L$9,0)+IF(BE$11=FB142,-'Rent Roll'!$B$10*'Rent Roll'!$L$10,0)+IF(BE$11=FB143,-'Rent Roll'!$B$11*'Rent Roll'!$L$11,0)+IF(BE$11=FB144,-'Rent Roll'!$B$12*'Rent Roll'!$L$12,0)+IF(BE$11=FB145,-'Rent Roll'!$B$13*'Rent Roll'!$L$13,0) | BF64: =IF(BF$11=FB141,-'Rent Roll'!$B$9*'Rent Roll'!$L$9,0)+IF(BF$11=FB142,-'Rent Roll'!$B$10*'Rent Roll'!$L$10,0)+IF(BF$11=FB143,-'Rent Roll'!$B$11*'Rent Roll'!$L$11,0)+IF(BF$11=FB144,-'Rent Roll'!$B$12*'Rent Roll'!$L$12,0)+IF(BF$11=FB145,-'Rent Roll'!$B$13*'Rent Roll'!$L$13,0) | BG64: =IF(BG$11=FB141,-'Rent Roll'!$B$9*'Rent Roll'!$L$9,0)+IF(BG$11=FB142,-'Rent Roll'!$B$10*'Rent Roll'!$L$10,0)+IF(BG$11=FB143,-'Rent Roll'!$B$11*'Rent Roll'!$L$11,0)+IF(BG$11=FB144,-'Rent Roll'!$B$12*'Rent Roll'!$L$12,0)+IF(BG$11=FB145,-'Rent Roll'!$B$13*'Rent Roll'!$L$13,0) | BH64: =IF(BH$11=FB141,-'Rent Roll'!$B$9*'Rent Roll'!$L$9,0)+IF(BH$11=FB142,-'Rent Roll'!$B$10*'Rent Roll'!$L$10,0)+IF(BH$11=FB143,-'Rent Roll'!$B$11*'Rent Roll'!$L$11,0)+IF(BH$11=FB144,-'Rent Roll'!$B$12*'Rent Roll'!$L$12,0)+IF(BH$11=FB145,-'Rent Roll'!$B$13*'Rent Roll'!$L$13,0) | BI64: =IF(BI$11=FB141,-'Rent Roll'!$B$9*'Rent Roll'!$L$9,0)+IF(BI$11=FB142,-'Rent Roll'!$B$10*'Rent Roll'!$L$10,0)+IF(BI$11=FB143,-'Rent Roll'!$B$11*'Rent Roll'!$L$11,0)+IF(BI$11=FB144,-'Rent Roll'!$B$12*'Rent Roll'!$L$12,0)+IF(BI$11=FB145,-'Rent Roll'!$B$13*'Rent Roll'!$L$13,0) | BJ64: =IF(BJ$11=FB141,-'Rent Roll'!$B$9*'Rent Roll'!$L$9,0)+IF(BJ$11=FB142,-'Rent Roll'!$B$10*'Rent Roll'!$L$10,0)+IF(BJ$11=FB143,-'Rent Roll'!$B$11*'Rent Roll'!$L$11,0)+IF(BJ$11=FB144,-'Rent Roll'!$B$12*'Rent Roll'!$L$12,0)+IF(BJ$11=FB145,-'Rent Roll'!$B$13*'Rent Roll'!$L$13,0) | BK64: =IF(BK$11=FB141,-'Rent Roll'!$B$9*'Rent Roll'!$L$9,0)+IF(BK$11=FB142,-'Rent Roll'!$B$10*'Rent Roll'!$L$10,0)+IF(BK$11=FB143,-'Rent Roll'!$B$11*'Rent Roll'!$L$11,0)+IF(BK$11=FB144,-'Rent Roll'!$B$12*'Rent Roll'!$L$12,0)+IF(BK$11=FB145,-'Rent Roll'!$B$13*'Rent Roll'!$L$13,0) | BL64: =IF(BL$11=FB141,-'Rent Roll'!$B$9*'Rent Roll'!$L$9,0)+IF(BL$11=FB142,-'Rent Roll'!$B$10*'Rent Roll'!$L$10,0)+IF(BL$11=FB143,-'Rent Roll'!$B$11*'Rent Roll'!$L$11,0)+IF(BL$11=FB144,-'Rent Roll'!$B$12*'Rent Roll'!$L$12,0)+IF(BL$11=FB145,-'Rent Roll'!$B$13*'Rent Roll'!$L$13,0) | BM64: =IF(BM$11=FC141,-'Rent Roll'!$B$9*'Rent Roll'!$L$9,0)+IF(BM$11=FC142,-'Rent Roll'!$B$10*'Rent Roll'!$L$10,0)+IF(BM$11=FC143,-'Rent Roll'!$B$11*'Rent Roll'!$L$11,0)+IF(BM$11=FC144,-'Rent Roll'!$B$12*'Rent Roll'!$L$12,0)+IF(BM$11=FC145,-'Rent Roll'!$B$13*'Rent Roll'!$L$13,0) | BN64: =IF(BN$11=FD141,-'Rent Roll'!$B$9*'Rent Roll'!$L$9,0)+IF(BN$11=FD142,-'Rent Roll'!$B$10*'Rent Roll'!$L$10,0)+IF(BN$11=FD143,-'Rent Roll'!$B$11*'Rent Roll'!$L$11,0)+IF(BN$11=FD144,-'Rent Roll'!$B$12*'Rent Roll'!$L$12,0)+IF(BN$11=FD145,-'Rent Roll'!$B$13*'Rent Roll'!$L$13,0) | BO64: =IF(BO$11=FE141,-'Rent Roll'!$B$9*'Rent Roll'!$L$9,0)+IF(BO$11=FE142,-'Rent Roll'!$B$10*'Rent Roll'!$L$10,0)+IF(BO$11=FE143,-'Rent Roll'!$B$11*'Rent Roll'!$L$11,0)+IF(BO$11=FE144,-'Rent Roll'!$B$12*'Rent Roll'!$L$12,0)+IF(BO$11=FE145,-'Rent Roll'!$B$13*'Rent Roll'!$L$13,0) | BP64: =IF(BP$11=FF141,-'Rent Roll'!$B$9*'Rent Roll'!$L$9,0)+IF(BP$11=FF142,-'Rent Roll'!$B$10*'Rent Roll'!$L$10,0)+IF(BP$11=FF143,-'Rent Roll'!$B$11*'Rent Roll'!$L$11,0)+IF(BP$11=FF144,-'Rent Roll'!$B$12*'Rent Roll'!$L$12,0)+IF(BP$11=FF145,-'Rent Roll'!$B$13*'Rent Roll'!$L$13,0) | BQ64: =IF(BQ$11=FG141,-'Rent Roll'!$B$9*'Rent Roll'!$L$9,0)+IF(BQ$11=FG142,-'Rent Roll'!$B$10*'Rent Roll'!$L$10,0)+IF(BQ$11=FG143,-'Rent Roll'!$B$11*'Rent Roll'!$L$11,0)+IF(BQ$11=FG144,-'Rent Roll'!$B$12*'Rent Roll'!$L$12,0)+IF(BQ$11=FG145,-'Rent Roll'!$B$13*'Rent Roll'!$L$13,0) | BR64: =IF(BR$11=FH141,-'Rent Roll'!$B$9*'Rent Roll'!$L$9,0)+IF(BR$11=FH142,-'Rent Roll'!$B$10*'Rent Roll'!$L$10,0)+IF(BR$11=FH143,-'Rent Roll'!$B$11*'Rent Roll'!$L$11,0)+IF(BR$11=FH144,-'Rent Roll'!$B$12*'Rent Roll'!$L$12,0)+IF(BR$11=FH145,-'Rent Roll'!$B$13*'Rent Roll'!$L$13,0) | BS64: =IF(BS$11=FI141,-'Rent Roll'!$B$9*'Rent Roll'!$L$9,0)+IF(BS$11=FI142,-'Rent Roll'!$B$10*'Rent Roll'!$L$10,0)+IF(BS$11=FI143,-'Rent Roll'!$B$11*'Rent Roll'!$L$11,0)+IF(BS$11=FI144,-'Rent Roll'!$B$12*'Rent Roll'!$L$12,0)+IF(BS$11=FI145,-'Rent Roll'!$B$13*'Rent Roll'!$L$13,0) | ... DT64: =IF(DT$11=HJ141,-'Rent Roll'!$B$9*'Rent Roll'!$L$9,0)+IF(DT$11=HJ142,-'Rent Roll'!$B$10*'Rent Roll'!$L$10,0)+IF(DT$11=HJ143,-'Rent Roll'!$B$11*'Rent Roll'!$L$11,0)+IF(DT$11=HJ144,-'Rent Roll'!$B$12*'Rent Roll'!$L$12,0)+IF(DT$11=HJ145,-'Rent Roll'!$B$13*'Rent Roll'!$L$13,0)
A65: Market Tenant Improvements | C65: =SUM(D65:DT65) | D65: =IF(D$11=FB146,-'Rent Roll'!$B$36*'Rent Roll'!$L$36,0)+IF(D$11=FB147,-'Rent Roll'!$B$37*'Rent Roll'!$L$37,0)+IF(D$11=FB148,-'Rent Roll'!$B$38*'Rent Roll'!$L$38,0)+IF(D$11=FB149,-'Rent Roll'!$B$39*'Rent Roll'!$L$39,0)+IF(D$11=FB150,-'Rent Roll'!$B$40*'Rent Roll'!$L$40,0) | E65: =IF(E$11=FB146,-'Rent Roll'!$B$36*'Rent Roll'!$L$36,0)+IF(E$11=FB147,-'Rent Roll'!$B$37*'Rent Roll'!$L$37,0)+IF(E$11=FB148,-'Rent Roll'!$B$38*'Rent Roll'!$L$38,0)+IF(E$11=FB149,-'Rent Roll'!$B$39*'Rent Roll'!$L$39,0)+IF(E$11=FB150,-'Rent Roll'!$B$40*'Rent Roll'!$L$40,0) | F65: =IF(F$11=FB146,-'Rent Roll'!$B$36*'Rent Roll'!$L$36,0)+IF(F$11=FB147,-'Rent Roll'!$B$37*'Rent Roll'!$L$37,0)+IF(F$11=FB148,-'Rent Roll'!$B$38*'Rent Roll'!$L$38,0)+IF(F$11=FB149,-'Rent Roll'!$B$39*'Rent Roll'!$L$39,0)+IF(F$11=FB150,-'Rent Roll'!$B$40*'Rent Roll'!$L$40,0) | G65: =IF(G$11=FB146,-'Rent Roll'!$B$36*'Rent Roll'!$L$36,0)+IF(G$11=FB147,-'Rent Roll'!$B$37*'Rent Roll'!$L$37,0)+IF(G$11=FB148,-'Rent Roll'!$B$38*'Rent Roll'!$L$38,0)+IF(G$11=FB149,-'Rent Roll'!$B$39*'Rent Roll'!$L$39,0)+IF(G$11=FB150,-'Rent Roll'!$B$40*'Rent Roll'!$L$40,0) | H65: =IF(H$11=FB146,-'Rent Roll'!$B$36*'Rent Roll'!$L$36,0)+IF(H$11=FB147,-'Rent Roll'!$B$37*'Rent Roll'!$L$37,0)+IF(H$11=FB148,-'Rent Roll'!$B$38*'Rent Roll'!$L$38,0)+IF(H$11=FB149,-'Rent Roll'!$B$39*'Rent Roll'!$L$39,0)+IF(H$11=FB150,-'Rent Roll'!$B$40*'Rent Roll'!$L$40,0) | I65: =IF(I$11=FB146,-'Rent Roll'!$B$36*'Rent Roll'!$L$36,0)+IF(I$11=FB147,-'Rent Roll'!$B$37*'Rent Roll'!$L$37,0)+IF(I$11=FB148,-'Rent Roll'!$B$38*'Rent Roll'!$L$38,0)+IF(I$11=FB149,-'Rent Roll'!$B$39*'Rent Roll'!$L$39,0)+IF(I$11=FB150,-'Rent Roll'!$B$40*'Rent Roll'!$L$40,0) | J65: =IF(J$11=FB146,-'Rent Roll'!$B$36*'Rent Roll'!$L$36,0)+IF(J$11=FB147,-'Rent Roll'!$B$37*'Rent Roll'!$L$37,0)+IF(J$11=FB148,-'Rent Roll'!$B$38*'Rent Roll'!$L$38,0)+IF(J$11=FB149,-'Rent Roll'!$B$39*'Rent Roll'!$L$39,0)+IF(J$11=FB150,-'Rent Roll'!$B$40*'Rent Roll'!$L$40,0) | K65: =IF(K$11=FB146,-'Rent Roll'!$B$36*'Rent Roll'!$L$36,0)+IF(K$11=FB147,-'Rent Roll'!$B$37*'Rent Roll'!$L$37,0)+IF(K$11=FB148,-'Rent Roll'!$B$38*'Rent Roll'!$L$38,0)+IF(K$11=FB149,-'Rent Roll'!$B$39*'Rent Roll'!$L$39,0)+IF(K$11=FB150,-'Rent Roll'!$B$40*'Rent Roll'!$L$40,0) | L65: =IF(L$11=FB146,-'Rent Roll'!$B$36*'Rent Roll'!$L$36,0)+IF(L$11=FB147,-'Rent Roll'!$B$37*'Rent Roll'!$L$37,0)+IF(L$11=FB148,-'Rent Roll'!$B$38*'Rent Roll'!$L$38,0)+IF(L$11=FB149,-'Rent Roll'!$B$39*'Rent Roll'!$L$39,0)+IF(L$11=FB150,-'Rent Roll'!$B$40*'Rent Roll'!$L$40,0) | M65: =IF(M$11=FB146,-'Rent Roll'!$B$36*'Rent Roll'!$L$36,0)+IF(M$11=FB147,-'Rent Roll'!$B$37*'Rent Roll'!$L$37,0)+IF(M$11=FB148,-'Rent Roll'!$B$38*'Rent Roll'!$L$38,0)+IF(M$11=FB149,-'Rent Roll'!$B$39*'Rent Roll'!$L$39,0)+IF(M$11=FB150,-'Rent Roll'!$B$40*'Rent Roll'!$L$40,0) | N65: =IF(N$11=FB146,-'Rent Roll'!$B$36*'Rent Roll'!$L$36,0)+IF(N$11=FB147,-'Rent Roll'!$B$37*'Rent Roll'!$L$37,0)+IF(N$11=FB148,-'Rent Roll'!$B$38*'Rent Roll'!$L$38,0)+IF(N$11=FB149,-'Rent Roll'!$B$39*'Rent Roll'!$L$39,0)+IF(N$11=FB150,-'Rent Roll'!$B$40*'Rent Roll'!$L$40,0) | O65: =IF(O$11=FB146,-'Rent Roll'!$B$36*'Rent Roll'!$L$36,0)+IF(O$11=FB147,-'Rent Roll'!$B$37*'Rent Roll'!$L$37,0)+IF(O$11=FB148,-'Rent Roll'!$B$38*'Rent Roll'!$L$38,0)+IF(O$11=FB149,-'Rent Roll'!$B$39*'Rent Roll'!$L$39,0)+IF(O$11=FB150,-'Rent Roll'!$B$40*'Rent Roll'!$L$40,0) | P65: =IF(P$11=FB146,-'Rent Roll'!$B$36*'Rent Roll'!$L$36,0)+IF(P$11=FB147,-'Rent Roll'!$B$37*'Rent Roll'!$L$37,0)+IF(P$11=FB148,-'Rent Roll'!$B$38*'Rent Roll'!$L$38,0)+IF(P$11=FB149,-'Rent Roll'!$B$39*'Rent Roll'!$L$39,0)+IF(P$11=FB150,-'Rent Roll'!$B$40*'Rent Roll'!$L$40,0) | Q65: =IF(Q$11=FB146,-'Rent Roll'!$B$36*'Rent Roll'!$L$36,0)+IF(Q$11=FB147,-'Rent Roll'!$B$37*'Rent Roll'!$L$37,0)+IF(Q$11=FB148,-'Rent Roll'!$B$38*'Rent Roll'!$L$38,0)+IF(Q$11=FB149,-'Rent Roll'!$B$39*'Rent Roll'!$L$39,0)+IF(Q$11=FB150,-'Rent Roll'!$B$40*'Rent Roll'!$L$40,0) | R65: =IF(R$11=FB146,-'Rent Roll'!$B$36*'Rent Roll'!$L$36,0)+IF(R$11=FB147,-'Rent Roll'!$B$37*'Rent Roll'!$L$37,0)+IF(R$11=FB148,-'Rent Roll'!$B$38*'Rent Roll'!$L$38,0)+IF(R$11=FB149,-'Rent Roll'!$B$39*'Rent Roll'!$L$39,0)+IF(R$11=FB150,-'Rent Roll'!$B$40*'Rent Roll'!$L$40,0) | S65: =IF(S$11=FB146,-'Rent Roll'!$B$36*'Rent Roll'!$L$36,0)+IF(S$11=FB147,-'Rent Roll'!$B$37*'Rent Roll'!$L$37,0)+IF(S$11=FB148,-'Rent Roll'!$B$38*'Rent Roll'!$L$38,0)+IF(S$11=FB149,-'Rent Roll'!$B$39*'Rent Roll'!$L$39,0)+IF(S$11=FB150,-'Rent Roll'!$B$40*'Rent Roll'!$L$40,0) | T65: =IF(T$11=FB146,-'Rent Roll'!$B$36*'Rent Roll'!$L$36,0)+IF(T$11=FB147,-'Rent Roll'!$B$37*'Rent Roll'!$L$37,0)+IF(T$11=FB148,-'Rent Roll'!$B$38*'Rent Roll'!$L$38,0)+IF(T$11=FB149,-'Rent Roll'!$B$39*'Rent Roll'!$L$39,0)+IF(T$11=FB150,-'Rent Roll'!$B$40*'Rent Roll'!$L$40,0) | U65: =IF(U$11=FB146,-'Rent Roll'!$B$36*'Rent Roll'!$L$36,0)+IF(U$11=FB147,-'Rent Roll'!$B$37*'Rent Roll'!$L$37,0)+IF(U$11=FB148,-'Rent Roll'!$B$38*'Rent Roll'!$L$38,0)+IF(U$11=FB149,-'Rent Roll'!$B$39*'Rent Roll'!$L$39,0)+IF(U$11=FB150,-'Rent Roll'!$B$40*'Rent Roll'!$L$40,0) | V65: =IF(V$11=FB146,-'Rent Roll'!$B$36*'Rent Roll'!$L$36,0)+IF(V$11=FB147,-'Rent Roll'!$B$37*'Rent Roll'!$L$37,0)+IF(V$11=FB148,-'Rent Roll'!$B$38*'Rent Roll'!$L$38,0)+IF(V$11=FB149,-'Rent Roll'!$B$39*'Rent Roll'!$L$39,0)+IF(V$11=FB150,-'Rent Roll'!$B$40*'Rent Roll'!$L$40,0) | W65: =IF(W$11=FB146,-'Rent Roll'!$B$36*'Rent Roll'!$L$36,0)+IF(W$11=FB147,-'Rent Roll'!$B$37*'Rent Roll'!$L$37,0)+IF(W$11=FB148,-'Rent Roll'!$B$38*'Rent Roll'!$L$38,0)+IF(W$11=FB149,-'Rent Roll'!$B$39*'Rent Roll'!$L$39,0)+IF(W$11=FB150,-'Rent Roll'!$B$40*'Rent Roll'!$L$40,0) | X65: =IF(X$11=FB146,-'Rent Roll'!$B$36*'Rent Roll'!$L$36,0)+IF(X$11=FB147,-'Rent Roll'!$B$37*'Rent Roll'!$L$37,0)+IF(X$11=FB148,-'Rent Roll'!$B$38*'Rent Roll'!$L$38,0)+IF(X$11=FB149,-'Rent Roll'!$B$39*'Rent Roll'!$L$39,0)+IF(X$11=FB150,-'Rent Roll'!$B$40*'Rent Roll'!$L$40,0) | Y65: =IF(Y$11=FB146,-'Rent Roll'!$B$36*'Rent Roll'!$L$36,0)+IF(Y$11=FB147,-'Rent Roll'!$B$37*'Rent Roll'!$L$37,0)+IF(Y$11=FB148,-'Rent Roll'!$B$38*'Rent Roll'!$L$38,0)+IF(Y$11=FB149,-'Rent Roll'!$B$39*'Rent Roll'!$L$39,0)+IF(Y$11=FB150,-'Rent Roll'!$B$40*'Rent Roll'!$L$40,0) | Z65: =IF(Z$11=FB146,-'Rent Roll'!$B$36*'Rent Roll'!$L$36,0)+IF(Z$11=FB147,-'Rent Roll'!$B$37*'Rent Roll'!$L$37,0)+IF(Z$11=FB148,-'Rent Roll'!$B$38*'Rent Roll'!$L$38,0)+IF(Z$11=FB149,-'Rent Roll'!$B$39*'Rent Roll'!$L$39,0)+IF(Z$11=FB150,-'Rent Roll'!$B$40*'Rent Roll'!$L$40,0) | AA65: =IF(AA$11=FB146,-'Rent Roll'!$B$36*'Rent Roll'!$L$36,0)+IF(AA$11=FB147,-'Rent Roll'!$B$37*'Rent Roll'!$L$37,0)+IF(AA$11=FB148,-'Rent Roll'!$B$38*'Rent Roll'!$L$38,0)+IF(AA$11=FB149,-'Rent Roll'!$B$39*'Rent Roll'!$L$39,0)+IF(AA$11=FB150,-'Rent Roll'!$B$40*'Rent Roll'!$L$40,0) | AB65: =IF(AB$11=FB146,-'Rent Roll'!$B$36*'Rent Roll'!$L$36,0)+IF(AB$11=FB147,-'Rent Roll'!$B$37*'Rent Roll'!$L$37,0)+IF(AB$11=FB148,-'Rent Roll'!$B$38*'Rent Roll'!$L$38,0)+IF(AB$11=FB149,-'Rent Roll'!$B$39*'Rent Roll'!$L$39,0)+IF(AB$11=FB150,-'Rent Roll'!$B$40*'Rent Roll'!$L$40,0) | AC65: =IF(AC$11=FB146,-'Rent Roll'!$B$36*'Rent Roll'!$L$36,0)+IF(AC$11=FB147,-'Rent Roll'!$B$37*'Rent Roll'!$L$37,0)+IF(AC$11=FB148,-'Rent Roll'!$B$38*'Rent Roll'!$L$38,0)+IF(AC$11=FB149,-'Rent Roll'!$B$39*'Rent Roll'!$L$39,0)+IF(AC$11=FB150,-'Rent Roll'!$B$40*'Rent Roll'!$L$40,0) | AD65: =IF(AD$11=FB146,-'Rent Roll'!$B$36*'Rent Roll'!$L$36,0)+IF(AD$11=FB147,-'Rent Roll'!$B$37*'Rent Roll'!$L$37,0)+IF(AD$11=FB148,-'Rent Roll'!$B$38*'Rent Roll'!$L$38,0)+IF(AD$11=FB149,-'Rent Roll'!$B$39*'Rent Roll'!$L$39,0)+IF(AD$11=FB150,-'Rent Roll'!$B$40*'Rent Roll'!$L$40,0) | AE65: =IF(AE$11=FB146,-'Rent Roll'!$B$36*'Rent Roll'!$L$36,0)+IF(AE$11=FB147,-'Rent Roll'!$B$37*'Rent Roll'!$L$37,0)+IF(AE$11=FB148,-'Rent Roll'!$B$38*'Rent Roll'!$L$38,0)+IF(AE$11=FB149,-'Rent Roll'!$B$39*'Rent Roll'!$L$39,0)+IF(AE$11=FB150,-'Rent Roll'!$B$40*'Rent Roll'!$L$40,0) | AF65: =IF(AF$11=FB146,-'Rent Roll'!$B$36*'Rent Roll'!$L$36,0)+IF(AF$11=FB147,-'Rent Roll'!$B$37*'Rent Roll'!$L$37,0)+IF(AF$11=FB148,-'Rent Roll'!$B$38*'Rent Roll'!$L$38,0)+IF(AF$11=FB149,-'Rent Roll'!$B$39*'Rent Roll'!$L$39,0)+IF(AF$11=FB150,-'Rent Roll'!$B$40*'Rent Roll'!$L$40,0) | AG65: =IF(AG$11=FB146,-'Rent Roll'!$B$36*'Rent Roll'!$L$36,0)+IF(AG$11=FB147,-'Rent Roll'!$B$37*'Rent Roll'!$L$37,0)+IF(AG$11=FB148,-'Rent Roll'!$B$38*'Rent Roll'!$L$38,0)+IF(AG$11=FB149,-'Rent Roll'!$B$39*'Rent Roll'!$L$39,0)+IF(AG$11=FB150,-'Rent Roll'!$B$40*'Rent Roll'!$L$40,0) | AH65: =IF(AH$11=FB146,-'Rent Roll'!$B$36*'Rent Roll'!$L$36,0)+IF(AH$11=FB147,-'Rent Roll'!$B$37*'Rent Roll'!$L$37,0)+IF(AH$11=FB148,-'Rent Roll'!$B$38*'Rent Roll'!$L$38,0)+IF(AH$11=FB149,-'Rent Roll'!$B$39*'Rent Roll'!$L$39,0)+IF(AH$11=FB150,-'Rent Roll'!$B$40*'Rent Roll'!$L$40,0) | AI65: =IF(AI$11=FB146,-'Rent Roll'!$B$36*'Rent Roll'!$L$36,0)+IF(AI$11=FB147,-'Rent Roll'!$B$37*'Rent Roll'!$L$37,0)+IF(AI$11=FB148,-'Rent Roll'!$B$38*'Rent Roll'!$L$38,0)+IF(AI$11=FB149,-'Rent Roll'!$B$39*'Rent Roll'!$L$39,0)+IF(AI$11=FB150,-'Rent Roll'!$B$40*'Rent Roll'!$L$40,0) | AJ65: =IF(AJ$11=FB146,-'Rent Roll'!$B$36*'Rent Roll'!$L$36,0)+IF(AJ$11=FB147,-'Rent Roll'!$B$37*'Rent Roll'!$L$37,0)+IF(AJ$11=FB148,-'Rent Roll'!$B$38*'Rent Roll'!$L$38,0)+IF(AJ$11=FB149,-'Rent Roll'!$B$39*'Rent Roll'!$L$39,0)+IF(AJ$11=FB150,-'Rent Roll'!$B$40*'Rent Roll'!$L$40,0) | AK65: =IF(AK$11=FB146,-'Rent Roll'!$B$36*'Rent Roll'!$L$36,0)+IF(AK$11=FB147,-'Rent Roll'!$B$37*'Rent Roll'!$L$37,0)+IF(AK$11=FB148,-'Rent Roll'!$B$38*'Rent Roll'!$L$38,0)+IF(AK$11=FB149,-'Rent Roll'!$B$39*'Rent Roll'!$L$39,0)+IF(AK$11=FB150,-'Rent Roll'!$B$40*'Rent Roll'!$L$40,0) | AL65: =IF(AL$11=FB146,-'Rent Roll'!$B$36*'Rent Roll'!$L$36,0)+IF(AL$11=FB147,-'Rent Roll'!$B$37*'Rent Roll'!$L$37,0)+IF(AL$11=FB148,-'Rent Roll'!$B$38*'Rent Roll'!$L$38,0)+IF(AL$11=FB149,-'Rent Roll'!$B$39*'Rent Roll'!$L$39,0)+IF(AL$11=FB150,-'Rent Roll'!$B$40*'Rent Roll'!$L$40,0) | AM65: =IF(AM$11=FB146,-'Rent Roll'!$B$36*'Rent Roll'!$L$36,0)+IF(AM$11=FB147,-'Rent Roll'!$B$37*'Rent Roll'!$L$37,0)+IF(AM$11=FB148,-'Rent Roll'!$B$38*'Rent Roll'!$L$38,0)+IF(AM$11=FB149,-'Rent Roll'!$B$39*'Rent Roll'!$L$39,0)+IF(AM$11=FB150,-'Rent Roll'!$B$40*'Rent Roll'!$L$40,0) | AN65: =IF(AN$11=FB146,-'Rent Roll'!$B$36*'Rent Roll'!$L$36,0)+IF(AN$11=FB147,-'Rent Roll'!$B$37*'Rent Roll'!$L$37,0)+IF(AN$11=FB148,-'Rent Roll'!$B$38*'Rent Roll'!$L$38,0)+IF(AN$11=FB149,-'Rent Roll'!$B$39*'Rent Roll'!$L$39,0)+IF(AN$11=FB150,-'Rent Roll'!$B$40*'Rent Roll'!$L$40,0) | AO65: =IF(AO$11=FB146,-'Rent Roll'!$B$36*'Rent Roll'!$L$36,0)+IF(AO$11=FB147,-'Rent Roll'!$B$37*'Rent Roll'!$L$37,0)+IF(AO$11=FB148,-'Rent Roll'!$B$38*'Rent Roll'!$L$38,0)+IF(AO$11=FB149,-'Rent Roll'!$B$39*'Rent Roll'!$L$39,0)+IF(AO$11=FB150,-'Rent Roll'!$B$40*'Rent Roll'!$L$40,0) | AP65: =IF(AP$11=FB146,-'Rent Roll'!$B$36*'Rent Roll'!$L$36,0)+IF(AP$11=FB147,-'Rent Roll'!$B$37*'Rent Roll'!$L$37,0)+IF(AP$11=FB148,-'Rent Roll'!$B$38*'Rent Roll'!$L$38,0)+IF(AP$11=FB149,-'Rent Roll'!$B$39*'Rent Roll'!$L$39,0)+IF(AP$11=FB150,-'Rent Roll'!$B$40*'Rent Roll'!$L$40,0) | AQ65: =IF(AQ$11=FB146,-'Rent Roll'!$B$36*'Rent Roll'!$L$36,0)+IF(AQ$11=FB147,-'Rent Roll'!$B$37*'Rent Roll'!$L$37,0)+IF(AQ$11=FB148,-'Rent Roll'!$B$38*'Rent Roll'!$L$38,0)+IF(AQ$11=FB149,-'Rent Roll'!$B$39*'Rent Roll'!$L$39,0)+IF(AQ$11=FB150,-'Rent Roll'!$B$40*'Rent Roll'!$L$40,0) | AR65: =IF(AR$11=FB146,-'Rent Roll'!$B$36*'Rent Roll'!$L$36,0)+IF(AR$11=FB147,-'Rent Roll'!$B$37*'Rent Roll'!$L$37,0)+IF(AR$11=FB148,-'Rent Roll'!$B$38*'Rent Roll'!$L$38,0)+IF(AR$11=FB149,-'Rent Roll'!$B$39*'Rent Roll'!$L$39,0)+IF(AR$11=FB150,-'Rent Roll'!$B$40*'Rent Roll'!$L$40,0) | AS65: =IF(AS$11=FB146,-'Rent Roll'!$B$36*'Rent Roll'!$L$36,0)+IF(AS$11=FB147,-'Rent Roll'!$B$37*'Rent Roll'!$L$37,0)+IF(AS$11=FB148,-'Rent Roll'!$B$38*'Rent Roll'!$L$38,0)+IF(AS$11=FB149,-'Rent Roll'!$B$39*'Rent Roll'!$L$39,0)+IF(AS$11=FB150,-'Rent Roll'!$B$40*'Rent Roll'!$L$40,0) | AT65: =IF(AT$11=FB146,-'Rent Roll'!$B$36*'Rent Roll'!$L$36,0)+IF(AT$11=FB147,-'Rent Roll'!$B$37*'Rent Roll'!$L$37,0)+IF(AT$11=FB148,-'Rent Roll'!$B$38*'Rent Roll'!$L$38,0)+IF(AT$11=FB149,-'Rent Roll'!$B$39*'Rent Roll'!$L$39,0)+IF(AT$11=FB150,-'Rent Roll'!$B$40*'Rent Roll'!$L$40,0) | AU65: =IF(AU$11=FB146,-'Rent Roll'!$B$36*'Rent Roll'!$L$36,0)+IF(AU$11=FB147,-'Rent Roll'!$B$37*'Rent Roll'!$L$37,0)+IF(AU$11=FB148,-'Rent Roll'!$B$38*'Rent Roll'!$L$38,0)+IF(AU$11=FB149,-'Rent Roll'!$B$39*'Rent Roll'!$L$39,0)+IF(AU$11=FB150,-'Rent Roll'!$B$40*'Rent Roll'!$L$40,0) | AV65: =IF(AV$11=FB146,-'Rent Roll'!$B$36*'Rent Roll'!$L$36,0)+IF(AV$11=FB147,-'Rent Roll'!$B$37*'Rent Roll'!$L$37,0)+IF(AV$11=FB148,-'Rent Roll'!$B$38*'Rent Roll'!$L$38,0)+IF(AV$11=FB149,-'Rent Roll'!$B$39*'Rent Roll'!$L$39,0)+IF(AV$11=FB150,-'Rent Roll'!$B$40*'Rent Roll'!$L$40,0) | AW65: =IF(AW$11=FB146,-'Rent Roll'!$B$36*'Rent Roll'!$L$36,0)+IF(AW$11=FB147,-'Rent Roll'!$B$37*'Rent Roll'!$L$37,0)+IF(AW$11=FB148,-'Rent Roll'!$B$38*'Rent Roll'!$L$38,0)+IF(AW$11=FB149,-'Rent Roll'!$B$39*'Rent Roll'!$L$39,0)+IF(AW$11=FB150,-'Rent Roll'!$B$40*'Rent Roll'!$L$40,0) | AX65: =IF(AX$11=FB146,-'Rent Roll'!$B$36*'Rent Roll'!$L$36,0)+IF(AX$11=FB147,-'Rent Roll'!$B$37*'Rent Roll'!$L$37,0)+IF(AX$11=FB148,-'Rent Roll'!$B$38*'Rent Roll'!$L$38,0)+IF(AX$11=FB149,-'Rent Roll'!$B$39*'Rent Roll'!$L$39,0)+IF(AX$11=FB150,-'Rent Roll'!$B$40*'Rent Roll'!$L$40,0) | AY65: =IF(AY$11=FB146,-'Rent Roll'!$B$36*'Rent Roll'!$L$36,0)+IF(AY$11=FB147,-'Rent Roll'!$B$37*'Rent Roll'!$L$37,0)+IF(AY$11=FB148,-'Rent Roll'!$B$38*'Rent Roll'!$L$38,0)+IF(AY$11=FB149,-'Rent Roll'!$B$39*'Rent Roll'!$L$39,0)+IF(AY$11=FB150,-'Rent Roll'!$B$40*'Rent Roll'!$L$40,0) | AZ65: =IF(AZ$11=FB146,-'Rent Roll'!$B$36*'Rent Roll'!$L$36,0)+IF(AZ$11=FB147,-'Rent Roll'!$B$37*'Rent Roll'!$L$37,0)+IF(AZ$11=FB148,-'Rent Roll'!$B$38*'Rent Roll'!$L$38,0)+IF(AZ$11=FB149,-'Rent Roll'!$B$39*'Rent Roll'!$L$39,0)+IF(AZ$11=FB150,-'Rent Roll'!$B$40*'Rent Roll'!$L$40,0) | BA65: =IF(BA$11=FB146,-'Rent Roll'!$B$36*'Rent Roll'!$L$36,0)+IF(BA$11=FB147,-'Rent Roll'!$B$37*'Rent Roll'!$L$37,0)+IF(BA$11=FB148,-'Rent Roll'!$B$38*'Rent Roll'!$L$38,0)+IF(BA$11=FB149,-'Rent Roll'!$B$39*'Rent Roll'!$L$39,0)+IF(BA$11=FB150,-'Rent Roll'!$B$40*'Rent Roll'!$L$40,0) | BB65: =IF(BB$11=FB146,-'Rent Roll'!$B$36*'Rent Roll'!$L$36,0)+IF(BB$11=FB147,-'Rent Roll'!$B$37*'Rent Roll'!$L$37,0)+IF(BB$11=FB148,-'Rent Roll'!$B$38*'Rent Roll'!$L$38,0)+IF(BB$11=FB149,-'Rent Roll'!$B$39*'Rent Roll'!$L$39,0)+IF(BB$11=FB150,-'Rent Roll'!$B$40*'Rent Roll'!$L$40,0) | BC65: =IF(BC$11=FB146,-'Rent Roll'!$B$36*'Rent Roll'!$L$36,0)+IF(BC$11=FB147,-'Rent Roll'!$B$37*'Rent Roll'!$L$37,0)+IF(BC$11=FB148,-'Rent Roll'!$B$38*'Rent Roll'!$L$38,0)+IF(BC$11=FB149,-'Rent Roll'!$B$39*'Rent Roll'!$L$39,0)+IF(BC$11=FB150,-'Rent Roll'!$B$40*'Rent Roll'!$L$40,0) | BD65: =IF(BD$11=FB146,-'Rent Roll'!$B$36*'Rent Roll'!$L$36,0)+IF(BD$11=FB147,-'Rent Roll'!$B$37*'Rent Roll'!$L$37,0)+IF(BD$11=FB148,-'Rent Roll'!$B$38*'Rent Roll'!$L$38,0)+IF(BD$11=FB149,-'Rent Roll'!$B$39*'Rent Roll'!$L$39,0)+IF(BD$11=FB150,-'Rent Roll'!$B$40*'Rent Roll'!$L$40,0) | BE65: =IF(BE$11=FB146,-'Rent Roll'!$B$36*'Rent Roll'!$L$36,0)+IF(BE$11=FB147,-'Rent Roll'!$B$37*'Rent Roll'!$L$37,0)+IF(BE$11=FB148,-'Rent Roll'!$B$38*'Rent Roll'!$L$38,0)+IF(BE$11=FB149,-'Rent Roll'!$B$39*'Rent Roll'!$L$39,0)+IF(BE$11=FB150,-'Rent Roll'!$B$40*'Rent Roll'!$L$40,0) | BF65: =IF(BF$11=FB146,-'Rent Roll'!$B$36*'Rent Roll'!$L$36,0)+IF(BF$11=FB147,-'Rent Roll'!$B$37*'Rent Roll'!$L$37,0)+IF(BF$11=FB148,-'Rent Roll'!$B$38*'Rent Roll'!$L$38,0)+IF(BF$11=FB149,-'Rent Roll'!$B$39*'Rent Roll'!$L$39,0)+IF(BF$11=FB150,-'Rent Roll'!$B$40*'Rent Roll'!$L$40,0) | BG65: =IF(BG$11=FB146,-'Rent Roll'!$B$36*'Rent Roll'!$L$36,0)+IF(BG$11=FB147,-'Rent Roll'!$B$37*'Rent Roll'!$L$37,0)+IF(BG$11=FB148,-'Rent Roll'!$B$38*'Rent Roll'!$L$38,0)+IF(BG$11=FB149,-'Rent Roll'!$B$39*'Rent Roll'!$L$39,0)+IF(BG$11=FB150,-'Rent Roll'!$B$40*'Rent Roll'!$L$40,0) | BH65: =IF(BH$11=FB146,-'Rent Roll'!$B$36*'Rent Roll'!$L$36,0)+IF(BH$11=FB147,-'Rent Roll'!$B$37*'Rent Roll'!$L$37,0)+IF(BH$11=FB148,-'Rent Roll'!$B$38*'Rent Roll'!$L$38,0)+IF(BH$11=FB149,-'Rent Roll'!$B$39*'Rent Roll'!$L$39,0)+IF(BH$11=FB150,-'Rent Roll'!$B$40*'Rent Roll'!$L$40,0) | BI65: =IF(BI$11=FB146,-'Rent Roll'!$B$36*'Rent Roll'!$L$36,0)+IF(BI$11=FB147,-'Rent Roll'!$B$37*'Rent Roll'!$L$37,0)+IF(BI$11=FB148,-'Rent Roll'!$B$38*'Rent Roll'!$L$38,0)+IF(BI$11=FB149,-'Rent Roll'!$B$39*'Rent Roll'!$L$39,0)+IF(BI$11=FB150,-'Rent Roll'!$B$40*'Rent Roll'!$L$40,0) | BJ65: =IF(BJ$11=FB146,-'Rent Roll'!$B$36*'Rent Roll'!$L$36,0)+IF(BJ$11=FB147,-'Rent Roll'!$B$37*'Rent Roll'!$L$37,0)+IF(BJ$11=FB148,-'Rent Roll'!$B$38*'Rent Roll'!$L$38,0)+IF(BJ$11=FB149,-'Rent Roll'!$B$39*'Rent Roll'!$L$39,0)+IF(BJ$11=FB150,-'Rent Roll'!$B$40*'Rent Roll'!$L$40,0) | BK65: =IF(BK$11=FB146,-'Rent Roll'!$B$36*'Rent Roll'!$L$36,0)+IF(BK$11=FB147,-'Rent Roll'!$B$37*'Rent Roll'!$L$37,0)+IF(BK$11=FB148,-'Rent Roll'!$B$38*'Rent Roll'!$L$38,0)+IF(BK$11=FB149,-'Rent Roll'!$B$39*'Rent Roll'!$L$39,0)+IF(BK$11=FB150,-'Rent Roll'!$B$40*'Rent Roll'!$L$40,0) | BL65: =IF(BL$11=FB146,-'Rent Roll'!$B$36*'Rent Roll'!$L$36,0)+IF(BL$11=FB147,-'Rent Roll'!$B$37*'Rent Roll'!$L$37,0)+IF(BL$11=FB148,-'Rent Roll'!$B$38*'Rent Roll'!$L$38,0)+IF(BL$11=FB149,-'Rent Roll'!$B$39*'Rent Roll'!$L$39,0)+IF(BL$11=FB150,-'Rent Roll'!$B$40*'Rent Roll'!$L$40,0) | BM65: =IF(BM$11=FC146,-'Rent Roll'!$B$36*'Rent Roll'!$L$36,0)+IF(BM$11=FC147,-'Rent Roll'!$B$37*'Rent Roll'!$L$37,0)+IF(BM$11=FC148,-'Rent Roll'!$B$38*'Rent Roll'!$L$38,0)+IF(BM$11=FC149,-'Rent Roll'!$B$39*'Rent Roll'!$L$39,0)+IF(BM$11=FC150,-'Rent Roll'!$B$40*'Rent Roll'!$L$40,0) | BN65: =IF(BN$11=FD146,-'Rent Roll'!$B$36*'Rent Roll'!$L$36,0)+IF(BN$11=FD147,-'Rent Roll'!$B$37*'Rent Roll'!$L$37,0)+IF(BN$11=FD148,-'Rent Roll'!$B$38*'Rent Roll'!$L$38,0)+IF(BN$11=FD149,-'Rent Roll'!$B$39*'Rent Roll'!$L$39,0)+IF(BN$11=FD150,-'Rent Roll'!$B$40*'Rent Roll'!$L$40,0) | BO65: =IF(BO$11=FE146,-'Rent Roll'!$B$36*'Rent Roll'!$L$36,0)+IF(BO$11=FE147,-'Rent Roll'!$B$37*'Rent Roll'!$L$37,0)+IF(BO$11=FE148,-'Rent Roll'!$B$38*'Rent Roll'!$L$38,0)+IF(BO$11=FE149,-'Rent Roll'!$B$39*'Rent Roll'!$L$39,0)+IF(BO$11=FE150,-'Rent Roll'!$B$40*'Rent Roll'!$L$40,0) | BP65: =IF(BP$11=FF146,-'Rent Roll'!$B$36*'Rent Roll'!$L$36,0)+IF(BP$11=FF147,-'Rent Roll'!$B$37*'Rent Roll'!$L$37,0)+IF(BP$11=FF148,-'Rent Roll'!$B$38*'Rent Roll'!$L$38,0)+IF(BP$11=FF149,-'Rent Roll'!$B$39*'Rent Roll'!$L$39,0)+IF(BP$11=FF150,-'Rent Roll'!$B$40*'Rent Roll'!$L$40,0) | BQ65: =IF(BQ$11=FG146,-'Rent Roll'!$B$36*'Rent Roll'!$L$36,0)+IF(BQ$11=FG147,-'Rent Roll'!$B$37*'Rent Roll'!$L$37,0)+IF(BQ$11=FG148,-'Rent Roll'!$B$38*'Rent Roll'!$L$38,0)+IF(BQ$11=FG149,-'Rent Roll'!$B$39*'Rent Roll'!$L$39,0)+IF(BQ$11=FG150,-'Rent Roll'!$B$40*'Rent Roll'!$L$40,0) | BR65: =IF(BR$11=FH146,-'Rent Roll'!$B$36*'Rent Roll'!$L$36,0)+IF(BR$11=FH147,-'Rent Roll'!$B$37*'Rent Roll'!$L$37,0)+IF(BR$11=FH148,-'Rent Roll'!$B$38*'Rent Roll'!$L$38,0)+IF(BR$11=FH149,-'Rent Roll'!$B$39*'Rent Roll'!$L$39,0)+IF(BR$11=FH150,-'Rent Roll'!$B$40*'Rent Roll'!$L$40,0) | BS65: =IF(BS$11=FI146,-'Rent Roll'!$B$36*'Rent Roll'!$L$36,0)+IF(BS$11=FI147,-'Rent Roll'!$B$37*'Rent Roll'!$L$37,0)+IF(BS$11=FI148,-'Rent Roll'!$B$38*'Rent Roll'!$L$38,0)+IF(BS$11=FI149,-'Rent Roll'!$B$39*'Rent Roll'!$L$39,0)+IF(BS$11=FI150,-'Rent Roll'!$B$40*'Rent Roll'!$L$40,0) | ... DT65: =IF(DT$11=HJ146,-'Rent Roll'!$B$36*'Rent Roll'!$L$36,0)+IF(DT$11=HJ147,-'Rent Roll'!$B$37*'Rent Roll'!$L$37,0)+IF(DT$11=HJ148,-'Rent Roll'!$B$38*'Rent Roll'!$L$38,0)+IF(DT$11=HJ149,-'Rent Roll'!$B$39*'Rent Roll'!$L$39,0)+IF(DT$11=HJ150,-'Rent Roll'!$B$40*'Rent Roll'!$L$40,0)
A66: Base Leasing Commissions | C66: =SUM(D66:DT66) | D66: =IF(D$11=FB141,-EI141,0)+IF(D$11=FB142,-EI142,0)+IF(D$11=FB143,-EI143,0)+IF(D$11=FB144,-EI144,0)+IF(D$11=FB145,-EI145,0) | E66: =IF(E$11=FB141,-EI141,0)+IF(E$11=FB142,-EI142,0)+IF(E$11=FB143,-EI143,0)+IF(E$11=FB144,-EI144,0)+IF(E$11=FB145,-EI145,0) | F66: =IF(F$11=FB141,-EI141,0)+IF(F$11=FB142,-EI142,0)+IF(F$11=FB143,-EI143,0)+IF(F$11=FB144,-EI144,0)+IF(F$11=FB145,-EI145,0) | G66: =IF(G$11=FB141,-EI141,0)+IF(G$11=FB142,-EI142,0)+IF(G$11=FB143,-EI143,0)+IF(G$11=FB144,-EI144,0)+IF(G$11=FB145,-EI145,0) | H66: =IF(H$11=FB141,-EI141,0)+IF(H$11=FB142,-EI142,0)+IF(H$11=FB143,-EI143,0)+IF(H$11=FB144,-EI144,0)+IF(H$11=FB145,-EI145,0) | I66: =IF(I$11=FB141,-EI141,0)+IF(I$11=FB142,-EI142,0)+IF(I$11=FB143,-EI143,0)+IF(I$11=FB144,-EI144,0)+IF(I$11=FB145,-EI145,0) | J66: =IF(J$11=FB141,-EI141,0)+IF(J$11=FB142,-EI142,0)+IF(J$11=FB143,-EI143,0)+IF(J$11=FB144,-EI144,0)+IF(J$11=FB145,-EI145,0) | K66: =IF(K$11=FB141,-EI141,0)+IF(K$11=FB142,-EI142,0)+IF(K$11=FB143,-EI143,0)+IF(K$11=FB144,-EI144,0)+IF(K$11=FB145,-EI145,0) | L66: =IF(L$11=FB141,-EI141,0)+IF(L$11=FB142,-EI142,0)+IF(L$11=FB143,-EI143,0)+IF(L$11=FB144,-EI144,0)+IF(L$11=FB145,-EI145,0) | M66: =IF(M$11=FB141,-EI141,0)+IF(M$11=FB142,-EI142,0)+IF(M$11=FB143,-EI143,0)+IF(M$11=FB144,-EI144,0)+IF(M$11=FB145,-EI145,0) | N66: =IF(N$11=FB141,-EI141,0)+IF(N$11=FB142,-EI142,0)+IF(N$11=FB143,-EI143,0)+IF(N$11=FB144,-EI144,0)+IF(N$11=FB145,-EI145,0) | O66: =IF(O$11=FB141,-EI141,0)+IF(O$11=FB142,-EI142,0)+IF(O$11=FB143,-EI143,0)+IF(O$11=FB144,-EI144,0)+IF(O$11=FB145,-EI145,0) | P66: =IF(P$11=FB141,-EI141,0)+IF(P$11=FB142,-EI142,0)+IF(P$11=FB143,-EI143,0)+IF(P$11=FB144,-EI144,0)+IF(P$11=FB145,-EI145,0) | Q66: =IF(Q$11=FB141,-EI141,0)+IF(Q$11=FB142,-EI142,0)+IF(Q$11=FB143,-EI143,0)+IF(Q$11=FB144,-EI144,0)+IF(Q$11=FB145,-EI145,0) | R66: =IF(R$11=FB141,-EI141,0)+IF(R$11=FB142,-EI142,0)+IF(R$11=FB143,-EI143,0)+IF(R$11=FB144,-EI144,0)+IF(R$11=FB145,-EI145,0) | S66: =IF(S$11=FB141,-EI141,0)+IF(S$11=FB142,-EI142,0)+IF(S$11=FB143,-EI143,0)+IF(S$11=FB144,-EI144,0)+IF(S$11=FB145,-EI145,0) | T66: =IF(T$11=FB141,-EI141,0)+IF(T$11=FB142,-EI142,0)+IF(T$11=FB143,-EI143,0)+IF(T$11=FB144,-EI144,0)+IF(T$11=FB145,-EI145,0) | U66: =IF(U$11=FB141,-EI141,0)+IF(U$11=FB142,-EI142,0)+IF(U$11=FB143,-EI143,0)+IF(U$11=FB144,-EI144,0)+IF(U$11=FB145,-EI145,0) | V66: =IF(V$11=FB141,-EI141,0)+IF(V$11=FB142,-EI142,0)+IF(V$11=FB143,-EI143,0)+IF(V$11=FB144,-EI144,0)+IF(V$11=FB145,-EI145,0) | W66: =IF(W$11=FB141,-EI141,0)+IF(W$11=FB142,-EI142,0)+IF(W$11=FB143,-EI143,0)+IF(W$11=FB144,-EI144,0)+IF(W$11=FB145,-EI145,0) | X66: =IF(X$11=FB141,-EI141,0)+IF(X$11=FB142,-EI142,0)+IF(X$11=FB143,-EI143,0)+IF(X$11=FB144,-EI144,0)+IF(X$11=FB145,-EI145,0) | Y66: =IF(Y$11=FB141,-EI141,0)+IF(Y$11=FB142,-EI142,0)+IF(Y$11=FB143,-EI143,0)+IF(Y$11=FB144,-EI144,0)+IF(Y$11=FB145,-EI145,0) | Z66: =IF(Z$11=FB141,-EI141,0)+IF(Z$11=FB142,-EI142,0)+IF(Z$11=FB143,-EI143,0)+IF(Z$11=FB144,-EI144,0)+IF(Z$11=FB145,-EI145,0) | AA66: =IF(AA$11=FB141,-EI141,0)+IF(AA$11=FB142,-EI142,0)+IF(AA$11=FB143,-EI143,0)+IF(AA$11=FB144,-EI144,0)+IF(AA$11=FB145,-EI145,0) | AB66: =IF(AB$11=FB141,-EI141,0)+IF(AB$11=FB142,-EI142,0)+IF(AB$11=FB143,-EI143,0)+IF(AB$11=FB144,-EI144,0)+IF(AB$11=FB145,-EI145,0) | AC66: =IF(AC$11=FB141,-EI141,0)+IF(AC$11=FB142,-EI142,0)+IF(AC$11=FB143,-EI143,0)+IF(AC$11=FB144,-EI144,0)+IF(AC$11=FB145,-EI145,0) | AD66: =IF(AD$11=FB141,-EI141,0)+IF(AD$11=FB142,-EI142,0)+IF(AD$11=FB143,-EI143,0)+IF(AD$11=FB144,-EI144,0)+IF(AD$11=FB145,-EI145,0) | AE66: =IF(AE$11=FB141,-EI141,0)+IF(AE$11=FB142,-EI142,0)+IF(AE$11=FB143,-EI143,0)+IF(AE$11=FB144,-EI144,0)+IF(AE$11=FB145,-EI145,0) | AF66: =IF(AF$11=FB141,-EI141,0)+IF(AF$11=FB142,-EI142,0)+IF(AF$11=FB143,-EI143,0)+IF(AF$11=FB144,-EI144,0)+IF(AF$11=FB145,-EI145,0) | AG66: =IF(AG$11=FB141,-EI141,0)+IF(AG$11=FB142,-EI142,0)+IF(AG$11=FB143,-EI143,0)+IF(AG$11=FB144,-EI144,0)+IF(AG$11=FB145,-EI145,0) | AH66: =IF(AH$11=FB141,-EI141,0)+IF(AH$11=FB142,-EI142,0)+IF(AH$11=FB143,-EI143,0)+IF(AH$11=FB144,-EI144,0)+IF(AH$11=FB145,-EI145,0) | AI66: =IF(AI$11=FB141,-EI141,0)+IF(AI$11=FB142,-EI142,0)+IF(AI$11=FB143,-EI143,0)+IF(AI$11=FB144,-EI144,0)+IF(AI$11=FB145,-EI145,0) | AJ66: =IF(AJ$11=FB141,-EI141,0)+IF(AJ$11=FB142,-EI142,0)+IF(AJ$11=FB143,-EI143,0)+IF(AJ$11=FB144,-EI144,0)+IF(AJ$11=FB145,-EI145,0) | AK66: =IF(AK$11=FB141,-EI141,0)+IF(AK$11=FB142,-EI142,0)+IF(AK$11=FB143,-EI143,0)+IF(AK$11=FB144,-EI144,0)+IF(AK$11=FB145,-EI145,0) | AL66: =IF(AL$11=FB141,-EI141,0)+IF(AL$11=FB142,-EI142,0)+IF(AL$11=FB143,-EI143,0)+IF(AL$11=FB144,-EI144,0)+IF(AL$11=FB145,-EI145,0) | AM66: =IF(AM$11=FB141,-EI141,0)+IF(AM$11=FB142,-EI142,0)+IF(AM$11=FB143,-EI143,0)+IF(AM$11=FB144,-EI144,0)+IF(AM$11=FB145,-EI145,0) | AN66: =IF(AN$11=FB141,-EI141,0)+IF(AN$11=FB142,-EI142,0)+IF(AN$11=FB143,-EI143,0)+IF(AN$11=FB144,-EI144,0)+IF(AN$11=FB145,-EI145,0) | AO66: =IF(AO$11=FB141,-EI141,0)+IF(AO$11=FB142,-EI142,0)+IF(AO$11=FB143,-EI143,0)+IF(AO$11=FB144,-EI144,0)+IF(AO$11=FB145,-EI145,0) | AP66: =IF(AP$11=FB141,-EI141,0)+IF(AP$11=FB142,-EI142,0)+IF(AP$11=FB143,-EI143,0)+IF(AP$11=FB144,-EI144,0)+IF(AP$11=FB145,-EI145,0) | AQ66: =IF(AQ$11=FB141,-EI141,0)+IF(AQ$11=FB142,-EI142,0)+IF(AQ$11=FB143,-EI143,0)+IF(AQ$11=FB144,-EI144,0)+IF(AQ$11=FB145,-EI145,0) | AR66: =IF(AR$11=FB141,-EI141,0)+IF(AR$11=FB142,-EI142,0)+IF(AR$11=FB143,-EI143,0)+IF(AR$11=FB144,-EI144,0)+IF(AR$11=FB145,-EI145,0) | AS66: =IF(AS$11=FB141,-EI141,0)+IF(AS$11=FB142,-EI142,0)+IF(AS$11=FB143,-EI143,0)+IF(AS$11=FB144,-EI144,0)+IF(AS$11=FB145,-EI145,0) | AT66: =IF(AT$11=FB141,-EI141,0)+IF(AT$11=FB142,-EI142,0)+IF(AT$11=FB143,-EI143,0)+IF(AT$11=FB144,-EI144,0)+IF(AT$11=FB145,-EI145,0) | AU66: =IF(AU$11=FB141,-EI141,0)+IF(AU$11=FB142,-EI142,0)+IF(AU$11=FB143,-EI143,0)+IF(AU$11=FB144,-EI144,0)+IF(AU$11=FB145,-EI145,0) | AV66: =IF(AV$11=FB141,-EI141,0)+IF(AV$11=FB142,-EI142,0)+IF(AV$11=FB143,-EI143,0)+IF(AV$11=FB144,-EI144,0)+IF(AV$11=FB145,-EI145,0) | AW66: =IF(AW$11=FB141,-EI141,0)+IF(AW$11=FB142,-EI142,0)+IF(AW$11=FB143,-EI143,0)+IF(AW$11=FB144,-EI144,0)+IF(AW$11=FB145,-EI145,0) | AX66: =IF(AX$11=FB141,-EI141,0)+IF(AX$11=FB142,-EI142,0)+IF(AX$11=FB143,-EI143,0)+IF(AX$11=FB144,-EI144,0)+IF(AX$11=FB145,-EI145,0) | AY66: =IF(AY$11=FB141,-EI141,0)+IF(AY$11=FB142,-EI142,0)+IF(AY$11=FB143,-EI143,0)+IF(AY$11=FB144,-EI144,0)+IF(AY$11=FB145,-EI145,0) | AZ66: =IF(AZ$11=FB141,-EI141,0)+IF(AZ$11=FB142,-EI142,0)+IF(AZ$11=FB143,-EI143,0)+IF(AZ$11=FB144,-EI144,0)+IF(AZ$11=FB145,-EI145,0) | BA66: =IF(BA$11=FB141,-EI141,0)+IF(BA$11=FB142,-EI142,0)+IF(BA$11=FB143,-EI143,0)+IF(BA$11=FB144,-EI144,0)+IF(BA$11=FB145,-EI145,0) | BB66: =IF(BB$11=FB141,-EI141,0)+IF(BB$11=FB142,-EI142,0)+IF(BB$11=FB143,-EI143,0)+IF(BB$11=FB144,-EI144,0)+IF(BB$11=FB145,-EI145,0) | BC66: =IF(BC$11=FB141,-EI141,0)+IF(BC$11=FB142,-EI142,0)+IF(BC$11=FB143,-EI143,0)+IF(BC$11=FB144,-EI144,0)+IF(BC$11=FB145,-EI145,0) | BD66: =IF(BD$11=FB141,-EI141,0)+IF(BD$11=FB142,-EI142,0)+IF(BD$11=FB143,-EI143,0)+IF(BD$11=FB144,-EI144,0)+IF(BD$11=FB145,-EI145,0) | BE66: =IF(BE$11=FB141,-EI141,0)+IF(BE$11=FB142,-EI142,0)+IF(BE$11=FB143,-EI143,0)+IF(BE$11=FB144,-EI144,0)+IF(BE$11=FB145,-EI145,0) | BF66: =IF(BF$11=FB141,-EI141,0)+IF(BF$11=FB142,-EI142,0)+IF(BF$11=FB143,-EI143,0)+IF(BF$11=FB144,-EI144,0)+IF(BF$11=FB145,-EI145,0) | BG66: =IF(BG$11=FB141,-EI141,0)+IF(BG$11=FB142,-EI142,0)+IF(BG$11=FB143,-EI143,0)+IF(BG$11=FB144,-EI144,0)+IF(BG$11=FB145,-EI145,0) | BH66: =IF(BH$11=FB141,-EI141,0)+IF(BH$11=FB142,-EI142,0)+IF(BH$11=FB143,-EI143,0)+IF(BH$11=FB144,-EI144,0)+IF(BH$11=FB145,-EI145,0) | BI66: =IF(BI$11=FB141,-EI141,0)+IF(BI$11=FB142,-EI142,0)+IF(BI$11=FB143,-EI143,0)+IF(BI$11=FB144,-EI144,0)+IF(BI$11=FB145,-EI145,0) | BJ66: =IF(BJ$11=FB141,-EI141,0)+IF(BJ$11=FB142,-EI142,0)+IF(BJ$11=FB143,-EI143,0)+IF(BJ$11=FB144,-EI144,0)+IF(BJ$11=FB145,-EI145,0) | BK66: =IF(BK$11=FB141,-EI141,0)+IF(BK$11=FB142,-EI142,0)+IF(BK$11=FB143,-EI143,0)+IF(BK$11=FB144,-EI144,0)+IF(BK$11=FB145,-EI145,0) | BL66: =IF(BL$11=FB141,-EI141,0)+IF(BL$11=FB142,-EI142,0)+IF(BL$11=FB143,-EI143,0)+IF(BL$11=FB144,-EI144,0)+IF(BL$11=FB145,-EI145,0) | BM66: =IF(BM$11=FC141,-EJ141,0)+IF(BM$11=FC142,-EJ142,0)+IF(BM$11=FC143,-EJ143,0)+IF(BM$11=FC144,-EJ144,0)+IF(BM$11=FC145,-EJ145,0) | BN66: =IF(BN$11=FD141,-EK141,0)+IF(BN$11=FD142,-EK142,0)+IF(BN$11=FD143,-EK143,0)+IF(BN$11=FD144,-EK144,0)+IF(BN$11=FD145,-EK145,0) | BO66: =IF(BO$11=FE141,-EL141,0)+IF(BO$11=FE142,-EL142,0)+IF(BO$11=FE143,-EL143,0)+IF(BO$11=FE144,-EL144,0)+IF(BO$11=FE145,-EL145,0) | BP66: =IF(BP$11=FF141,-EM141,0)+IF(BP$11=FF142,-EM142,0)+IF(BP$11=FF143,-EM143,0)+IF(BP$11=FF144,-EM144,0)+IF(BP$11=FF145,-EM145,0) | BQ66: =IF(BQ$11=FG141,-EN141,0)+IF(BQ$11=FG142,-EN142,0)+IF(BQ$11=FG143,-EN143,0)+IF(BQ$11=FG144,-EN144,0)+IF(BQ$11=FG145,-EN145,0) | BR66: =IF(BR$11=FH141,-EO141,0)+IF(BR$11=FH142,-EO142,0)+IF(BR$11=FH143,-EO143,0)+IF(BR$11=FH144,-EO144,0)+IF(BR$11=FH145,-EO145,0) | BS66: =IF(BS$11=FI141,-EP141,0)+IF(BS$11=FI142,-EP142,0)+IF(BS$11=FI143,-EP143,0)+IF(BS$11=FI144,-EP144,0)+IF(BS$11=FI145,-EP145,0) | ... DT66: =IF(DT$11=HJ141,-GQ141,0)+IF(DT$11=HJ142,-GQ142,0)+IF(DT$11=HJ143,-GQ143,0)+IF(DT$11=HJ144,-GQ144,0)+IF(DT$11=HJ145,-GQ145,0)
A67: Market Leasing Commissions | C67: =SUM(D67:DT67) | D67: =IF(D$11=FB146,-EI146,0)+IF(D$11=FB147,-EI147,0)+IF(D$11=FB148,-EI148,0)+IF(D$11=FB149,-EI149,0)+IF(D$11=FB150,-EI150,0) | E67: =IF(E$11=FB146,-EI146,0)+IF(E$11=FB147,-EI147,0)+IF(E$11=FB148,-EI148,0)+IF(E$11=FB149,-EI149,0)+IF(E$11=FB150,-EI150,0) | F67: =IF(F$11=FB146,-EI146,0)+IF(F$11=FB147,-EI147,0)+IF(F$11=FB148,-EI148,0)+IF(F$11=FB149,-EI149,0)+IF(F$11=FB150,-EI150,0) | G67: =IF(G$11=FB146,-EI146,0)+IF(G$11=FB147,-EI147,0)+IF(G$11=FB148,-EI148,0)+IF(G$11=FB149,-EI149,0)+IF(G$11=FB150,-EI150,0) | H67: =IF(H$11=FB146,-EI146,0)+IF(H$11=FB147,-EI147,0)+IF(H$11=FB148,-EI148,0)+IF(H$11=FB149,-EI149,0)+IF(H$11=FB150,-EI150,0) | I67: =IF(I$11=FB146,-EI146,0)+IF(I$11=FB147,-EI147,0)+IF(I$11=FB148,-EI148,0)+IF(I$11=FB149,-EI149,0)+IF(I$11=FB150,-EI150,0) | J67: =IF(J$11=FB146,-EI146,0)+IF(J$11=FB147,-EI147,0)+IF(J$11=FB148,-EI148,0)+IF(J$11=FB149,-EI149,0)+IF(J$11=FB150,-EI150,0) | K67: =IF(K$11=FB146,-EI146,0)+IF(K$11=FB147,-EI147,0)+IF(K$11=FB148,-EI148,0)+IF(K$11=FB149,-EI149,0)+IF(K$11=FB150,-EI150,0) | L67: =IF(L$11=FB146,-EI146,0)+IF(L$11=FB147,-EI147,0)+IF(L$11=FB148,-EI148,0)+IF(L$11=FB149,-EI149,0)+IF(L$11=FB150,-EI150,0) | M67: =IF(M$11=FB146,-EI146,0)+IF(M$11=FB147,-EI147,0)+IF(M$11=FB148,-EI148,0)+IF(M$11=FB149,-EI149,0)+IF(M$11=FB150,-EI150,0) | N67: =IF(N$11=FB146,-EI146,0)+IF(N$11=FB147,-EI147,0)+IF(N$11=FB148,-EI148,0)+IF(N$11=FB149,-EI149,0)+IF(N$11=FB150,-EI150,0) | O67: =IF(O$11=FB146,-EI146,0)+IF(O$11=FB147,-EI147,0)+IF(O$11=FB148,-EI148,0)+IF(O$11=FB149,-EI149,0)+IF(O$11=FB150,-EI150,0) | P67: =IF(P$11=FB146,-EI146,0)+IF(P$11=FB147,-EI147,0)+IF(P$11=FB148,-EI148,0)+IF(P$11=FB149,-EI149,0)+IF(P$11=FB150,-EI150,0) | Q67: =IF(Q$11=FB146,-EI146,0)+IF(Q$11=FB147,-EI147,0)+IF(Q$11=FB148,-EI148,0)+IF(Q$11=FB149,-EI149,0)+IF(Q$11=FB150,-EI150,0) | R67: =IF(R$11=FB146,-EI146,0)+IF(R$11=FB147,-EI147,0)+IF(R$11=FB148,-EI148,0)+IF(R$11=FB149,-EI149,0)+IF(R$11=FB150,-EI150,0) | S67: =IF(S$11=FB146,-EI146,0)+IF(S$11=FB147,-EI147,0)+IF(S$11=FB148,-EI148,0)+IF(S$11=FB149,-EI149,0)+IF(S$11=FB150,-EI150,0) | T67: =IF(T$11=FB146,-EI146,0)+IF(T$11=FB147,-EI147,0)+IF(T$11=FB148,-EI148,0)+IF(T$11=FB149,-EI149,0)+IF(T$11=FB150,-EI150,0) | U67: =IF(U$11=FB146,-EI146,0)+IF(U$11=FB147,-EI147,0)+IF(U$11=FB148,-EI148,0)+IF(U$11=FB149,-EI149,0)+IF(U$11=FB150,-EI150,0) | V67: =IF(V$11=FB146,-EI146,0)+IF(V$11=FB147,-EI147,0)+IF(V$11=FB148,-EI148,0)+IF(V$11=FB149,-EI149,0)+IF(V$11=FB150,-EI150,0) | W67: =IF(W$11=FB146,-EI146,0)+IF(W$11=FB147,-EI147,0)+IF(W$11=FB148,-EI148,0)+IF(W$11=FB149,-EI149,0)+IF(W$11=FB150,-EI150,0) | X67: =IF(X$11=FB146,-EI146,0)+IF(X$11=FB147,-EI147,0)+IF(X$11=FB148,-EI148,0)+IF(X$11=FB149,-EI149,0)+IF(X$11=FB150,-EI150,0) | Y67: =IF(Y$11=FB146,-EI146,0)+IF(Y$11=FB147,-EI147,0)+IF(Y$11=FB148,-EI148,0)+IF(Y$11=FB149,-EI149,0)+IF(Y$11=FB150,-EI150,0) | Z67: =IF(Z$11=FB146,-EI146,0)+IF(Z$11=FB147,-EI147,0)+IF(Z$11=FB148,-EI148,0)+IF(Z$11=FB149,-EI149,0)+IF(Z$11=FB150,-EI150,0) | AA67: =IF(AA$11=FB146,-EI146,0)+IF(AA$11=FB147,-EI147,0)+IF(AA$11=FB148,-EI148,0)+IF(AA$11=FB149,-EI149,0)+IF(AA$11=FB150,-EI150,0) | AB67: =IF(AB$11=FB146,-EI146,0)+IF(AB$11=FB147,-EI147,0)+IF(AB$11=FB148,-EI148,0)+IF(AB$11=FB149,-EI149,0)+IF(AB$11=FB150,-EI150,0) | AC67: =IF(AC$11=FB146,-EI146,0)+IF(AC$11=FB147,-EI147,0)+IF(AC$11=FB148,-EI148,0)+IF(AC$11=FB149,-EI149,0)+IF(AC$11=FB150,-EI150,0) | AD67: =IF(AD$11=FB146,-EI146,0)+IF(AD$11=FB147,-EI147,0)+IF(AD$11=FB148,-EI148,0)+IF(AD$11=FB149,-EI149,0)+IF(AD$11=FB150,-EI150,0) | AE67: =IF(AE$11=FB146,-EI146,0)+IF(AE$11=FB147,-EI147,0)+IF(AE$11=FB148,-EI148,0)+IF(AE$11=FB149,-EI149,0)+IF(AE$11=FB150,-EI150,0) | AF67: =IF(AF$11=FB146,-EI146,0)+IF(AF$11=FB147,-EI147,0)+IF(AF$11=FB148,-EI148,0)+IF(AF$11=FB149,-EI149,0)+IF(AF$11=FB150,-EI150,0) | AG67: =IF(AG$11=FB146,-EI146,0)+IF(AG$11=FB147,-EI147,0)+IF(AG$11=FB148,-EI148,0)+IF(AG$11=FB149,-EI149,0)+IF(AG$11=FB150,-EI150,0) | AH67: =IF(AH$11=FB146,-EI146,0)+IF(AH$11=FB147,-EI147,0)+IF(AH$11=FB148,-EI148,0)+IF(AH$11=FB149,-EI149,0)+IF(AH$11=FB150,-EI150,0) | AI67: =IF(AI$11=FB146,-EI146,0)+IF(AI$11=FB147,-EI147,0)+IF(AI$11=FB148,-EI148,0)+IF(AI$11=FB149,-EI149,0)+IF(AI$11=FB150,-EI150,0) | AJ67: =IF(AJ$11=FB146,-EI146,0)+IF(AJ$11=FB147,-EI147,0)+IF(AJ$11=FB148,-EI148,0)+IF(AJ$11=FB149,-EI149,0)+IF(AJ$11=FB150,-EI150,0) | AK67: =IF(AK$11=FB146,-EI146,0)+IF(AK$11=FB147,-EI147,0)+IF(AK$11=FB148,-EI148,0)+IF(AK$11=FB149,-EI149,0)+IF(AK$11=FB150,-EI150,0) | AL67: =IF(AL$11=FB146,-EI146,0)+IF(AL$11=FB147,-EI147,0)+IF(AL$11=FB148,-EI148,0)+IF(AL$11=FB149,-EI149,0)+IF(AL$11=FB150,-EI150,0) | AM67: =IF(AM$11=FB146,-EI146,0)+IF(AM$11=FB147,-EI147,0)+IF(AM$11=FB148,-EI148,0)+IF(AM$11=FB149,-EI149,0)+IF(AM$11=FB150,-EI150,0) | AN67: =IF(AN$11=FB146,-EI146,0)+IF(AN$11=FB147,-EI147,0)+IF(AN$11=FB148,-EI148,0)+IF(AN$11=FB149,-EI149,0)+IF(AN$11=FB150,-EI150,0) | AO67: =IF(AO$11=FB146,-EI146,0)+IF(AO$11=FB147,-EI147,0)+IF(AO$11=FB148,-EI148,0)+IF(AO$11=FB149,-EI149,0)+IF(AO$11=FB150,-EI150,0) | AP67: =IF(AP$11=FB146,-EI146,0)+IF(AP$11=FB147,-EI147,0)+IF(AP$11=FB148,-EI148,0)+IF(AP$11=FB149,-EI149,0)+IF(AP$11=FB150,-EI150,0) | AQ67: =IF(AQ$11=FB146,-EI146,0)+IF(AQ$11=FB147,-EI147,0)+IF(AQ$11=FB148,-EI148,0)+IF(AQ$11=FB149,-EI149,0)+IF(AQ$11=FB150,-EI150,0) | AR67: =IF(AR$11=FB146,-EI146,0)+IF(AR$11=FB147,-EI147,0)+IF(AR$11=FB148,-EI148,0)+IF(AR$11=FB149,-EI149,0)+IF(AR$11=FB150,-EI150,0) | AS67: =IF(AS$11=FB146,-EI146,0)+IF(AS$11=FB147,-EI147,0)+IF(AS$11=FB148,-EI148,0)+IF(AS$11=FB149,-EI149,0)+IF(AS$11=FB150,-EI150,0) | AT67: =IF(AT$11=FB146,-EI146,0)+IF(AT$11=FB147,-EI147,0)+IF(AT$11=FB148,-EI148,0)+IF(AT$11=FB149,-EI149,0)+IF(AT$11=FB150,-EI150,0) | AU67: =IF(AU$11=FB146,-EI146,0)+IF(AU$11=FB147,-EI147,0)+IF(AU$11=FB148,-EI148,0)+IF(AU$11=FB149,-EI149,0)+IF(AU$11=FB150,-EI150,0) | AV67: =IF(AV$11=FB146,-EI146,0)+IF(AV$11=FB147,-EI147,0)+IF(AV$11=FB148,-EI148,0)+IF(AV$11=FB149,-EI149,0)+IF(AV$11=FB150,-EI150,0) | AW67: =IF(AW$11=FB146,-EI146,0)+IF(AW$11=FB147,-EI147,0)+IF(AW$11=FB148,-EI148,0)+IF(AW$11=FB149,-EI149,0)+IF(AW$11=FB150,-EI150,0) | AX67: =IF(AX$11=FB146,-EI146,0)+IF(AX$11=FB147,-EI147,0)+IF(AX$11=FB148,-EI148,0)+IF(AX$11=FB149,-EI149,0)+IF(AX$11=FB150,-EI150,0) | AY67: =IF(AY$11=FB146,-EI146,0)+IF(AY$11=FB147,-EI147,0)+IF(AY$11=FB148,-EI148,0)+IF(AY$11=FB149,-EI149,0)+IF(AY$11=FB150,-EI150,0) | AZ67: =IF(AZ$11=FB146,-EI146,0)+IF(AZ$11=FB147,-EI147,0)+IF(AZ$11=FB148,-EI148,0)+IF(AZ$11=FB149,-EI149,0)+IF(AZ$11=FB150,-EI150,0) | BA67: =IF(BA$11=FB146,-EI146,0)+IF(BA$11=FB147,-EI147,0)+IF(BA$11=FB148,-EI148,0)+IF(BA$11=FB149,-EI149,0)+IF(BA$11=FB150,-EI150,0) | BB67: =IF(BB$11=FB146,-EI146,0)+IF(BB$11=FB147,-EI147,0)+IF(BB$11=FB148,-EI148,0)+IF(BB$11=FB149,-EI149,0)+IF(BB$11=FB150,-EI150,0) | BC67: =IF(BC$11=FB146,-EI146,0)+IF(BC$11=FB147,-EI147,0)+IF(BC$11=FB148,-EI148,0)+IF(BC$11=FB149,-EI149,0)+IF(BC$11=FB150,-EI150,0) | BD67: =IF(BD$11=FB146,-EI146,0)+IF(BD$11=FB147,-EI147,0)+IF(BD$11=FB148,-EI148,0)+IF(BD$11=FB149,-EI149,0)+IF(BD$11=FB150,-EI150,0) | BE67: =IF(BE$11=FB146,-EI146,0)+IF(BE$11=FB147,-EI147,0)+IF(BE$11=FB148,-EI148,0)+IF(BE$11=FB149,-EI149,0)+IF(BE$11=FB150,-EI150,0) | BF67: =IF(BF$11=FB146,-EI146,0)+IF(BF$11=FB147,-EI147,0)+IF(BF$11=FB148,-EI148,0)+IF(BF$11=FB149,-EI149,0)+IF(BF$11=FB150,-EI150,0) | BG67: =IF(BG$11=FB146,-EI146,0)+IF(BG$11=FB147,-EI147,0)+IF(BG$11=FB148,-EI148,0)+IF(BG$11=FB149,-EI149,0)+IF(BG$11=FB150,-EI150,0) | BH67: =IF(BH$11=FB146,-EI146,0)+IF(BH$11=FB147,-EI147,0)+IF(BH$11=FB148,-EI148,0)+IF(BH$11=FB149,-EI149,0)+IF(BH$11=FB150,-EI150,0) | BI67: =IF(BI$11=FB146,-EI146,0)+IF(BI$11=FB147,-EI147,0)+IF(BI$11=FB148,-EI148,0)+IF(BI$11=FB149,-EI149,0)+IF(BI$11=FB150,-EI150,0) | BJ67: =IF(BJ$11=FB146,-EI146,0)+IF(BJ$11=FB147,-EI147,0)+IF(BJ$11=FB148,-EI148,0)+IF(BJ$11=FB149,-EI149,0)+IF(BJ$11=FB150,-EI150,0) | BK67: =IF(BK$11=FB146,-EI146,0)+IF(BK$11=FB147,-EI147,0)+IF(BK$11=FB148,-EI148,0)+IF(BK$11=FB149,-EI149,0)+IF(BK$11=FB150,-EI150,0) | BL67: =IF(BL$11=FB146,-EI146,0)+IF(BL$11=FB147,-EI147,0)+IF(BL$11=FB148,-EI148,0)+IF(BL$11=FB149,-EI149,0)+IF(BL$11=FB150,-EI150,0) | BM67: =IF(BM$11=FC146,-EJ146,0)+IF(BM$11=FC147,-EJ147,0)+IF(BM$11=FC148,-EJ148,0)+IF(BM$11=FC149,-EJ149,0)+IF(BM$11=FC150,-EJ150,0) | BN67: =IF(BN$11=FD146,-EK146,0)+IF(BN$11=FD147,-EK147,0)+IF(BN$11=FD148,-EK148,0)+IF(BN$11=FD149,-EK149,0)+IF(BN$11=FD150,-EK150,0) | BO67: =IF(BO$11=FE146,-EL146,0)+IF(BO$11=FE147,-EL147,0)+IF(BO$11=FE148,-EL148,0)+IF(BO$11=FE149,-EL149,0)+IF(BO$11=FE150,-EL150,0) | BP67: =IF(BP$11=FF146,-EM146,0)+IF(BP$11=FF147,-EM147,0)+IF(BP$11=FF148,-EM148,0)+IF(BP$11=FF149,-EM149,0)+IF(BP$11=FF150,-EM150,0) | BQ67: =IF(BQ$11=FG146,-EN146,0)+IF(BQ$11=FG147,-EN147,0)+IF(BQ$11=FG148,-EN148,0)+IF(BQ$11=FG149,-EN149,0)+IF(BQ$11=FG150,-EN150,0) | BR67: =IF(BR$11=FH146,-EO146,0)+IF(BR$11=FH147,-EO147,0)+IF(BR$11=FH148,-EO148,0)+IF(BR$11=FH149,-EO149,0)+IF(BR$11=FH150,-EO150,0) | BS67: =IF(BS$11=FI146,-EP146,0)+IF(BS$11=FI147,-EP147,0)+IF(BS$11=FI148,-EP148,0)+IF(BS$11=FI149,-EP149,0)+IF(BS$11=FI150,-EP150,0) | ... DT67: =IF(DT$11=HJ146,-GQ146,0)+IF(DT$11=HJ147,-GQ147,0)+IF(DT$11=HJ148,-GQ148,0)+IF(DT$11=HJ149,-GQ149,0)+IF(DT$11=HJ150,-GQ150,0)
A68: CapEx Reserves | C68: =SUM(D68:DT68) | D68: =IF(D$11=0,0,-ROUND(Assumptions!$F$13*Assumptions!$P$34*(1+Assumptions!$P$38)^(D$9-1)/12,0)) | E68: =IF(E$11=0,0,-ROUND(Assumptions!$F$13*Assumptions!$P$34*(1+Assumptions!$P$38)^(E$9-1)/12,0)) | F68: =IF(F$11=0,0,-ROUND(Assumptions!$F$13*Assumptions!$P$34*(1+Assumptions!$P$38)^(F$9-1)/12,0)) | G68: =IF(G$11=0,0,-ROUND(Assumptions!$F$13*Assumptions!$P$34*(1+Assumptions!$P$38)^(G$9-1)/12,0)) | H68: =IF(H$11=0,0,-ROUND(Assumptions!$F$13*Assumptions!$P$34*(1+Assumptions!$P$38)^(H$9-1)/12,0)) | I68: =IF(I$11=0,0,-ROUND(Assumptions!$F$13*Assumptions!$P$34*(1+Assumptions!$P$38)^(I$9-1)/12,0)) | J68: =IF(J$11=0,0,-ROUND(Assumptions!$F$13*Assumptions!$P$34*(1+Assumptions!$P$38)^(J$9-1)/12,0)) | K68: =IF(K$11=0,0,-ROUND(Assumptions!$F$13*Assumptions!$P$34*(1+Assumptions!$P$38)^(K$9-1)/12,0)) | ... DT68: =IF(DT$11=0,0,-ROUND(Assumptions!$F$13*Assumptions!$P$34*(1+Assumptions!$P$38)^(DT$9-1)/12,0))
A69: Other CapEx (Not Incl. in Reno. Costs) | C69: =SUM(D69:DT69) | D69: =0 | E69: =0 | F69: =0 | G69: =0 | H69: =0 | I69: =0 | J69: =0 | K69: =0 | ... DT69: =0
A70: Total Capital Expenditures | C70: =SUM(D70:DT70) | D70: =SUM(D$64,D$65,D$66,D$67,D$68,D$69) | E70: =SUM(E$64,E$65,E$66,E$67,E$68,E$69) | F70: =SUM(F$64,F$65,F$66,F$67,F$68,F$69) | G70: =SUM(G$64,G$65,G$66,G$67,G$68,G$69) | H70: =SUM(H$64,H$65,H$66,H$67,H$68,H$69) | I70: =SUM(I$64,I$65,I$66,I$67,I$68,I$69) | J70: =SUM(J$64,J$65,J$66,J$67,J$68,J$69) | K70: =SUM(K$64,K$65,K$66,K$67,K$68,K$69) | ... DT70: =SUM(DT$64,DT$65,DT$66,DT$67,DT$68,DT$69)
A72: Unlevered Operating Cash Flow | C72: =SUM(D72:DT72) | D72: =D$56+D$70 | E72: =E$56+E$70 | F72: =F$56+F$70 | G72: =G$56+G$70 | H72: =H$56+H$70 | I72: =I$56+I$70 | J72: =J$56+J$70 | K72: =K$56+K$70 | ... DT72: =DT$56+DT$70
A73: DSCR | D73: =IF(IF(D$11=0,0,IF(D$11<=36,-D$183,-D$191))=0,"N/A",D$72/IF(D$11=0,0,IF(D$11<=36,-D$183,-D$191))) | E73: =IF(IF(E$11=0,0,IF(E$11<=36,-E$183,-E$191))=0,"N/A",E$72/IF(E$11=0,0,IF(E$11<=36,-E$183,-E$191))) | F73: =IF(IF(F$11=0,0,IF(F$11<=36,-F$183,-F$191))=0,"N/A",F$72/IF(F$11=0,0,IF(F$11<=36,-F$183,-F$191))) | G73: =IF(IF(G$11=0,0,IF(G$11<=36,-G$183,-G$191))=0,"N/A",G$72/IF(G$11=0,0,IF(G$11<=36,-G$183,-G$191))) | H73: =IF(IF(H$11=0,0,IF(H$11<=36,-H$183,-H$191))=0,"N/A",H$72/IF(H$11=0,0,IF(H$11<=36,-H$183,-H$191))) | I73: =IF(IF(I$11=0,0,IF(I$11<=36,-I$183,-I$191))=0,"N/A",I$72/IF(I$11=0,0,IF(I$11<=36,-I$183,-I$191))) | J73: =IF(IF(J$11=0,0,IF(J$11<=36,-J$183,-J$191))=0,"N/A",J$72/IF(J$11=0,0,IF(J$11<=36,-J$183,-J$191))) | K73: =IF(IF(K$11=0,0,IF(K$11<=36,-K$183,-K$191))=0,"N/A",K$72/IF(K$11=0,0,IF(K$11<=36,-K$183,-K$191))) | ... DT73: =IF(IF(DT$11=0,0,IF(DT$11<=36,-DT$183,-DT$191))=0,"N/A",DT$72/IF(DT$11=0,0,IF(DT$11<=36,-DT$183,-DT$191)))
A75: Building Schedule | C75: =SUM(D75:DT75)
A76: Building Purchase | C76: =SUM(D76:DT76) | D76: =IF(D$11=0,-Assumptions!$F$24,0) | E76: =IF(E$11=0,-Assumptions!$F$24,0) | F76: =IF(F$11=0,-Assumptions!$F$24,0) | G76: =IF(G$11=0,-Assumptions!$F$24,0) | H76: =IF(H$11=0,-Assumptions!$F$24,0) | I76: =IF(I$11=0,-Assumptions!$F$24,0) | J76: =IF(J$11=0,-Assumptions!$F$24,0) | K76: =IF(K$11=0,-Assumptions!$F$24,0) | ... DT76: =IF(DT$11=0,-Assumptions!$F$24,0)
A78: Hard Costs | C78: =SUM(D78:DT78)
A79: Shell Industrial | C79: =SUM(D79:DT79) | D79: =IF(AND(D$11>=(12*(YEAR('Renovation Budget'!$F$9)-YEAR(Assumptions!$F$11))+(MONTH('Renovation Budget'!$F$9)-MONTH(Assumptions!$F$11))),D$11<=((12*(YEAR('Renovation Budget'!$F$9)-YEAR(Assumptions!$F$11))+(MONTH('Renovation Budget'!$F$9)-MONTH(Assumptions!$F$11)))+'Renovation Budget'!$G$9-1)),-'Renovation Budget'!$C$9/'Renovation Budget'!$G$9,0) | E79: =IF(AND(E$11>=(12*(YEAR('Renovation Budget'!$F$9)-YEAR(Assumptions!$F$11))+(MONTH('Renovation Budget'!$F$9)-MONTH(Assumptions!$F$11))),E$11<=((12*(YEAR('Renovation Budget'!$F$9)-YEAR(Assumptions!$F$11))+(MONTH('Renovation Budget'!$F$9)-MONTH(Assumptions!$F$11)))+'Renovation Budget'!$G$9-1)),-'Renovation Budget'!$C$9/'Renovation Budget'!$G$9,0) | F79: =IF(AND(F$11>=(12*(YEAR('Renovation Budget'!$F$9)-YEAR(Assumptions!$F$11))+(MONTH('Renovation Budget'!$F$9)-MONTH(Assumptions!$F$11))),F$11<=((12*(YEAR('Renovation Budget'!$F$9)-YEAR(Assumptions!$F$11))+(MONTH('Renovation Budget'!$F$9)-MONTH(Assumptions!$F$11)))+'Renovation Budget'!$G$9-1)),-'Renovation Budget'!$C$9/'Renovation Budget'!$G$9,0) | G79: =IF(AND(G$11>=(12*(YEAR('Renovation Budget'!$F$9)-YEAR(Assumptions!$F$11))+(MONTH('Renovation Budget'!$F$9)-MONTH(Assumptions!$F$11))),G$11<=((12*(YEAR('Renovation Budget'!$F$9)-YEAR(Assumptions!$F$11))+(MONTH('Renovation Budget'!$F$9)-MONTH(Assumptions!$F$11)))+'Renovation Budget'!$G$9-1)),-'Renovation Budget'!$C$9/'Renovation Budget'!$G$9,0) | H79: =IF(AND(H$11>=(12*(YEAR('Renovation Budget'!$F$9)-YEAR(Assumptions!$F$11))+(MONTH('Renovation Budget'!$F$9)-MONTH(Assumptions!$F$11))),H$11<=((12*(YEAR('Renovation Budget'!$F$9)-YEAR(Assumptions!$F$11))+(MONTH('Renovation Budget'!$F$9)-MONTH(Assumptions!$F$11)))+'Renovation Budget'!$G$9-1)),-'Renovation Budget'!$C$9/'Renovation Budget'!$G$9,0) | I79: =IF(AND(I$11>=(12*(YEAR('Renovation Budget'!$F$9)-YEAR(Assumptions!$F$11))+(MONTH('Renovation Budget'!$F$9)-MONTH(Assumptions!$F$11))),I$11<=((12*(YEAR('Renovation Budget'!$F$9)-YEAR(Assumptions!$F$11))+(MONTH('Renovation Budget'!$F$9)-MONTH(Assumptions!$F$11)))+'Renovation Budget'!$G$9-1)),-'Renovation Budget'!$C$9/'Renovation Budget'!$G$9,0) | J79: =IF(AND(J$11>=(12*(YEAR('Renovation Budget'!$F$9)-YEAR(Assumptions!$F$11))+(MONTH('Renovation Budget'!$F$9)-MONTH(Assumptions!$F$11))),J$11<=((12*(YEAR('Renovation Budget'!$F$9)-YEAR(Assumptions!$F$11))+(MONTH('Renovation Budget'!$F$9)-MONTH(Assumptions!$F$11)))+'Renovation Budget'!$G$9-1)),-'Renovation Budget'!$C$9/'Renovation Budget'!$G$9,0) | K79: =IF(AND(K$11>=(12*(YEAR('Renovation Budget'!$F$9)-YEAR(Assumptions!$F$11))+(MONTH('Renovation Budget'!$F$9)-MONTH(Assumptions!$F$11))),K$11<=((12*(YEAR('Renovation Budget'!$F$9)-YEAR(Assumptions!$F$11))+(MONTH('Renovation Budget'!$F$9)-MONTH(Assumptions!$F$11)))+'Renovation Budget'!$G$9-1)),-'Renovation Budget'!$C$9/'Renovation Budget'!$G$9,0) | ... DT79: =IF(AND(DT$11>=(12*(YEAR('Renovation Budget'!$F$9)-YEAR(Assumptions!$F$11))+(MONTH('Renovation Budget'!$F$9)-MONTH(Assumptions!$F$11))),DT$11<=((12*(YEAR('Renovation Budget'!$F$9)-YEAR(Assumptions!$F$11))+(MONTH('Renovation Budget'!$F$9)-MONTH(Assumptions!$F$11)))+'Renovation Budget'!$G$9-1)),-'Renovation Budget'!$C$9/'Renovation Budget'!$G$9,0)
A80: Sitework | C80: =SUM(D80:DT80) | D80: =IF(AND(D$11>=(12*(YEAR('Renovation Budget'!$F$10)-YEAR(Assumptions!$F$11))+(MONTH('Renovation Budget'!$F$10)-MONTH(Assumptions!$F$11))),D$11<=((12*(YEAR('Renovation Budget'!$F$10)-YEAR(Assumptions!$F$11))+(MONTH('Renovation Budget'!$F$10)-MONTH(Assumptions!$F$11)))+'Renovation Budget'!$G$10-1)),-'Renovation Budget'!$C$10/'Renovation Budget'!$G$10,0) | E80: =IF(AND(E$11>=(12*(YEAR('Renovation Budget'!$F$10)-YEAR(Assumptions!$F$11))+(MONTH('Renovation Budget'!$F$10)-MONTH(Assumptions!$F$11))),E$11<=((12*(YEAR('Renovation Budget'!$F$10)-YEAR(Assumptions!$F$11))+(MONTH('Renovation Budget'!$F$10)-MONTH(Assumptions!$F$11)))+'Renovation Budget'!$G$10-1)),-'Renovation Budget'!$C$10/'Renovation Budget'!$G$10,0) | F80: =IF(AND(F$11>=(12*(YEAR('Renovation Budget'!$F$10)-YEAR(Assumptions!$F$11))+(MONTH('Renovation Budget'!$F$10)-MONTH(Assumptions!$F$11))),F$11<=((12*(YEAR('Renovation Budget'!$F$10)-YEAR(Assumptions!$F$11))+(MONTH('Renovation Budget'!$F$10)-MONTH(Assumptions!$F$11)))+'Renovation Budget'!$G$10-1)),-'Renovation Budget'!$C$10/'Renovation Budget'!$G$10,0) | G80: =IF(AND(G$11>=(12*(YEAR('Renovation Budget'!$F$10)-YEAR(Assumptions!$F$11))+(MONTH('Renovation Budget'!$F$10)-MONTH(Assumptions!$F$11))),G$11<=((12*(YEAR('Renovation Budget'!$F$10)-YEAR(Assumptions!$F$11))+(MONTH('Renovation Budget'!$F$10)-MONTH(Assumptions!$F$11)))+'Renovation Budget'!$G$10-1)),-'Renovation Budget'!$C$10/'Renovation Budget'!$G$10,0) | H80: =IF(AND(H$11>=(12*(YEAR('Renovation Budget'!$F$10)-YEAR(Assumptions!$F$11))+(MONTH('Renovation Budget'!$F$10)-MONTH(Assumptions!$F$11))),H$11<=((12*(YEAR('Renovation Budget'!$F$10)-YEAR(Assumptions!$F$11))+(MONTH('Renovation Budget'!$F$10)-MONTH(Assumptions!$F$11)))+'Renovation Budget'!$G$10-1)),-'Renovation Budget'!$C$10/'Renovation Budget'!$G$10,0) | I80: =IF(AND(I$11>=(12*(YEAR('Renovation Budget'!$F$10)-YEAR(Assumptions!$F$11))+(MONTH('Renovation Budget'!$F$10)-MONTH(Assumptions!$F$11))),I$11<=((12*(YEAR('Renovation Budget'!$F$10)-YEAR(Assumptions!$F$11))+(MONTH('Renovation Budget'!$F$10)-MONTH(Assumptions!$F$11)))+'Renovation Budget'!$G$10-1)),-'Renovation Budget'!$C$10/'Renovation Budget'!$G$10,0) | J80: =IF(AND(J$11>=(12*(YEAR('Renovation Budget'!$F$10)-YEAR(Assumptions!$F$11))+(MONTH('Renovation Budget'!$F$10)-MONTH(Assumptions!$F$11))),J$11<=((12*(YEAR('Renovation Budget'!$F$10)-YEAR(Assumptions!$F$11))+(MONTH('Renovation Budget'!$F$10)-MONTH(Assumptions!$F$11)))+'Renovation Budget'!$G$10-1)),-'Renovation Budget'!$C$10/'Renovation Budget'!$G$10,0) | K80: =IF(AND(K$11>=(12*(YEAR('Renovation Budget'!$F$10)-YEAR(Assumptions!$F$11))+(MONTH('Renovation Budget'!$F$10)-MONTH(Assumptions!$F$11))),K$11<=((12*(YEAR('Renovation Budget'!$F$10)-YEAR(Assumptions!$F$11))+(MONTH('Renovation Budget'!$F$10)-MONTH(Assumptions!$F$11)))+'Renovation Budget'!$G$10-1)),-'Renovation Budget'!$C$10/'Renovation Budget'!$G$10,0) | ... DT80: =IF(AND(DT$11>=(12*(YEAR('Renovation Budget'!$F$10)-YEAR(Assumptions!$F$11))+(MONTH('Renovation Budget'!$F$10)-MONTH(Assumptions!$F$11))),DT$11<=((12*(YEAR('Renovation Budget'!$F$10)-YEAR(Assumptions!$F$11))+(MONTH('Renovation Budget'!$F$10)-MONTH(Assumptions!$F$11)))+'Renovation Budget'!$G$10-1)),-'Renovation Budget'!$C$10/'Renovation Budget'!$G$10,0)
A81: Landscape (Ground Level) | C81: =SUM(D81:DT81) | D81: =IF(AND(D$11>=(12*(YEAR('Renovation Budget'!$F$11)-YEAR(Assumptions!$F$11))+(MONTH('Renovation Budget'!$F$11)-MONTH(Assumptions!$F$11))),D$11<=((12*(YEAR('Renovation Budget'!$F$11)-YEAR(Assumptions!$F$11))+(MONTH('Renovation Budget'!$F$11)-MONTH(Assumptions!$F$11)))+'Renovation Budget'!$G$11-1)),-'Renovation Budget'!$C$11/'Renovation Budget'!$G$11,0) | E81: =IF(AND(E$11>=(12*(YEAR('Renovation Budget'!$F$11)-YEAR(Assumptions!$F$11))+(MONTH('Renovation Budget'!$F$11)-MONTH(Assumptions!$F$11))),E$11<=((12*(YEAR('Renovation Budget'!$F$11)-YEAR(Assumptions!$F$11))+(MONTH('Renovation Budget'!$F$11)-MONTH(Assumptions!$F$11)))+'Renovation Budget'!$G$11-1)),-'Renovation Budget'!$C$11/'Renovation Budget'!$G$11,0) | F81: =IF(AND(F$11>=(12*(YEAR('Renovation Budget'!$F$11)-YEAR(Assumptions!$F$11))+(MONTH('Renovation Budget'!$F$11)-MONTH(Assumptions!$F$11))),F$11<=((12*(YEAR('Renovation Budget'!$F$11)-YEAR(Assumptions!$F$11))+(MONTH('Renovation Budget'!$F$11)-MONTH(Assumptions!$F$11)))+'Renovation Budget'!$G$11-1)),-'Renovation Budget'!$C$11/'Renovation Budget'!$G$11,0) | G81: =IF(AND(G$11>=(12*(YEAR('Renovation Budget'!$F$11)-YEAR(Assumptions!$F$11))+(MONTH('Renovation Budget'!$F$11)-MONTH(Assumptions!$F$11))),G$11<=((12*(YEAR('Renovation Budget'!$F$11)-YEAR(Assumptions!$F$11))+(MONTH('Renovation Budget'!$F$11)-MONTH(Assumptions!$F$11)))+'Renovation Budget'!$G$11-1)),-'Renovation Budget'!$C$11/'Renovation Budget'!$G$11,0) | H81: =IF(AND(H$11>=(12*(YEAR('Renovation Budget'!$F$11)-YEAR(Assumptions!$F$11))+(MONTH('Renovation Budget'!$F$11)-MONTH(Assumptions!$F$11))),H$11<=((12*(YEAR('Renovation Budget'!$F$11)-YEAR(Assumptions!$F$11))+(MONTH('Renovation Budget'!$F$11)-MONTH(Assumptions!$F$11)))+'Renovation Budget'!$G$11-1)),-'Renovation Budget'!$C$11/'Renovation Budget'!$G$11,0) | I81: =IF(AND(I$11>=(12*(YEAR('Renovation Budget'!$F$11)-YEAR(Assumptions!$F$11))+(MONTH('Renovation Budget'!$F$11)-MONTH(Assumptions!$F$11))),I$11<=((12*(YEAR('Renovation Budget'!$F$11)-YEAR(Assumptions!$F$11))+(MONTH('Renovation Budget'!$F$11)-MONTH(Assumptions!$F$11)))+'Renovation Budget'!$G$11-1)),-'Renovation Budget'!$C$11/'Renovation Budget'!$G$11,0) | J81: =IF(AND(J$11>=(12*(YEAR('Renovation Budget'!$F$11)-YEAR(Assumptions!$F$11))+(MONTH('Renovation Budget'!$F$11)-MONTH(Assumptions!$F$11))),J$11<=((12*(YEAR('Renovation Budget'!$F$11)-YEAR(Assumptions!$F$11))+(MONTH('Renovation Budget'!$F$11)-MONTH(Assumptions!$F$11)))+'Renovation Budget'!$G$11-1)),-'Renovation Budget'!$C$11/'Renovation Budget'!$G$11,0) | K81: =IF(AND(K$11>=(12*(YEAR('Renovation Budget'!$F$11)-YEAR(Assumptions!$F$11))+(MONTH('Renovation Budget'!$F$11)-MONTH(Assumptions!$F$11))),K$11<=((12*(YEAR('Renovation Budget'!$F$11)-YEAR(Assumptions!$F$11))+(MONTH('Renovation Budget'!$F$11)-MONTH(Assumptions!$F$11)))+'Renovation Budget'!$G$11-1)),-'Renovation Budget'!$C$11/'Renovation Budget'!$G$11,0) | ... DT81: =IF(AND(DT$11>=(12*(YEAR('Renovation Budget'!$F$11)-YEAR(Assumptions!$F$11))+(MONTH('Renovation Budget'!$F$11)-MONTH(Assumptions!$F$11))),DT$11<=((12*(YEAR('Renovation Budget'!$F$11)-YEAR(Assumptions!$F$11))+(MONTH('Renovation Budget'!$F$11)-MONTH(Assumptions!$F$11)))+'Renovation Budget'!$G$11-1)),-'Renovation Budget'!$C$11/'Renovation Budget'!$G$11,0)
A82: Landscape (Amenity + Penthouse) | C82: =SUM(D82:DT82) | D82: =IF(AND(D$11>=(12*(YEAR('Renovation Budget'!$F$12)-YEAR(Assumptions!$F$11))+(MONTH('Renovation Budget'!$F$12)-MONTH(Assumptions!$F$11))),D$11<=((12*(YEAR('Renovation Budget'!$F$12)-YEAR(Assumptions!$F$11))+(MONTH('Renovation Budget'!$F$12)-MONTH(Assumptions!$F$11)))+'Renovation Budget'!$G$12-1)),-'Renovation Budget'!$C$12/'Renovation Budget'!$G$12,0) | E82: =IF(AND(E$11>=(12*(YEAR('Renovation Budget'!$F$12)-YEAR(Assumptions!$F$11))+(MONTH('Renovation Budget'!$F$12)-MONTH(Assumptions!$F$11))),E$11<=((12*(YEAR('Renovation Budget'!$F$12)-YEAR(Assumptions!$F$11))+(MONTH('Renovation Budget'!$F$12)-MONTH(Assumptions!$F$11)))+'Renovation Budget'!$G$12-1)),-'Renovation Budget'!$C$12/'Renovation Budget'!$G$12,0) | F82: =IF(AND(F$11>=(12*(YEAR('Renovation Budget'!$F$12)-YEAR(Assumptions!$F$11))+(MONTH('Renovation Budget'!$F$12)-MONTH(Assumptions!$F$11))),F$11<=((12*(YEAR('Renovation Budget'!$F$12)-YEAR(Assumptions!$F$11))+(MONTH('Renovation Budget'!$F$12)-MONTH(Assumptions!$F$11)))+'Renovation Budget'!$G$12-1)),-'Renovation Budget'!$C$12/'Renovation Budget'!$G$12,0) | G82: =IF(AND(G$11>=(12*(YEAR('Renovation Budget'!$F$12)-YEAR(Assumptions!$F$11))+(MONTH('Renovation Budget'!$F$12)-MONTH(Assumptions!$F$11))),G$11<=((12*(YEAR('Renovation Budget'!$F$12)-YEAR(Assumptions!$F$11))+(MONTH('Renovation Budget'!$F$12)-MONTH(Assumptions!$F$11)))+'Renovation Budget'!$G$12-1)),-'Renovation Budget'!$C$12/'Renovation Budget'!$G$12,0) | H82: =IF(AND(H$11>=(12*(YEAR('Renovation Budget'!$F$12)-YEAR(Assumptions!$F$11))+(MONTH('Renovation Budget'!$F$12)-MONTH(Assumptions!$F$11))),H$11<=((12*(YEAR('Renovation Budget'!$F$12)-YEAR(Assumptions!$F$11))+(MONTH('Renovation Budget'!$F$12)-MONTH(Assumptions!$F$11)))+'Renovation Budget'!$G$12-1)),-'Renovation Budget'!$C$12/'Renovation Budget'!$G$12,0) | I82: =IF(AND(I$11>=(12*(YEAR('Renovation Budget'!$F$12)-YEAR(Assumptions!$F$11))+(MONTH('Renovation Budget'!$F$12)-MONTH(Assumptions!$F$11))),I$11<=((12*(YEAR('Renovation Budget'!$F$12)-YEAR(Assumptions!$F$11))+(MONTH('Renovation Budget'!$F$12)-MONTH(Assumptions!$F$11)))+'Renovation Budget'!$G$12-1)),-'Renovation Budget'!$C$12/'Renovation Budget'!$G$12,0) | J82: =IF(AND(J$11>=(12*(YEAR('Renovation Budget'!$F$12)-YEAR(Assumptions!$F$11))+(MONTH('Renovation Budget'!$F$12)-MONTH(Assumptions!$F$11))),J$11<=((12*(YEAR('Renovation Budget'!$F$12)-YEAR(Assumptions!$F$11))+(MONTH('Renovation Budget'!$F$12)-MONTH(Assumptions!$F$11)))+'Renovation Budget'!$G$12-1)),-'Renovation Budget'!$C$12/'Renovation Budget'!$G$12,0) | K82: =IF(AND(K$11>=(12*(YEAR('Renovation Budget'!$F$12)-YEAR(Assumptions!$F$11))+(MONTH('Renovation Budget'!$F$12)-MONTH(Assumptions!$F$11))),K$11<=((12*(YEAR('Renovation Budget'!$F$12)-YEAR(Assumptions!$F$11))+(MONTH('Renovation Budget'!$F$12)-MONTH(Assumptions!$F$11)))+'Renovation Budget'!$G$12-1)),-'Renovation Budget'!$C$12/'Renovation Budget'!$G$12,0) | ... DT82: =IF(AND(DT$11>=(12*(YEAR('Renovation Budget'!$F$12)-YEAR(Assumptions!$F$11))+(MONTH('Renovation Budget'!$F$12)-MONTH(Assumptions!$F$11))),DT$11<=((12*(YEAR('Renovation Budget'!$F$12)-YEAR(Assumptions!$F$11))+(MONTH('Renovation Budget'!$F$12)-MONTH(Assumptions!$F$11)))+'Renovation Budget'!$G$12-1)),-'Renovation Budget'!$C$12/'Renovation Budget'!$G$12,0)
A83: Improvements | C83: =SUM(D83:DT83) | D83: =IF(AND(D$11>=(12*(YEAR('Renovation Budget'!$F$13)-YEAR(Assumptions!$F$11))+(MONTH('Renovation Budget'!$F$13)-MONTH(Assumptions!$F$11))),D$11<=((12*(YEAR('Renovation Budget'!$F$13)-YEAR(Assumptions!$F$11))+(MONTH('Renovation Budget'!$F$13)-MONTH(Assumptions!$F$11)))+'Renovation Budget'!$G$13-1)),-'Renovation Budget'!$C$13/'Renovation Budget'!$G$13,0) | E83: =IF(AND(E$11>=(12*(YEAR('Renovation Budget'!$F$13)-YEAR(Assumptions!$F$11))+(MONTH('Renovation Budget'!$F$13)-MONTH(Assumptions!$F$11))),E$11<=((12*(YEAR('Renovation Budget'!$F$13)-YEAR(Assumptions!$F$11))+(MONTH('Renovation Budget'!$F$13)-MONTH(Assumptions!$F$11)))+'Renovation Budget'!$G$13-1)),-'Renovation Budget'!$C$13/'Renovation Budget'!$G$13,0) | F83: =IF(AND(F$11>=(12*(YEAR('Renovation Budget'!$F$13)-YEAR(Assumptions!$F$11))+(MONTH('Renovation Budget'!$F$13)-MONTH(Assumptions!$F$11))),F$11<=((12*(YEAR('Renovation Budget'!$F$13)-YEAR(Assumptions!$F$11))+(MONTH('Renovation Budget'!$F$13)-MONTH(Assumptions!$F$11)))+'Renovation Budget'!$G$13-1)),-'Renovation Budget'!$C$13/'Renovation Budget'!$G$13,0) | G83: =IF(AND(G$11>=(12*(YEAR('Renovation Budget'!$F$13)-YEAR(Assumptions!$F$11))+(MONTH('Renovation Budget'!$F$13)-MONTH(Assumptions!$F$11))),G$11<=((12*(YEAR('Renovation Budget'!$F$13)-YEAR(Assumptions!$F$11))+(MONTH('Renovation Budget'!$F$13)-MONTH(Assumptions!$F$11)))+'Renovation Budget'!$G$13-1)),-'Renovation Budget'!$C$13/'Renovation Budget'!$G$13,0) | H83: =IF(AND(H$11>=(12*(YEAR('Renovation Budget'!$F$13)-YEAR(Assumptions!$F$11))+(MONTH('Renovation Budget'!$F$13)-MONTH(Assumptions!$F$11))),H$11<=((12*(YEAR('Renovation Budget'!$F$13)-YEAR(Assumptions!$F$11))+(MONTH('Renovation Budget'!$F$13)-MONTH(Assumptions!$F$11)))+'Renovation Budget'!$G$13-1)),-'Renovation Budget'!$C$13/'Renovation Budget'!$G$13,0) | I83: =IF(AND(I$11>=(12*(YEAR('Renovation Budget'!$F$13)-YEAR(Assumptions!$F$11))+(MONTH('Renovation Budget'!$F$13)-MONTH(Assumptions!$F$11))),I$11<=((12*(YEAR('Renovation Budget'!$F$13)-YEAR(Assumptions!$F$11))+(MONTH('Renovation Budget'!$F$13)-MONTH(Assumptions!$F$11)))+'Renovation Budget'!$G$13-1)),-'Renovation Budget'!$C$13/'Renovation Budget'!$G$13,0) | J83: =IF(AND(J$11>=(12*(YEAR('Renovation Budget'!$F$13)-YEAR(Assumptions!$F$11))+(MONTH('Renovation Budget'!$F$13)-MONTH(Assumptions!$F$11))),J$11<=((12*(YEAR('Renovation Budget'!$F$13)-YEAR(Assumptions!$F$11))+(MONTH('Renovation Budget'!$F$13)-MONTH(Assumptions!$F$11)))+'Renovation Budget'!$G$13-1)),-'Renovation Budget'!$C$13/'Renovation Budget'!$G$13,0) | K83: =IF(AND(K$11>=(12*(YEAR('Renovation Budget'!$F$13)-YEAR(Assumptions!$F$11))+(MONTH('Renovation Budget'!$F$13)-MONTH(Assumptions!$F$11))),K$11<=((12*(YEAR('Renovation Budget'!$F$13)-YEAR(Assumptions!$F$11))+(MONTH('Renovation Budget'!$F$13)-MONTH(Assumptions!$F$11)))+'Renovation Budget'!$G$13-1)),-'Renovation Budget'!$C$13/'Renovation Budget'!$G$13,0) | ... DT83: =IF(AND(DT$11>=(12*(YEAR('Renovation Budget'!$F$13)-YEAR(Assumptions!$F$11))+(MONTH('Renovation Budget'!$F$13)-MONTH(Assumptions!$F$11))),DT$11<=((12*(YEAR('Renovation Budget'!$F$13)-YEAR(Assumptions!$F$11))+(MONTH('Renovation Budget'!$F$13)-MONTH(Assumptions!$F$11)))+'Renovation Budget'!$G$13-1)),-'Renovation Budget'!$C$13/'Renovation Budget'!$G$13,0)
A84: Garage - Above Grade | C84: =SUM(D84:DT84) | D84: =IF(AND(D$11>=(12*(YEAR('Renovation Budget'!$F$14)-YEAR(Assumptions!$F$11))+(MONTH('Renovation Budget'!$F$14)-MONTH(Assumptions!$F$11))),D$11<=((12*(YEAR('Renovation Budget'!$F$14)-YEAR(Assumptions!$F$11))+(MONTH('Renovation Budget'!$F$14)-MONTH(Assumptions!$F$11)))+'Renovation Budget'!$G$14-1)),-'Renovation Budget'!$C$14/'Renovation Budget'!$G$14,0) | E84: =IF(AND(E$11>=(12*(YEAR('Renovation Budget'!$F$14)-YEAR(Assumptions!$F$11))+(MONTH('Renovation Budget'!$F$14)-MONTH(Assumptions!$F$11))),E$11<=((12*(YEAR('Renovation Budget'!$F$14)-YEAR(Assumptions!$F$11))+(MONTH('Renovation Budget'!$F$14)-MONTH(Assumptions!$F$11)))+'Renovation Budget'!$G$14-1)),-'Renovation Budget'!$C$14/'Renovation Budget'!$G$14,0) | F84: =IF(AND(F$11>=(12*(YEAR('Renovation Budget'!$F$14)-YEAR(Assumptions!$F$11))+(MONTH('Renovation Budget'!$F$14)-MONTH(Assumptions!$F$11))),F$11<=((12*(YEAR('Renovation Budget'!$F$14)-YEAR(Assumptions!$F$11))+(MONTH('Renovation Budget'!$F$14)-MONTH(Assumptions!$F$11)))+'Renovation Budget'!$G$14-1)),-'Renovation Budget'!$C$14/'Renovation Budget'!$G$14,0) | G84: =IF(AND(G$11>=(12*(YEAR('Renovation Budget'!$F$14)-YEAR(Assumptions!$F$11))+(MONTH('Renovation Budget'!$F$14)-MONTH(Assumptions!$F$11))),G$11<=((12*(YEAR('Renovation Budget'!$F$14)-YEAR(Assumptions!$F$11))+(MONTH('Renovation Budget'!$F$14)-MONTH(Assumptions!$F$11)))+'Renovation Budget'!$G$14-1)),-'Renovation Budget'!$C$14/'Renovation Budget'!$G$14,0) | H84: =IF(AND(H$11>=(12*(YEAR('Renovation Budget'!$F$14)-YEAR(Assumptions!$F$11))+(MONTH('Renovation Budget'!$F$14)-MONTH(Assumptions!$F$11))),H$11<=((12*(YEAR('Renovation Budget'!$F$14)-YEAR(Assumptions!$F$11))+(MONTH('Renovation Budget'!$F$14)-MONTH(Assumptions!$F$11)))+'Renovation Budget'!$G$14-1)),-'Renovation Budget'!$C$14/'Renovation Budget'!$G$14,0) | I84: =IF(AND(I$11>=(12*(YEAR('Renovation Budget'!$F$14)-YEAR(Assumptions!$F$11))+(MONTH('Renovation Budget'!$F$14)-MONTH(Assumptions!$F$11))),I$11<=((12*(YEAR('Renovation Budget'!$F$14)-YEAR(Assumptions!$F$11))+(MONTH('Renovation Budget'!$F$14)-MONTH(Assumptions!$F$11)))+'Renovation Budget'!$G$14-1)),-'Renovation Budget'!$C$14/'Renovation Budget'!$G$14,0) | J84: =IF(AND(J$11>=(12*(YEAR('Renovation Budget'!$F$14)-YEAR(Assumptions!$F$11))+(MONTH('Renovation Budget'!$F$14)-MONTH(Assumptions!$F$11))),J$11<=((12*(YEAR('Renovation Budget'!$F$14)-YEAR(Assumptions!$F$11))+(MONTH('Renovation Budget'!$F$14)-MONTH(Assumptions!$F$11)))+'Renovation Budget'!$G$14-1)),-'Renovation Budget'!$C$14/'Renovation Budget'!$G$14,0) | K84: =IF(AND(K$11>=(12*(YEAR('Renovation Budget'!$F$14)-YEAR(Assumptions!$F$11))+(MONTH('Renovation Budget'!$F$14)-MONTH(Assumptions!$F$11))),K$11<=((12*(YEAR('Renovation Budget'!$F$14)-YEAR(Assumptions!$F$11))+(MONTH('Renovation Budget'!$F$14)-MONTH(Assumptions!$F$11)))+'Renovation Budget'!$G$14-1)),-'Renovation Budget'!$C$14/'Renovation Budget'!$G$14,0) | ... DT84: =IF(AND(DT$11>=(12*(YEAR('Renovation Budget'!$F$14)-YEAR(Assumptions!$F$11))+(MONTH('Renovation Budget'!$F$14)-MONTH(Assumptions!$F$11))),DT$11<=((12*(YEAR('Renovation Budget'!$F$14)-YEAR(Assumptions!$F$11))+(MONTH('Renovation Budget'!$F$14)-MONTH(Assumptions!$F$11)))+'Renovation Budget'!$G$14-1)),-'Renovation Budget'!$C$14/'Renovation Budget'!$G$14,0)
A85: Thermal and Moisture Protection | C85: =SUM(D85:DT85) | D85: =IF(AND(D$11>=(12*(YEAR('Renovation Budget'!$F$15)-YEAR(Assumptions!$F$11))+(MONTH('Renovation Budget'!$F$15)-MONTH(Assumptions!$F$11))),D$11<=((12*(YEAR('Renovation Budget'!$F$15)-YEAR(Assumptions!$F$11))+(MONTH('Renovation Budget'!$F$15)-MONTH(Assumptions!$F$11)))+'Renovation Budget'!$G$15-1)),-'Renovation Budget'!$C$15/'Renovation Budget'!$G$15,0) | E85: =IF(AND(E$11>=(12*(YEAR('Renovation Budget'!$F$15)-YEAR(Assumptions!$F$11))+(MONTH('Renovation Budget'!$F$15)-MONTH(Assumptions!$F$11))),E$11<=((12*(YEAR('Renovation Budget'!$F$15)-YEAR(Assumptions!$F$11))+(MONTH('Renovation Budget'!$F$15)-MONTH(Assumptions!$F$11)))+'Renovation Budget'!$G$15-1)),-'Renovation Budget'!$C$15/'Renovation Budget'!$G$15,0) | F85: =IF(AND(F$11>=(12*(YEAR('Renovation Budget'!$F$15)-YEAR(Assumptions!$F$11))+(MONTH('Renovation Budget'!$F$15)-MONTH(Assumptions!$F$11))),F$11<=((12*(YEAR('Renovation Budget'!$F$15)-YEAR(Assumptions!$F$11))+(MONTH('Renovation Budget'!$F$15)-MONTH(Assumptions!$F$11)))+'Renovation Budget'!$G$15-1)),-'Renovation Budget'!$C$15/'Renovation Budget'!$G$15,0) | G85: =IF(AND(G$11>=(12*(YEAR('Renovation Budget'!$F$15)-YEAR(Assumptions!$F$11))+(MONTH('Renovation Budget'!$F$15)-MONTH(Assumptions!$F$11))),G$11<=((12*(YEAR('Renovation Budget'!$F$15)-YEAR(Assumptions!$F$11))+(MONTH('Renovation Budget'!$F$15)-MONTH(Assumptions!$F$11)))+'Renovation Budget'!$G$15-1)),-'Renovation Budget'!$C$15/'Renovation Budget'!$G$15,0) | H85: =IF(AND(H$11>=(12*(YEAR('Renovation Budget'!$F$15)-YEAR(Assumptions!$F$11))+(MONTH('Renovation Budget'!$F$15)-MONTH(Assumptions!$F$11))),H$11<=((12*(YEAR('Renovation Budget'!$F$15)-YEAR(Assumptions!$F$11))+(MONTH('Renovation Budget'!$F$15)-MONTH(Assumptions!$F$11)))+'Renovation Budget'!$G$15-1)),-'Renovation Budget'!$C$15/'Renovation Budget'!$G$15,0) | I85: =IF(AND(I$11>=(12*(YEAR('Renovation Budget'!$F$15)-YEAR(Assumptions!$F$11))+(MONTH('Renovation Budget'!$F$15)-MONTH(Assumptions!$F$11))),I$11<=((12*(YEAR('Renovation Budget'!$F$15)-YEAR(Assumptions!$F$11))+(MONTH('Renovation Budget'!$F$15)-MONTH(Assumptions!$F$11)))+'Renovation Budget'!$G$15-1)),-'Renovation Budget'!$C$15/'Renovation Budget'!$G$15,0) | J85: =IF(AND(J$11>=(12*(YEAR('Renovation Budget'!$F$15)-YEAR(Assumptions!$F$11))+(MONTH('Renovation Budget'!$F$15)-MONTH(Assumptions!$F$11))),J$11<=((12*(YEAR('Renovation Budget'!$F$15)-YEAR(Assumptions!$F$11))+(MONTH('Renovation Budget'!$F$15)-MONTH(Assumptions!$F$11)))+'Renovation Budget'!$G$15-1)),-'Renovation Budget'!$C$15/'Renovation Budget'!$G$15,0) | K85: =IF(AND(K$11>=(12*(YEAR('Renovation Budget'!$F$15)-YEAR(Assumptions!$F$11))+(MONTH('Renovation Budget'!$F$15)-MONTH(Assumptions!$F$11))),K$11<=((12*(YEAR('Renovation Budget'!$F$15)-YEAR(Assumptions!$F$11))+(MONTH('Renovation Budget'!$F$15)-MONTH(Assumptions!$F$11)))+'Renovation Budget'!$G$15-1)),-'Renovation Budget'!$C$15/'Renovation Budget'!$G$15,0) | ... DT85: =IF(AND(DT$11>=(12*(YEAR('Renovation Budget'!$F$15)-YEAR(Assumptions!$F$11))+(MONTH('Renovation Budget'!$F$15)-MONTH(Assumptions!$F$11))),DT$11<=((12*(YEAR('Renovation Budget'!$F$15)-YEAR(Assumptions!$F$11))+(MONTH('Renovation Budget'!$F$15)-MONTH(Assumptions!$F$11)))+'Renovation Budget'!$G$15-1)),-'Renovation Budget'!$C$15/'Renovation Budget'!$G$15,0)
A86: Doors and Windows | C86: =SUM(D86:DT86) | D86: =IF(AND(D$11>=(12*(YEAR('Renovation Budget'!$F$16)-YEAR(Assumptions!$F$11))+(MONTH('Renovation Budget'!$F$16)-MONTH(Assumptions!$F$11))),D$11<=((12*(YEAR('Renovation Budget'!$F$16)-YEAR(Assumptions!$F$11))+(MONTH('Renovation Budget'!$F$16)-MONTH(Assumptions!$F$11)))+'Renovation Budget'!$G$16-1)),-'Renovation Budget'!$C$16/'Renovation Budget'!$G$16,0) | E86: =IF(AND(E$11>=(12*(YEAR('Renovation Budget'!$F$16)-YEAR(Assumptions!$F$11))+(MONTH('Renovation Budget'!$F$16)-MONTH(Assumptions!$F$11))),E$11<=((12*(YEAR('Renovation Budget'!$F$16)-YEAR(Assumptions!$F$11))+(MONTH('Renovation Budget'!$F$16)-MONTH(Assumptions!$F$11)))+'Renovation Budget'!$G$16-1)),-'Renovation Budget'!$C$16/'Renovation Budget'!$G$16,0) | F86: =IF(AND(F$11>=(12*(YEAR('Renovation Budget'!$F$16)-YEAR(Assumptions!$F$11))+(MONTH('Renovation Budget'!$F$16)-MONTH(Assumptions!$F$11))),F$11<=((12*(YEAR('Renovation Budget'!$F$16)-YEAR(Assumptions!$F$11))+(MONTH('Renovation Budget'!$F$16)-MONTH(Assumptions!$F$11)))+'Renovation Budget'!$G$16-1)),-'Renovation Budget'!$C$16/'Renovation Budget'!$G$16,0) | G86: =IF(AND(G$11>=(12*(YEAR('Renovation Budget'!$F$16)-YEAR(Assumptions!$F$11))+(MONTH('Renovation Budget'!$F$16)-MONTH(Assumptions!$F$11))),G$11<=((12*(YEAR('Renovation Budget'!$F$16)-YEAR(Assumptions!$F$11))+(MONTH('Renovation Budget'!$F$16)-MONTH(Assumptions!$F$11)))+'Renovation Budget'!$G$16-1)),-'Renovation Budget'!$C$16/'Renovation Budget'!$G$16,0) | H86: =IF(AND(H$11>=(12*(YEAR('Renovation Budget'!$F$16)-YEAR(Assumptions!$F$11))+(MONTH('Renovation Budget'!$F$16)-MONTH(Assumptions!$F$11))),H$11<=((12*(YEAR('Renovation Budget'!$F$16)-YEAR(Assumptions!$F$11))+(MONTH('Renovation Budget'!$F$16)-MONTH(Assumptions!$F$11)))+'Renovation Budget'!$G$16-1)),-'Renovation Budget'!$C$16/'Renovation Budget'!$G$16,0) | I86: =IF(AND(I$11>=(12*(YEAR('Renovation Budget'!$F$16)-YEAR(Assumptions!$F$11))+(MONTH('Renovation Budget'!$F$16)-MONTH(Assumptions!$F$11))),I$11<=((12*(YEAR('Renovation Budget'!$F$16)-YEAR(Assumptions!$F$11))+(MONTH('Renovation Budget'!$F$16)-MONTH(Assumptions!$F$11)))+'Renovation Budget'!$G$16-1)),-'Renovation Budget'!$C$16/'Renovation Budget'!$G$16,0) | J86: =IF(AND(J$11>=(12*(YEAR('Renovation Budget'!$F$16)-YEAR(Assumptions!$F$11))+(MONTH('Renovation Budget'!$F$16)-MONTH(Assumptions!$F$11))),J$11<=((12*(YEAR('Renovation Budget'!$F$16)-YEAR(Assumptions!$F$11))+(MONTH('Renovation Budget'!$F$16)-MONTH(Assumptions!$F$11)))+'Renovation Budget'!$G$16-1)),-'Renovation Budget'!$C$16/'Renovation Budget'!$G$16,0) | K86: =IF(AND(K$11>=(12*(YEAR('Renovation Budget'!$F$16)-YEAR(Assumptions!$F$11))+(MONTH('Renovation Budget'!$F$16)-MONTH(Assumptions!$F$11))),K$11<=((12*(YEAR('Renovation Budget'!$F$16)-YEAR(Assumptions!$F$11))+(MONTH('Renovation Budget'!$F$16)-MONTH(Assumptions!$F$11)))+'Renovation Budget'!$G$16-1)),-'Renovation Budget'!$C$16/'Renovation Budget'!$G$16,0) | ... DT86: =IF(AND(DT$11>=(12*(YEAR('Renovation Budget'!$F$16)-YEAR(Assumptions!$F$11))+(MONTH('Renovation Budget'!$F$16)-MONTH(Assumptions!$F$11))),DT$11<=((12*(YEAR('Renovation Budget'!$F$16)-YEAR(Assumptions!$F$11))+(MONTH('Renovation Budget'!$F$16)-MONTH(Assumptions!$F$11)))+'Renovation Budget'!$G$16-1)),-'Renovation Budget'!$C$16/'Renovation Budget'!$G$16,0)
A87: Finishes | C87: =SUM(D87:DT87) | D87: =IF(AND(D$11>=(12*(YEAR('Renovation Budget'!$F$17)-YEAR(Assumptions!$F$11))+(MONTH('Renovation Budget'!$F$17)-MONTH(Assumptions!$F$11))),D$11<=((12*(YEAR('Renovation Budget'!$F$17)-YEAR(Assumptions!$F$11))+(MONTH('Renovation Budget'!$F$17)-MONTH(Assumptions!$F$11)))+'Renovation Budget'!$G$17-1)),-'Renovation Budget'!$C$17/'Renovation Budget'!$G$17,0) | E87: =IF(AND(E$11>=(12*(YEAR('Renovation Budget'!$F$17)-YEAR(Assumptions!$F$11))+(MONTH('Renovation Budget'!$F$17)-MONTH(Assumptions!$F$11))),E$11<=((12*(YEAR('Renovation Budget'!$F$17)-YEAR(Assumptions!$F$11))+(MONTH('Renovation Budget'!$F$17)-MONTH(Assumptions!$F$11)))+'Renovation Budget'!$G$17-1)),-'Renovation Budget'!$C$17/'Renovation Budget'!$G$17,0) | F87: =IF(AND(F$11>=(12*(YEAR('Renovation Budget'!$F$17)-YEAR(Assumptions!$F$11))+(MONTH('Renovation Budget'!$F$17)-MONTH(Assumptions!$F$11))),F$11<=((12*(YEAR('Renovation Budget'!$F$17)-YEAR(Assumptions!$F$11))+(MONTH('Renovation Budget'!$F$17)-MONTH(Assumptions!$F$11)))+'Renovation Budget'!$G$17-1)),-'Renovation Budget'!$C$17/'Renovation Budget'!$G$17,0) | G87: =IF(AND(G$11>=(12*(YEAR('Renovation Budget'!$F$17)-YEAR(Assumptions!$F$11))+(MONTH('Renovation Budget'!$F$17)-MONTH(Assumptions!$F$11))),G$11<=((12*(YEAR('Renovation Budget'!$F$17)-YEAR(Assumptions!$F$11))+(MONTH('Renovation Budget'!$F$17)-MONTH(Assumptions!$F$11)))+'Renovation Budget'!$G$17-1)),-'Renovation Budget'!$C$17/'Renovation Budget'!$G$17,0) | H87: =IF(AND(H$11>=(12*(YEAR('Renovation Budget'!$F$17)-YEAR(Assumptions!$F$11))+(MONTH('Renovation Budget'!$F$17)-MONTH(Assumptions!$F$11))),H$11<=((12*(YEAR('Renovation Budget'!$F$17)-YEAR(Assumptions!$F$11))+(MONTH('Renovation Budget'!$F$17)-MONTH(Assumptions!$F$11)))+'Renovation Budget'!$G$17-1)),-'Renovation Budget'!$C$17/'Renovation Budget'!$G$17,0) | I87: =IF(AND(I$11>=(12*(YEAR('Renovation Budget'!$F$17)-YEAR(Assumptions!$F$11))+(MONTH('Renovation Budget'!$F$17)-MONTH(Assumptions!$F$11))),I$11<=((12*(YEAR('Renovation Budget'!$F$17)-YEAR(Assumptions!$F$11))+(MONTH('Renovation Budget'!$F$17)-MONTH(Assumptions!$F$11)))+'Renovation Budget'!$G$17-1)),-'Renovation Budget'!$C$17/'Renovation Budget'!$G$17,0) | J87: =IF(AND(J$11>=(12*(YEAR('Renovation Budget'!$F$17)-YEAR(Assumptions!$F$11))+(MONTH('Renovation Budget'!$F$17)-MONTH(Assumptions!$F$11))),J$11<=((12*(YEAR('Renovation Budget'!$F$17)-YEAR(Assumptions!$F$11))+(MONTH('Renovation Budget'!$F$17)-MONTH(Assumptions!$F$11)))+'Renovation Budget'!$G$17-1)),-'Renovation Budget'!$C$17/'Renovation Budget'!$G$17,0) | K87: =IF(AND(K$11>=(12*(YEAR('Renovation Budget'!$F$17)-YEAR(Assumptions!$F$11))+(MONTH('Renovation Budget'!$F$17)-MONTH(Assumptions!$F$11))),K$11<=((12*(YEAR('Renovation Budget'!$F$17)-YEAR(Assumptions!$F$11))+(MONTH('Renovation Budget'!$F$17)-MONTH(Assumptions!$F$11)))+'Renovation Budget'!$G$17-1)),-'Renovation Budget'!$C$17/'Renovation Budget'!$G$17,0) | ... DT87: =IF(AND(DT$11>=(12*(YEAR('Renovation Budget'!$F$17)-YEAR(Assumptions!$F$11))+(MONTH('Renovation Budget'!$F$17)-MONTH(Assumptions!$F$11))),DT$11<=((12*(YEAR('Renovation Budget'!$F$17)-YEAR(Assumptions!$F$11))+(MONTH('Renovation Budget'!$F$17)-MONTH(Assumptions!$F$11)))+'Renovation Budget'!$G$17-1)),-'Renovation Budget'!$C$17/'Renovation Budget'!$G$17,0)
A88: Special Ties | C88: =SUM(D88:DT88) | D88: =IF(AND(D$11>=(12*(YEAR('Renovation Budget'!$F$18)-YEAR(Assumptions!$F$11))+(MONTH('Renovation Budget'!$F$18)-MONTH(Assumptions!$F$11))),D$11<=((12*(YEAR('Renovation Budget'!$F$18)-YEAR(Assumptions!$F$11))+(MONTH('Renovation Budget'!$F$18)-MONTH(Assumptions!$F$11)))+'Renovation Budget'!$G$18-1)),-'Renovation Budget'!$C$18/'Renovation Budget'!$G$18,0) | E88: =IF(AND(E$11>=(12*(YEAR('Renovation Budget'!$F$18)-YEAR(Assumptions!$F$11))+(MONTH('Renovation Budget'!$F$18)-MONTH(Assumptions!$F$11))),E$11<=((12*(YEAR('Renovation Budget'!$F$18)-YEAR(Assumptions!$F$11))+(MONTH('Renovation Budget'!$F$18)-MONTH(Assumptions!$F$11)))+'Renovation Budget'!$G$18-1)),-'Renovation Budget'!$C$18/'Renovation Budget'!$G$18,0) | F88: =IF(AND(F$11>=(12*(YEAR('Renovation Budget'!$F$18)-YEAR(Assumptions!$F$11))+(MONTH('Renovation Budget'!$F$18)-MONTH(Assumptions!$F$11))),F$11<=((12*(YEAR('Renovation Budget'!$F$18)-YEAR(Assumptions!$F$11))+(MONTH('Renovation Budget'!$F$18)-MONTH(Assumptions!$F$11)))+'Renovation Budget'!$G$18-1)),-'Renovation Budget'!$C$18/'Renovation Budget'!$G$18,0) | G88: =IF(AND(G$11>=(12*(YEAR('Renovation Budget'!$F$18)-YEAR(Assumptions!$F$11))+(MONTH('Renovation Budget'!$F$18)-MONTH(Assumptions!$F$11))),G$11<=((12*(YEAR('Renovation Budget'!$F$18)-YEAR(Assumptions!$F$11))+(MONTH('Renovation Budget'!$F$18)-MONTH(Assumptions!$F$11)))+'Renovation Budget'!$G$18-1)),-'Renovation Budget'!$C$18/'Renovation Budget'!$G$18,0) | H88: =IF(AND(H$11>=(12*(YEAR('Renovation Budget'!$F$18)-YEAR(Assumptions!$F$11))+(MONTH('Renovation Budget'!$F$18)-MONTH(Assumptions!$F$11))),H$11<=((12*(YEAR('Renovation Budget'!$F$18)-YEAR(Assumptions!$F$11))+(MONTH('Renovation Budget'!$F$18)-MONTH(Assumptions!$F$11)))+'Renovation Budget'!$G$18-1)),-'Renovation Budget'!$C$18/'Renovation Budget'!$G$18,0) | I88: =IF(AND(I$11>=(12*(YEAR('Renovation Budget'!$F$18)-YEAR(Assumptions!$F$11))+(MONTH('Renovation Budget'!$F$18)-MONTH(Assumptions!$F$11))),I$11<=((12*(YEAR('Renovation Budget'!$F$18)-YEAR(Assumptions!$F$11))+(MONTH('Renovation Budget'!$F$18)-MONTH(Assumptions!$F$11)))+'Renovation Budget'!$G$18-1)),-'Renovation Budget'!$C$18/'Renovation Budget'!$G$18,0) | J88: =IF(AND(J$11>=(12*(YEAR('Renovation Budget'!$F$18)-YEAR(Assumptions!$F$11))+(MONTH('Renovation Budget'!$F$18)-MONTH(Assumptions!$F$11))),J$11<=((12*(YEAR('Renovation Budget'!$F$18)-YEAR(Assumptions!$F$11))+(MONTH('Renovation Budget'!$F$18)-MONTH(Assumptions!$F$11)))+'Renovation Budget'!$G$18-1)),-'Renovation Budget'!$C$18/'Renovation Budget'!$G$18,0) | K88: =IF(AND(K$11>=(12*(YEAR('Renovation Budget'!$F$18)-YEAR(Assumptions!$F$11))+(MONTH('Renovation Budget'!$F$18)-MONTH(Assumptions!$F$11))),K$11<=((12*(YEAR('Renovation Budget'!$F$18)-YEAR(Assumptions!$F$11))+(MONTH('Renovation Budget'!$F$18)-MONTH(Assumptions!$F$11)))+'Renovation Budget'!$G$18-1)),-'Renovation Budget'!$C$18/'Renovation Budget'!$G$18,0) | ... DT88: =IF(AND(DT$11>=(12*(YEAR('Renovation Budget'!$F$18)-YEAR(Assumptions!$F$11))+(MONTH('Renovation Budget'!$F$18)-MONTH(Assumptions!$F$11))),DT$11<=((12*(YEAR('Renovation Budget'!$F$18)-YEAR(Assumptions!$F$11))+(MONTH('Renovation Budget'!$F$18)-MONTH(Assumptions!$F$11)))+'Renovation Budget'!$G$18-1)),-'Renovation Budget'!$C$18/'Renovation Budget'!$G$18,0)
A89: Equipment | C89: =SUM(D89:DT89) | D89: =IF(AND(D$11>=(12*(YEAR('Renovation Budget'!$F$19)-YEAR(Assumptions!$F$11))+(MONTH('Renovation Budget'!$F$19)-MONTH(Assumptions!$F$11))),D$11<=((12*(YEAR('Renovation Budget'!$F$19)-YEAR(Assumptions!$F$11))+(MONTH('Renovation Budget'!$F$19)-MONTH(Assumptions!$F$11)))+'Renovation Budget'!$G$19-1)),-'Renovation Budget'!$C$19/'Renovation Budget'!$G$19,0) | E89: =IF(AND(E$11>=(12*(YEAR('Renovation Budget'!$F$19)-YEAR(Assumptions!$F$11))+(MONTH('Renovation Budget'!$F$19)-MONTH(Assumptions!$F$11))),E$11<=((12*(YEAR('Renovation Budget'!$F$19)-YEAR(Assumptions!$F$11))+(MONTH('Renovation Budget'!$F$19)-MONTH(Assumptions!$F$11)))+'Renovation Budget'!$G$19-1)),-'Renovation Budget'!$C$19/'Renovation Budget'!$G$19,0) | F89: =IF(AND(F$11>=(12*(YEAR('Renovation Budget'!$F$19)-YEAR(Assumptions!$F$11))+(MONTH('Renovation Budget'!$F$19)-MONTH(Assumptions!$F$11))),F$11<=((12*(YEAR('Renovation Budget'!$F$19)-YEAR(Assumptions!$F$11))+(MONTH('Renovation Budget'!$F$19)-MONTH(Assumptions!$F$11)))+'Renovation Budget'!$G$19-1)),-'Renovation Budget'!$C$19/'Renovation Budget'!$G$19,0) | G89: =IF(AND(G$11>=(12*(YEAR('Renovation Budget'!$F$19)-YEAR(Assumptions!$F$11))+(MONTH('Renovation Budget'!$F$19)-MONTH(Assumptions!$F$11))),G$11<=((12*(YEAR('Renovation Budget'!$F$19)-YEAR(Assumptions!$F$11))+(MONTH('Renovation Budget'!$F$19)-MONTH(Assumptions!$F$11)))+'Renovation Budget'!$G$19-1)),-'Renovation Budget'!$C$19/'Renovation Budget'!$G$19,0) | H89: =IF(AND(H$11>=(12*(YEAR('Renovation Budget'!$F$19)-YEAR(Assumptions!$F$11))+(MONTH('Renovation Budget'!$F$19)-MONTH(Assumptions!$F$11))),H$11<=((12*(YEAR('Renovation Budget'!$F$19)-YEAR(Assumptions!$F$11))+(MONTH('Renovation Budget'!$F$19)-MONTH(Assumptions!$F$11)))+'Renovation Budget'!$G$19-1)),-'Renovation Budget'!$C$19/'Renovation Budget'!$G$19,0) | I89: =IF(AND(I$11>=(12*(YEAR('Renovation Budget'!$F$19)-YEAR(Assumptions!$F$11))+(MONTH('Renovation Budget'!$F$19)-MONTH(Assumptions!$F$11))),I$11<=((12*(YEAR('Renovation Budget'!$F$19)-YEAR(Assumptions!$F$11))+(MONTH('Renovation Budget'!$F$19)-MONTH(Assumptions!$F$11)))+'Renovation Budget'!$G$19-1)),-'Renovation Budget'!$C$19/'Renovation Budget'!$G$19,0) | J89: =IF(AND(J$11>=(12*(YEAR('Renovation Budget'!$F$19)-YEAR(Assumptions!$F$11))+(MONTH('Renovation Budget'!$F$19)-MONTH(Assumptions!$F$11))),J$11<=((12*(YEAR('Renovation Budget'!$F$19)-YEAR(Assumptions!$F$11))+(MONTH('Renovation Budget'!$F$19)-MONTH(Assumptions!$F$11)))+'Renovation Budget'!$G$19-1)),-'Renovation Budget'!$C$19/'Renovation Budget'!$G$19,0) | K89: =IF(AND(K$11>=(12*(YEAR('Renovation Budget'!$F$19)-YEAR(Assumptions!$F$11))+(MONTH('Renovation Budget'!$F$19)-MONTH(Assumptions!$F$11))),K$11<=((12*(YEAR('Renovation Budget'!$F$19)-YEAR(Assumptions!$F$11))+(MONTH('Renovation Budget'!$F$19)-MONTH(Assumptions!$F$11)))+'Renovation Budget'!$G$19-1)),-'Renovation Budget'!$C$19/'Renovation Budget'!$G$19,0) | ... DT89: =IF(AND(DT$11>=(12*(YEAR('Renovation Budget'!$F$19)-YEAR(Assumptions!$F$11))+(MONTH('Renovation Budget'!$F$19)-MONTH(Assumptions!$F$11))),DT$11<=((12*(YEAR('Renovation Budget'!$F$19)-YEAR(Assumptions!$F$11))+(MONTH('Renovation Budget'!$F$19)-MONTH(Assumptions!$F$11)))+'Renovation Budget'!$G$19-1)),-'Renovation Budget'!$C$19/'Renovation Budget'!$G$19,0)
A90: Furnishings | C90: =SUM(D90:DT90) | D90: =IF(AND(D$11>=(12*(YEAR('Renovation Budget'!$F$20)-YEAR(Assumptions!$F$11))+(MONTH('Renovation Budget'!$F$20)-MONTH(Assumptions!$F$11))),D$11<=((12*(YEAR('Renovation Budget'!$F$20)-YEAR(Assumptions!$F$11))+(MONTH('Renovation Budget'!$F$20)-MONTH(Assumptions!$F$11)))+'Renovation Budget'!$G$20-1)),-'Renovation Budget'!$C$20/'Renovation Budget'!$G$20,0) | E90: =IF(AND(E$11>=(12*(YEAR('Renovation Budget'!$F$20)-YEAR(Assumptions!$F$11))+(MONTH('Renovation Budget'!$F$20)-MONTH(Assumptions!$F$11))),E$11<=((12*(YEAR('Renovation Budget'!$F$20)-YEAR(Assumptions!$F$11))+(MONTH('Renovation Budget'!$F$20)-MONTH(Assumptions!$F$11)))+'Renovation Budget'!$G$20-1)),-'Renovation Budget'!$C$20/'Renovation Budget'!$G$20,0) | F90: =IF(AND(F$11>=(12*(YEAR('Renovation Budget'!$F$20)-YEAR(Assumptions!$F$11))+(MONTH('Renovation Budget'!$F$20)-MONTH(Assumptions!$F$11))),F$11<=((12*(YEAR('Renovation Budget'!$F$20)-YEAR(Assumptions!$F$11))+(MONTH('Renovation Budget'!$F$20)-MONTH(Assumptions!$F$11)))+'Renovation Budget'!$G$20-1)),-'Renovation Budget'!$C$20/'Renovation Budget'!$G$20,0) | G90: =IF(AND(G$11>=(12*(YEAR('Renovation Budget'!$F$20)-YEAR(Assumptions!$F$11))+(MONTH('Renovation Budget'!$F$20)-MONTH(Assumptions!$F$11))),G$11<=((12*(YEAR('Renovation Budget'!$F$20)-YEAR(Assumptions!$F$11))+(MONTH('Renovation Budget'!$F$20)-MONTH(Assumptions!$F$11)))+'Renovation Budget'!$G$20-1)),-'Renovation Budget'!$C$20/'Renovation Budget'!$G$20,0) | H90: =IF(AND(H$11>=(12*(YEAR('Renovation Budget'!$F$20)-YEAR(Assumptions!$F$11))+(MONTH('Renovation Budget'!$F$20)-MONTH(Assumptions!$F$11))),H$11<=((12*(YEAR('Renovation Budget'!$F$20)-YEAR(Assumptions!$F$11))+(MONTH('Renovation Budget'!$F$20)-MONTH(Assumptions!$F$11)))+'Renovation Budget'!$G$20-1)),-'Renovation Budget'!$C$20/'Renovation Budget'!$G$20,0) | I90: =IF(AND(I$11>=(12*(YEAR('Renovation Budget'!$F$20)-YEAR(Assumptions!$F$11))+(MONTH('Renovation Budget'!$F$20)-MONTH(Assumptions!$F$11))),I$11<=((12*(YEAR('Renovation Budget'!$F$20)-YEAR(Assumptions!$F$11))+(MONTH('Renovation Budget'!$F$20)-MONTH(Assumptions!$F$11)))+'Renovation Budget'!$G$20-1)),-'Renovation Budget'!$C$20/'Renovation Budget'!$G$20,0) | J90: =IF(AND(J$11>=(12*(YEAR('Renovation Budget'!$F$20)-YEAR(Assumptions!$F$11))+(MONTH('Renovation Budget'!$F$20)-MONTH(Assumptions!$F$11))),J$11<=((12*(YEAR('Renovation Budget'!$F$20)-YEAR(Assumptions!$F$11))+(MONTH('Renovation Budget'!$F$20)-MONTH(Assumptions!$F$11)))+'Renovation Budget'!$G$20-1)),-'Renovation Budget'!$C$20/'Renovation Budget'!$G$20,0) | K90: =IF(AND(K$11>=(12*(YEAR('Renovation Budget'!$F$20)-YEAR(Assumptions!$F$11))+(MONTH('Renovation Budget'!$F$20)-MONTH(Assumptions!$F$11))),K$11<=((12*(YEAR('Renovation Budget'!$F$20)-YEAR(Assumptions!$F$11))+(MONTH('Renovation Budget'!$F$20)-MONTH(Assumptions!$F$11)))+'Renovation Budget'!$G$20-1)),-'Renovation Budget'!$C$20/'Renovation Budget'!$G$20,0) | ... DT90: =IF(AND(DT$11>=(12*(YEAR('Renovation Budget'!$F$20)-YEAR(Assumptions!$F$11))+(MONTH('Renovation Budget'!$F$20)-MONTH(Assumptions!$F$11))),DT$11<=((12*(YEAR('Renovation Budget'!$F$20)-YEAR(Assumptions!$F$11))+(MONTH('Renovation Budget'!$F$20)-MONTH(Assumptions!$F$11)))+'Renovation Budget'!$G$20-1)),-'Renovation Budget'!$C$20/'Renovation Budget'!$G$20,0)
A91: Hard Cost Contingency | C91: =SUM(D91:DT91) | D91: =IF(AND(D$11>=(12*(YEAR('Renovation Budget'!$F$21)-YEAR(Assumptions!$F$11))+(MONTH('Renovation Budget'!$F$21)-MONTH(Assumptions!$F$11))),D$11<=((12*(YEAR('Renovation Budget'!$F$21)-YEAR(Assumptions!$F$11))+(MONTH('Renovation Budget'!$F$21)-MONTH(Assumptions!$F$11)))+'Renovation Budget'!$G$21-1)),-'Renovation Budget'!$C$21/'Renovation Budget'!$G$21,0) | E91: =IF(AND(E$11>=(12*(YEAR('Renovation Budget'!$F$21)-YEAR(Assumptions!$F$11))+(MONTH('Renovation Budget'!$F$21)-MONTH(Assumptions!$F$11))),E$11<=((12*(YEAR('Renovation Budget'!$F$21)-YEAR(Assumptions!$F$11))+(MONTH('Renovation Budget'!$F$21)-MONTH(Assumptions!$F$11)))+'Renovation Budget'!$G$21-1)),-'Renovation Budget'!$C$21/'Renovation Budget'!$G$21,0) | F91: =IF(AND(F$11>=(12*(YEAR('Renovation Budget'!$F$21)-YEAR(Assumptions!$F$11))+(MONTH('Renovation Budget'!$F$21)-MONTH(Assumptions!$F$11))),F$11<=((12*(YEAR('Renovation Budget'!$F$21)-YEAR(Assumptions!$F$11))+(MONTH('Renovation Budget'!$F$21)-MONTH(Assumptions!$F$11)))+'Renovation Budget'!$G$21-1)),-'Renovation Budget'!$C$21/'Renovation Budget'!$G$21,0) | G91: =IF(AND(G$11>=(12*(YEAR('Renovation Budget'!$F$21)-YEAR(Assumptions!$F$11))+(MONTH('Renovation Budget'!$F$21)-MONTH(Assumptions!$F$11))),G$11<=((12*(YEAR('Renovation Budget'!$F$21)-YEAR(Assumptions!$F$11))+(MONTH('Renovation Budget'!$F$21)-MONTH(Assumptions!$F$11)))+'Renovation Budget'!$G$21-1)),-'Renovation Budget'!$C$21/'Renovation Budget'!$G$21,0) | H91: =IF(AND(H$11>=(12*(YEAR('Renovation Budget'!$F$21)-YEAR(Assumptions!$F$11))+(MONTH('Renovation Budget'!$F$21)-MONTH(Assumptions!$F$11))),H$11<=((12*(YEAR('Renovation Budget'!$F$21)-YEAR(Assumptions!$F$11))+(MONTH('Renovation Budget'!$F$21)-MONTH(Assumptions!$F$11)))+'Renovation Budget'!$G$21-1)),-'Renovation Budget'!$C$21/'Renovation Budget'!$G$21,0) | I91: =IF(AND(I$11>=(12*(YEAR('Renovation Budget'!$F$21)-YEAR(Assumptions!$F$11))+(MONTH('Renovation Budget'!$F$21)-MONTH(Assumptions!$F$11))),I$11<=((12*(YEAR('Renovation Budget'!$F$21)-YEAR(Assumptions!$F$11))+(MONTH('Renovation Budget'!$F$21)-MONTH(Assumptions!$F$11)))+'Renovation Budget'!$G$21-1)),-'Renovation Budget'!$C$21/'Renovation Budget'!$G$21,0) | J91: =IF(AND(J$11>=(12*(YEAR('Renovation Budget'!$F$21)-YEAR(Assumptions!$F$11))+(MONTH('Renovation Budget'!$F$21)-MONTH(Assumptions!$F$11))),J$11<=((12*(YEAR('Renovation Budget'!$F$21)-YEAR(Assumptions!$F$11))+(MONTH('Renovation Budget'!$F$21)-MONTH(Assumptions!$F$11)))+'Renovation Budget'!$G$21-1)),-'Renovation Budget'!$C$21/'Renovation Budget'!$G$21,0) | K91: =IF(AND(K$11>=(12*(YEAR('Renovation Budget'!$F$21)-YEAR(Assumptions!$F$11))+(MONTH('Renovation Budget'!$F$21)-MONTH(Assumptions!$F$11))),K$11<=((12*(YEAR('Renovation Budget'!$F$21)-YEAR(Assumptions!$F$11))+(MONTH('Renovation Budget'!$F$21)-MONTH(Assumptions!$F$11)))+'Renovation Budget'!$G$21-1)),-'Renovation Budget'!$C$21/'Renovation Budget'!$G$21,0) | ... DT91: =IF(AND(DT$11>=(12*(YEAR('Renovation Budget'!$F$21)-YEAR(Assumptions!$F$11))+(MONTH('Renovation Budget'!$F$21)-MONTH(Assumptions!$F$11))),DT$11<=((12*(YEAR('Renovation Budget'!$F$21)-YEAR(Assumptions!$F$11))+(MONTH('Renovation Budget'!$F$21)-MONTH(Assumptions!$F$11)))+'Renovation Budget'!$G$21-1)),-'Renovation Budget'!$C$21/'Renovation Budget'!$G$21,0)
A92: Preliminary Renovation Costs | C92: =SUM(D92:DT92) | D92: =IF(AND(D$11>=(12*(YEAR('Renovation Budget'!$F$22)-YEAR(Assumptions!$F$11))+(MONTH('Renovation Budget'!$F$22)-MONTH(Assumptions!$F$11))),D$11<=((12*(YEAR('Renovation Budget'!$F$22)-YEAR(Assumptions!$F$11))+(MONTH('Renovation Budget'!$F$22)-MONTH(Assumptions!$F$11)))+'Renovation Budget'!$G$22-1)),-'Renovation Budget'!$C$22/'Renovation Budget'!$G$22,0) | E92: =IF(AND(E$11>=(12*(YEAR('Renovation Budget'!$F$22)-YEAR(Assumptions!$F$11))+(MONTH('Renovation Budget'!$F$22)-MONTH(Assumptions!$F$11))),E$11<=((12*(YEAR('Renovation Budget'!$F$22)-YEAR(Assumptions!$F$11))+(MONTH('Renovation Budget'!$F$22)-MONTH(Assumptions!$F$11)))+'Renovation Budget'!$G$22-1)),-'Renovation Budget'!$C$22/'Renovation Budget'!$G$22,0) | F92: =IF(AND(F$11>=(12*(YEAR('Renovation Budget'!$F$22)-YEAR(Assumptions!$F$11))+(MONTH('Renovation Budget'!$F$22)-MONTH(Assumptions!$F$11))),F$11<=((12*(YEAR('Renovation Budget'!$F$22)-YEAR(Assumptions!$F$11))+(MONTH('Renovation Budget'!$F$22)-MONTH(Assumptions!$F$11)))+'Renovation Budget'!$G$22-1)),-'Renovation Budget'!$C$22/'Renovation Budget'!$G$22,0) | G92: =IF(AND(G$11>=(12*(YEAR('Renovation Budget'!$F$22)-YEAR(Assumptions!$F$11))+(MONTH('Renovation Budget'!$F$22)-MONTH(Assumptions!$F$11))),G$11<=((12*(YEAR('Renovation Budget'!$F$22)-YEAR(Assumptions!$F$11))+(MONTH('Renovation Budget'!$F$22)-MONTH(Assumptions!$F$11)))+'Renovation Budget'!$G$22-1)),-'Renovation Budget'!$C$22/'Renovation Budget'!$G$22,0) | H92: =IF(AND(H$11>=(12*(YEAR('Renovation Budget'!$F$22)-YEAR(Assumptions!$F$11))+(MONTH('Renovation Budget'!$F$22)-MONTH(Assumptions!$F$11))),H$11<=((12*(YEAR('Renovation Budget'!$F$22)-YEAR(Assumptions!$F$11))+(MONTH('Renovation Budget'!$F$22)-MONTH(Assumptions!$F$11)))+'Renovation Budget'!$G$22-1)),-'Renovation Budget'!$C$22/'Renovation Budget'!$G$22,0) | I92: =IF(AND(I$11>=(12*(YEAR('Renovation Budget'!$F$22)-YEAR(Assumptions!$F$11))+(MONTH('Renovation Budget'!$F$22)-MONTH(Assumptions!$F$11))),I$11<=((12*(YEAR('Renovation Budget'!$F$22)-YEAR(Assumptions!$F$11))+(MONTH('Renovation Budget'!$F$22)-MONTH(Assumptions!$F$11)))+'Renovation Budget'!$G$22-1)),-'Renovation Budget'!$C$22/'Renovation Budget'!$G$22,0) | J92: =IF(AND(J$11>=(12*(YEAR('Renovation Budget'!$F$22)-YEAR(Assumptions!$F$11))+(MONTH('Renovation Budget'!$F$22)-MONTH(Assumptions!$F$11))),J$11<=((12*(YEAR('Renovation Budget'!$F$22)-YEAR(Assumptions!$F$11))+(MONTH('Renovation Budget'!$F$22)-MONTH(Assumptions!$F$11)))+'Renovation Budget'!$G$22-1)),-'Renovation Budget'!$C$22/'Renovation Budget'!$G$22,0) | K92: =IF(AND(K$11>=(12*(YEAR('Renovation Budget'!$F$22)-YEAR(Assumptions!$F$11))+(MONTH('Renovation Budget'!$F$22)-MONTH(Assumptions!$F$11))),K$11<=((12*(YEAR('Renovation Budget'!$F$22)-YEAR(Assumptions!$F$11))+(MONTH('Renovation Budget'!$F$22)-MONTH(Assumptions!$F$11)))+'Renovation Budget'!$G$22-1)),-'Renovation Budget'!$C$22/'Renovation Budget'!$G$22,0) | ... DT92: =IF(AND(DT$11>=(12*(YEAR('Renovation Budget'!$F$22)-YEAR(Assumptions!$F$11))+(MONTH('Renovation Budget'!$F$22)-MONTH(Assumptions!$F$11))),DT$11<=((12*(YEAR('Renovation Budget'!$F$22)-YEAR(Assumptions!$F$11))+(MONTH('Renovation Budget'!$F$22)-MONTH(Assumptions!$F$11)))+'Renovation Budget'!$G$22-1)),-'Renovation Budget'!$C$22/'Renovation Budget'!$G$22,0)
A93: Subtotal: Hard Costs | C93: =SUM(D93:DT93) | D93: =SUM(D$79:D$92) | E93: =SUM(E$79:E$92) | F93: =SUM(F$79:F$92) | G93: =SUM(G$79:G$92) | H93: =SUM(H$79:H$92) | I93: =SUM(I$79:I$92) | J93: =SUM(J$79:J$92) | K93: =SUM(K$79:K$92) | ... DT93: =SUM(DT$79:DT$92)
A95: Soft Costs | C95: =SUM(D95:DT95)
A96: Acquisition Management Fee | C96: =SUM(D96:DT96) | D96: =IF(AND(D$11>=(12*(YEAR('Renovation Budget'!$F$27)-YEAR(Assumptions!$F$11))+(MONTH('Renovation Budget'!$F$27)-MONTH(Assumptions!$F$11))),D$11<=((12*(YEAR('Renovation Budget'!$F$27)-YEAR(Assumptions!$F$11))+(MONTH('Renovation Budget'!$F$27)-MONTH(Assumptions!$F$11)))+'Renovation Budget'!$G$27-1)),-'Renovation Budget'!$C$27/'Renovation Budget'!$G$27,0) | E96: =IF(AND(E$11>=(12*(YEAR('Renovation Budget'!$F$27)-YEAR(Assumptions!$F$11))+(MONTH('Renovation Budget'!$F$27)-MONTH(Assumptions!$F$11))),E$11<=((12*(YEAR('Renovation Budget'!$F$27)-YEAR(Assumptions!$F$11))+(MONTH('Renovation Budget'!$F$27)-MONTH(Assumptions!$F$11)))+'Renovation Budget'!$G$27-1)),-'Renovation Budget'!$C$27/'Renovation Budget'!$G$27,0) | F96: =IF(AND(F$11>=(12*(YEAR('Renovation Budget'!$F$27)-YEAR(Assumptions!$F$11))+(MONTH('Renovation Budget'!$F$27)-MONTH(Assumptions!$F$11))),F$11<=((12*(YEAR('Renovation Budget'!$F$27)-YEAR(Assumptions!$F$11))+(MONTH('Renovation Budget'!$F$27)-MONTH(Assumptions!$F$11)))+'Renovation Budget'!$G$27-1)),-'Renovation Budget'!$C$27/'Renovation Budget'!$G$27,0) | G96: =IF(AND(G$11>=(12*(YEAR('Renovation Budget'!$F$27)-YEAR(Assumptions!$F$11))+(MONTH('Renovation Budget'!$F$27)-MONTH(Assumptions!$F$11))),G$11<=((12*(YEAR('Renovation Budget'!$F$27)-YEAR(Assumptions!$F$11))+(MONTH('Renovation Budget'!$F$27)-MONTH(Assumptions!$F$11)))+'Renovation Budget'!$G$27-1)),-'Renovation Budget'!$C$27/'Renovation Budget'!$G$27,0) | H96: =IF(AND(H$11>=(12*(YEAR('Renovation Budget'!$F$27)-YEAR(Assumptions!$F$11))+(MONTH('Renovation Budget'!$F$27)-MONTH(Assumptions!$F$11))),H$11<=((12*(YEAR('Renovation Budget'!$F$27)-YEAR(Assumptions!$F$11))+(MONTH('Renovation Budget'!$F$27)-MONTH(Assumptions!$F$11)))+'Renovation Budget'!$G$27-1)),-'Renovation Budget'!$C$27/'Renovation Budget'!$G$27,0) | I96: =IF(AND(I$11>=(12*(YEAR('Renovation Budget'!$F$27)-YEAR(Assumptions!$F$11))+(MONTH('Renovation Budget'!$F$27)-MONTH(Assumptions!$F$11))),I$11<=((12*(YEAR('Renovation Budget'!$F$27)-YEAR(Assumptions!$F$11))+(MONTH('Renovation Budget'!$F$27)-MONTH(Assumptions!$F$11)))+'Renovation Budget'!$G$27-1)),-'Renovation Budget'!$C$27/'Renovation Budget'!$G$27,0) | J96: =IF(AND(J$11>=(12*(YEAR('Renovation Budget'!$F$27)-YEAR(Assumptions!$F$11))+(MONTH('Renovation Budget'!$F$27)-MONTH(Assumptions!$F$11))),J$11<=((12*(YEAR('Renovation Budget'!$F$27)-YEAR(Assumptions!$F$11))+(MONTH('Renovation Budget'!$F$27)-MONTH(Assumptions!$F$11)))+'Renovation Budget'!$G$27-1)),-'Renovation Budget'!$C$27/'Renovation Budget'!$G$27,0) | K96: =IF(AND(K$11>=(12*(YEAR('Renovation Budget'!$F$27)-YEAR(Assumptions!$F$11))+(MONTH('Renovation Budget'!$F$27)-MONTH(Assumptions!$F$11))),K$11<=((12*(YEAR('Renovation Budget'!$F$27)-YEAR(Assumptions!$F$11))+(MONTH('Renovation Budget'!$F$27)-MONTH(Assumptions!$F$11)))+'Renovation Budget'!$G$27-1)),-'Renovation Budget'!$C$27/'Renovation Budget'!$G$27,0) | ... DT96: =IF(AND(DT$11>=(12*(YEAR('Renovation Budget'!$F$27)-YEAR(Assumptions!$F$11))+(MONTH('Renovation Budget'!$F$27)-MONTH(Assumptions!$F$11))),DT$11<=((12*(YEAR('Renovation Budget'!$F$27)-YEAR(Assumptions!$F$11))+(MONTH('Renovation Budget'!$F$27)-MONTH(Assumptions!$F$11)))+'Renovation Budget'!$G$27-1)),-'Renovation Budget'!$C$27/'Renovation Budget'!$G$27,0)
A97: Bury Power Lines (Austin Energy) | C97: =SUM(D97:DT97) | D97: =IF(AND(D$11>=(12*(YEAR('Renovation Budget'!$F$28)-YEAR(Assumptions!$F$11))+(MONTH('Renovation Budget'!$F$28)-MONTH(Assumptions!$F$11))),D$11<=((12*(YEAR('Renovation Budget'!$F$28)-YEAR(Assumptions!$F$11))+(MONTH('Renovation Budget'!$F$28)-MONTH(Assumptions!$F$11)))+'Renovation Budget'!$G$28-1)),-'Renovation Budget'!$C$28/'Renovation Budget'!$G$28,0) | E97: =IF(AND(E$11>=(12*(YEAR('Renovation Budget'!$F$28)-YEAR(Assumptions!$F$11))+(MONTH('Renovation Budget'!$F$28)-MONTH(Assumptions!$F$11))),E$11<=((12*(YEAR('Renovation Budget'!$F$28)-YEAR(Assumptions!$F$11))+(MONTH('Renovation Budget'!$F$28)-MONTH(Assumptions!$F$11)))+'Renovation Budget'!$G$28-1)),-'Renovation Budget'!$C$28/'Renovation Budget'!$G$28,0) | F97: =IF(AND(F$11>=(12*(YEAR('Renovation Budget'!$F$28)-YEAR(Assumptions!$F$11))+(MONTH('Renovation Budget'!$F$28)-MONTH(Assumptions!$F$11))),F$11<=((12*(YEAR('Renovation Budget'!$F$28)-YEAR(Assumptions!$F$11))+(MONTH('Renovation Budget'!$F$28)-MONTH(Assumptions!$F$11)))+'Renovation Budget'!$G$28-1)),-'Renovation Budget'!$C$28/'Renovation Budget'!$G$28,0) | G97: =IF(AND(G$11>=(12*(YEAR('Renovation Budget'!$F$28)-YEAR(Assumptions!$F$11))+(MONTH('Renovation Budget'!$F$28)-MONTH(Assumptions!$F$11))),G$11<=((12*(YEAR('Renovation Budget'!$F$28)-YEAR(Assumptions!$F$11))+(MONTH('Renovation Budget'!$F$28)-MONTH(Assumptions!$F$11)))+'Renovation Budget'!$G$28-1)),-'Renovation Budget'!$C$28/'Renovation Budget'!$G$28,0) | H97: =IF(AND(H$11>=(12*(YEAR('Renovation Budget'!$F$28)-YEAR(Assumptions!$F$11))+(MONTH('Renovation Budget'!$F$28)-MONTH(Assumptions!$F$11))),H$11<=((12*(YEAR('Renovation Budget'!$F$28)-YEAR(Assumptions!$F$11))+(MONTH('Renovation Budget'!$F$28)-MONTH(Assumptions!$F$11)))+'Renovation Budget'!$G$28-1)),-'Renovation Budget'!$C$28/'Renovation Budget'!$G$28,0) | I97: =IF(AND(I$11>=(12*(YEAR('Renovation Budget'!$F$28)-YEAR(Assumptions!$F$11))+(MONTH('Renovation Budget'!$F$28)-MONTH(Assumptions!$F$11))),I$11<=((12*(YEAR('Renovation Budget'!$F$28)-YEAR(Assumptions!$F$11))+(MONTH('Renovation Budget'!$F$28)-MONTH(Assumptions!$F$11)))+'Renovation Budget'!$G$28-1)),-'Renovation Budget'!$C$28/'Renovation Budget'!$G$28,0) | J97: =IF(AND(J$11>=(12*(YEAR('Renovation Budget'!$F$28)-YEAR(Assumptions!$F$11))+(MONTH('Renovation Budget'!$F$28)-MONTH(Assumptions!$F$11))),J$11<=((12*(YEAR('Renovation Budget'!$F$28)-YEAR(Assumptions!$F$11))+(MONTH('Renovation Budget'!$F$28)-MONTH(Assumptions!$F$11)))+'Renovation Budget'!$G$28-1)),-'Renovation Budget'!$C$28/'Renovation Budget'!$G$28,0) | K97: =IF(AND(K$11>=(12*(YEAR('Renovation Budget'!$F$28)-YEAR(Assumptions!$F$11))+(MONTH('Renovation Budget'!$F$28)-MONTH(Assumptions!$F$11))),K$11<=((12*(YEAR('Renovation Budget'!$F$28)-YEAR(Assumptions!$F$11))+(MONTH('Renovation Budget'!$F$28)-MONTH(Assumptions!$F$11)))+'Renovation Budget'!$G$28-1)),-'Renovation Budget'!$C$28/'Renovation Budget'!$G$28,0) | ... DT97: =IF(AND(DT$11>=(12*(YEAR('Renovation Budget'!$F$28)-YEAR(Assumptions!$F$11))+(MONTH('Renovation Budget'!$F$28)-MONTH(Assumptions!$F$11))),DT$11<=((12*(YEAR('Renovation Budget'!$F$28)-YEAR(Assumptions!$F$11))+(MONTH('Renovation Budget'!$F$28)-MONTH(Assumptions!$F$11)))+'Renovation Budget'!$G$28-1)),-'Renovation Budget'!$C$28/'Renovation Budget'!$G$28,0)
A98: Soft Cost Contingency | C98: =SUM(D98:DT98) | D98: =IF(AND(D$11>=(12*(YEAR('Renovation Budget'!$F$29)-YEAR(Assumptions!$F$11))+(MONTH('Renovation Budget'!$F$29)-MONTH(Assumptions!$F$11))),D$11<=((12*(YEAR('Renovation Budget'!$F$29)-YEAR(Assumptions!$F$11))+(MONTH('Renovation Budget'!$F$29)-MONTH(Assumptions!$F$11)))+'Renovation Budget'!$G$29-1)),-'Renovation Budget'!$C$29/'Renovation Budget'!$G$29,0) | E98: =IF(AND(E$11>=(12*(YEAR('Renovation Budget'!$F$29)-YEAR(Assumptions!$F$11))+(MONTH('Renovation Budget'!$F$29)-MONTH(Assumptions!$F$11))),E$11<=((12*(YEAR('Renovation Budget'!$F$29)-YEAR(Assumptions!$F$11))+(MONTH('Renovation Budget'!$F$29)-MONTH(Assumptions!$F$11)))+'Renovation Budget'!$G$29-1)),-'Renovation Budget'!$C$29/'Renovation Budget'!$G$29,0) | F98: =IF(AND(F$11>=(12*(YEAR('Renovation Budget'!$F$29)-YEAR(Assumptions!$F$11))+(MONTH('Renovation Budget'!$F$29)-MONTH(Assumptions!$F$11))),F$11<=((12*(YEAR('Renovation Budget'!$F$29)-YEAR(Assumptions!$F$11))+(MONTH('Renovation Budget'!$F$29)-MONTH(Assumptions!$F$11)))+'Renovation Budget'!$G$29-1)),-'Renovation Budget'!$C$29/'Renovation Budget'!$G$29,0) | G98: =IF(AND(G$11>=(12*(YEAR('Renovation Budget'!$F$29)-YEAR(Assumptions!$F$11))+(MONTH('Renovation Budget'!$F$29)-MONTH(Assumptions!$F$11))),G$11<=((12*(YEAR('Renovation Budget'!$F$29)-YEAR(Assumptions!$F$11))+(MONTH('Renovation Budget'!$F$29)-MONTH(Assumptions!$F$11)))+'Renovation Budget'!$G$29-1)),-'Renovation Budget'!$C$29/'Renovation Budget'!$G$29,0) | H98: =IF(AND(H$11>=(12*(YEAR('Renovation Budget'!$F$29)-YEAR(Assumptions!$F$11))+(MONTH('Renovation Budget'!$F$29)-MONTH(Assumptions!$F$11))),H$11<=((12*(YEAR('Renovation Budget'!$F$29)-YEAR(Assumptions!$F$11))+(MONTH('Renovation Budget'!$F$29)-MONTH(Assumptions!$F$11)))+'Renovation Budget'!$G$29-1)),-'Renovation Budget'!$C$29/'Renovation Budget'!$G$29,0) | I98: =IF(AND(I$11>=(12*(YEAR('Renovation Budget'!$F$29)-YEAR(Assumptions!$F$11))+(MONTH('Renovation Budget'!$F$29)-MONTH(Assumptions!$F$11))),I$11<=((12*(YEAR('Renovation Budget'!$F$29)-YEAR(Assumptions!$F$11))+(MONTH('Renovation Budget'!$F$29)-MONTH(Assumptions!$F$11)))+'Renovation Budget'!$G$29-1)),-'Renovation Budget'!$C$29/'Renovation Budget'!$G$29,0) | J98: =IF(AND(J$11>=(12*(YEAR('Renovation Budget'!$F$29)-YEAR(Assumptions!$F$11))+(MONTH('Renovation Budget'!$F$29)-MONTH(Assumptions!$F$11))),J$11<=((12*(YEAR('Renovation Budget'!$F$29)-YEAR(Assumptions!$F$11))+(MONTH('Renovation Budget'!$F$29)-MONTH(Assumptions!$F$11)))+'Renovation Budget'!$G$29-1)),-'Renovation Budget'!$C$29/'Renovation Budget'!$G$29,0) | K98: =IF(AND(K$11>=(12*(YEAR('Renovation Budget'!$F$29)-YEAR(Assumptions!$F$11))+(MONTH('Renovation Budget'!$F$29)-MONTH(Assumptions!$F$11))),K$11<=((12*(YEAR('Renovation Budget'!$F$29)-YEAR(Assumptions!$F$11))+(MONTH('Renovation Budget'!$F$29)-MONTH(Assumptions!$F$11)))+'Renovation Budget'!$G$29-1)),-'Renovation Budget'!$C$29/'Renovation Budget'!$G$29,0) | ... DT98: =IF(AND(DT$11>=(12*(YEAR('Renovation Budget'!$F$29)-YEAR(Assumptions!$F$11))+(MONTH('Renovation Budget'!$F$29)-MONTH(Assumptions!$F$11))),DT$11<=((12*(YEAR('Renovation Budget'!$F$29)-YEAR(Assumptions!$F$11))+(MONTH('Renovation Budget'!$F$29)-MONTH(Assumptions!$F$11)))+'Renovation Budget'!$G$29-1)),-'Renovation Budget'!$C$29/'Renovation Budget'!$G$29,0)
A99: Preliminary Soft Costs | C99: =SUM(D99:DT99) | D99: =IF(AND(D$11>=(12*(YEAR('Renovation Budget'!$F$30)-YEAR(Assumptions!$F$11))+(MONTH('Renovation Budget'!$F$30)-MONTH(Assumptions!$F$11))),D$11<=((12*(YEAR('Renovation Budget'!$F$30)-YEAR(Assumptions!$F$11))+(MONTH('Renovation Budget'!$F$30)-MONTH(Assumptions!$F$11)))+'Renovation Budget'!$G$30-1)),-'Renovation Budget'!$C$30/'Renovation Budget'!$G$30,0) | E99: =IF(AND(E$11>=(12*(YEAR('Renovation Budget'!$F$30)-YEAR(Assumptions!$F$11))+(MONTH('Renovation Budget'!$F$30)-MONTH(Assumptions!$F$11))),E$11<=((12*(YEAR('Renovation Budget'!$F$30)-YEAR(Assumptions!$F$11))+(MONTH('Renovation Budget'!$F$30)-MONTH(Assumptions!$F$11)))+'Renovation Budget'!$G$30-1)),-'Renovation Budget'!$C$30/'Renovation Budget'!$G$30,0) | F99: =IF(AND(F$11>=(12*(YEAR('Renovation Budget'!$F$30)-YEAR(Assumptions!$F$11))+(MONTH('Renovation Budget'!$F$30)-MONTH(Assumptions!$F$11))),F$11<=((12*(YEAR('Renovation Budget'!$F$30)-YEAR(Assumptions!$F$11))+(MONTH('Renovation Budget'!$F$30)-MONTH(Assumptions!$F$11)))+'Renovation Budget'!$G$30-1)),-'Renovation Budget'!$C$30/'Renovation Budget'!$G$30,0) | G99: =IF(AND(G$11>=(12*(YEAR('Renovation Budget'!$F$30)-YEAR(Assumptions!$F$11))+(MONTH('Renovation Budget'!$F$30)-MONTH(Assumptions!$F$11))),G$11<=((12*(YEAR('Renovation Budget'!$F$30)-YEAR(Assumptions!$F$11))+(MONTH('Renovation Budget'!$F$30)-MONTH(Assumptions!$F$11)))+'Renovation Budget'!$G$30-1)),-'Renovation Budget'!$C$30/'Renovation Budget'!$G$30,0) | H99: =IF(AND(H$11>=(12*(YEAR('Renovation Budget'!$F$30)-YEAR(Assumptions!$F$11))+(MONTH('Renovation Budget'!$F$30)-MONTH(Assumptions!$F$11))),H$11<=((12*(YEAR('Renovation Budget'!$F$30)-YEAR(Assumptions!$F$11))+(MONTH('Renovation Budget'!$F$30)-MONTH(Assumptions!$F$11)))+'Renovation Budget'!$G$30-1)),-'Renovation Budget'!$C$30/'Renovation Budget'!$G$30,0) | I99: =IF(AND(I$11>=(12*(YEAR('Renovation Budget'!$F$30)-YEAR(Assumptions!$F$11))+(MONTH('Renovation Budget'!$F$30)-MONTH(Assumptions!$F$11))),I$11<=((12*(YEAR('Renovation Budget'!$F$30)-YEAR(Assumptions!$F$11))+(MONTH('Renovation Budget'!$F$30)-MONTH(Assumptions!$F$11)))+'Renovation Budget'!$G$30-1)),-'Renovation Budget'!$C$30/'Renovation Budget'!$G$30,0) | J99: =IF(AND(J$11>=(12*(YEAR('Renovation Budget'!$F$30)-YEAR(Assumptions!$F$11))+(MONTH('Renovation Budget'!$F$30)-MONTH(Assumptions!$F$11))),J$11<=((12*(YEAR('Renovation Budget'!$F$30)-YEAR(Assumptions!$F$11))+(MONTH('Renovation Budget'!$F$30)-MONTH(Assumptions!$F$11)))+'Renovation Budget'!$G$30-1)),-'Renovation Budget'!$C$30/'Renovation Budget'!$G$30,0) | K99: =IF(AND(K$11>=(12*(YEAR('Renovation Budget'!$F$30)-YEAR(Assumptions!$F$11))+(MONTH('Renovation Budget'!$F$30)-MONTH(Assumptions!$F$11))),K$11<=((12*(YEAR('Renovation Budget'!$F$30)-YEAR(Assumptions!$F$11))+(MONTH('Renovation Budget'!$F$30)-MONTH(Assumptions!$F$11)))+'Renovation Budget'!$G$30-1)),-'Renovation Budget'!$C$30/'Renovation Budget'!$G$30,0) | ... DT99: =IF(AND(DT$11>=(12*(YEAR('Renovation Budget'!$F$30)-YEAR(Assumptions!$F$11))+(MONTH('Renovation Budget'!$F$30)-MONTH(Assumptions!$F$11))),DT$11<=((12*(YEAR('Renovation Budget'!$F$30)-YEAR(Assumptions!$F$11))+(MONTH('Renovation Budget'!$F$30)-MONTH(Assumptions!$F$11)))+'Renovation Budget'!$G$30-1)),-'Renovation Budget'!$C$30/'Renovation Budget'!$G$30,0)
